Workbook

Sheet README
A1: ERP vehicle project costing — dated cost lines
A3: CONTROLS — edit the yellow cells; every sheet follows
A4: As-of date | B4: 46234 | C4: drives the 'Active' flag on CostLines and the 'Active' column on ByVehicle
A5: Calendar year | B5: 2026 | C5: drives the 'In calendar year' flag on CostLines
A6: Financial year | B6: 2026-27 | C6: drives every FY column on ByVehicle. Financial years present: 2024-25, 2025-26, 2026-27
A9: Source | B9: POST http://172.16.10.169:8089/api/general/VehicleEmpMapProjectDetails (body {}, Content-Type: application/json)
A10: Pulled | B10: 1,054 rows, all Project_Type = VEHICLE
A11: Vehicles | B11: 64 distinct
A12: Cost heads | B12: 7 Proj_Activity_Name values / 33 Description values
A13: Period covered | B13: 01-04-2024 to 31-03-2027 (2024-25, 2025-26, 2026-27)
A14: Total Pur_Amount | B14: Rs 28,831,202 across all years
A16: WHY THIS FEED
A17: It is dated | B17: The employee feed's cost lines carry no date, so no payment could be assigned to a year — the open question at the end of 'ERP vehicle costing.xlsx'. Here every line has From_Date/To_Date and a Period_Name, so a cost can be placed in a financial year and pro-rated to a day.
A19: HOW THE ERP MODELS IT
A20: Proj_Activity_Name | B20: The cost head: ADBLU, FC WORK, ROAD TAX, RTO EXPENSE, TYRE, VEHICLE INSURANCE, VEHICLE OUTSIDE SERVICES
A21: Description | B21: A finer split of the same line — VEHICLE OUTSIDE SERVICES breaks into MAINTENANCE SERVICE, MAINTENANCE SERVICE - 2/3, GLASS STICKERS and so on. Equal to Proj_Activity_Name on 806 of 1,054 rows.
A22: Period_Name | B22: YEARLY, QUARTER - I..IV, or a month name. The amount covers THAT period only, so lines are not comparable until they are put on the same footing — use the Days column to pro-rate.
A23: Rate is a UNIT rate | B23: Rate is the rate per unit and Pur_Amount is rate x quantity — they are equal only where the quantity is 1. Pur_Amount is the amount to sum; Rate never is. On the 135 rows where they differ, ADBLU is Rs 60-61 per litre and TYRE is a per-tyre rate. Summing Rate instead of Pur_Amount would understate AdBlue alone by about 40x.
A24: Quantity is derived | B24: The feed has no quantity field, so CostLines derives it as Pur_Amount / Rate. It comes out a whole number on 1,028 of the 1,029 priced rows — 45 litres, 6 tyres — which is what confirms the reading. The exception is TN57AC3636 RTO EXPENSE at 1.87x (Rs 7,500 rate, Rs 14,000 purchased); that one row is either a part-charge or an error, and is worth asking about.
A25: Approved_Date | B25: Blank on 25 rows, and those are exactly the rows where Pur_Amount is 0 (Rs 1,287,922 of rates planned, none of it purchased). Approval is what turns a planned line into spend. Every FY2026-27 line is approved.
A26: Grs_Amount | B26: Identical to Pur_Amount on all rows in this pull, so it is not carried into CostLines.
A27: Employee / Testing | B27: Constant across the feed (VIVEK B / 'T') — the record's owner and a status flag, not per-vehicle data. Kept on CostLines verbatim but carries no information here.
A29: WHAT IT DOES NOT CARRY
A30: No diesel, no salary | B30: The cost heads are tax, insurance, tyres, servicing, RTO and FC work only. Fuel and driver salary — the two largest running costs — are in neither this feed nor the employee feed, so a per-bus running cost cannot be built from the ERP alone yet.
A31: Rented buses have none | B31: 39 of the 77 vehicles in the live fleet have no line here, and they are exactly the RENT VEHICLE entries. Every COMPANY VEHICLE is covered. See the FleetCoverage sheet — the hire charge for a rented bus is invoiced, not planned, so it lives somewhere else in the ERP.
A32: ADBLU stops in 2024 | B32: 123 AdBlue lines exist and every one starts in FY2024-25. Either the head was retired or later AdBlue is being booked elsewhere; worth asking before treating a 2026 total as complete.
A34: READ WITH CARE
A35: Repeated lines are real | B35: 174 rows repeat an existing (vehicle, head, period, from-date, amount) combination. Unlike the employee feed these are not a join artefact — a bus can genuinely take two tyre purchases in one period — but a duplicated entry would look identical, so large repeats deserve a check.
A36: Not a full-year view | B36: A period that has not started yet has no row. FY totals for the current year grow as the year is planned out, so they are not comparable with a closed year until it closes.

Sheet CostLines
A1: Veh_Name | B1: Division | C1: Proj_Activity_Name | D1: Description | E1: Period_Name | F1: From_Date | G1: To_Date | H1: Days | I1: FY | J1: Rate (per unit) | K1: Qty (derived) | L1: Pur_Amount (actual) | M1: Per day | N1: Approved_Date | O1: Approved | P1: Active on as-of | Q1: In cal. year | R1: Order_No | S1: Order_Date | T1: Plan_Entry_No | U1: Project_Type | V1: Testing | W1: Employee
A2: TN57AC3636 | B2: SOCKS | C2: FC WORK | D2: FC WORK | E2: YEARLY | F2: 45383 | G2: 45747 | H2: =IF(OR($F2="",$G2=""),"",$G2-$F2+1) | I2: =IF($F2="","",IF(MONTH($F2)>=4,YEAR($F2)&"-"&TEXT(YEAR($F2)+1-2000,"00"),YEAR($F2)-1&"-"&TEXT(YEAR($F2)-2000,"00"))) | J2: 56950 | K2: =IFERROR($L2/$J2,"") | L2: 56950 | M2: =IFERROR($L2/$H2,"") | N2: 45653 | O2: =IF($N2="","No","Yes") | P2: =IF(OR($F2="",$G2=""),0,IF(AND($F2<=README!$B$4,README!$B$4<=$G2),1,0)) | Q2: =IF(OR($F2="",$G2=""),0,IF(AND($F2<=DATE(README!$B$5,12,31),$G2>=DATE(README!$B$5,1,1)),1,0)) | R2: GUP-VEH0009 | S2: 45475 | T2: 546 | U2: VEHICLE | V2: T | W2: VIVEK B
A3: TN57AC3636 | B3: SOCKS | C3: ROAD TAX | D3: ROAD TAX | E3: YEARLY | F3: 45383 | G3: 45747 | H3: =IF(OR($F3="",$G3=""),"",$G3-$F3+1) | I3: =IF($F3="","",IF(MONTH($F3)>=4,YEAR($F3)&"-"&TEXT(YEAR($F3)+1-2000,"00"),YEAR($F3)-1&"-"&TEXT(YEAR($F3)-2000,"00"))) | J3: 24846 | K3: =IFERROR($L3/$J3,"") | L3: 24846 | M3: =IFERROR($L3/$H3,"") | N3: 45569 | O3: =IF($N3="","No","Yes") | P3: =IF(OR($F3="",$G3=""),0,IF(AND($F3<=README!$B$4,README!$B$4<=$G3),1,0)) | Q3: =IF(OR($F3="",$G3=""),0,IF(AND($F3<=DATE(README!$B$5,12,31),$G3>=DATE(README!$B$5,1,1)),1,0)) | R3: GUP-VEH0011 | S3: 45477 | T3: 548 | U3: VEHICLE | V3: T | W3: VIVEK B
A4: TN57AC3636 | B4: SOCKS | C4: ROAD TAX | D4: ROAD TAX | E4: YEARLY | F4: 45383 | G4: 45747 | H4: =IF(OR($F4="",$G4=""),"",$G4-$F4+1) | I4: =IF($F4="","",IF(MONTH($F4)>=4,YEAR($F4)&"-"&TEXT(YEAR($F4)+1-2000,"00"),YEAR($F4)-1&"-"&TEXT(YEAR($F4)-2000,"00"))) | J4: 24846 | K4: =IFERROR($L4/$J4,"") | L4: 24846 | M4: =IFERROR($L4/$H4,"") | N4: 45649 | O4: =IF($N4="","No","Yes") | P4: =IF(OR($F4="",$G4=""),0,IF(AND($F4<=README!$B$4,README!$B$4<=$G4),1,0)) | Q4: =IF(OR($F4="",$G4=""),0,IF(AND($F4<=DATE(README!$B$5,12,31),$G4>=DATE(README!$B$5,1,1)),1,0)) | R4: GUP-VEH0011 | S4: 45477 | T4: 548 | U4: VEHICLE | V4: T | W4: VIVEK B
A5: TN57AC3636 | B5: SOCKS | C5: ROAD TAX | D5: GREEN TAX | E5: YEARLY | F5: 45383 | G5: 45747 | H5: =IF(OR($F5="",$G5=""),"",$G5-$F5+1) | I5: =IF($F5="","",IF(MONTH($F5)>=4,YEAR($F5)&"-"&TEXT(YEAR($F5)+1-2000,"00"),YEAR($F5)-1&"-"&TEXT(YEAR($F5)-2000,"00"))) | J5: 190 | K5: =IFERROR($L5/$J5,"") | L5: 190 | M5: =IFERROR($L5/$H5,"") | N5: 45649 | O5: =IF($N5="","No","Yes") | P5: =IF(OR($F5="",$G5=""),0,IF(AND($F5<=README!$B$4,README!$B$4<=$G5),1,0)) | Q5: =IF(OR($F5="",$G5=""),0,IF(AND($F5<=DATE(README!$B$5,12,31),$G5>=DATE(README!$B$5,1,1)),1,0)) | R5: GUP-VEH0011 | S5: 45477 | T5: 548 | U5: VEHICLE | V5: T | W5: VIVEK B
A6: TN57AC3636 | B6: SOCKS | C6: ROAD TAX | D6: GREEN TAX | E6: YEARLY | F6: 45383 | G6: 45747 | H6: =IF(OR($F6="",$G6=""),"",$G6-$F6+1) | I6: =IF($F6="","",IF(MONTH($F6)>=4,YEAR($F6)&"-"&TEXT(YEAR($F6)+1-2000,"00"),YEAR($F6)-1&"-"&TEXT(YEAR($F6)-2000,"00"))) | J6: 190 | K6: =IFERROR($L6/$J6,"") | L6: 190 | M6: =IFERROR($L6/$H6,"") | N6: 45569 | O6: =IF($N6="","No","Yes") | P6: =IF(OR($F6="",$G6=""),0,IF(AND($F6<=README!$B$4,README!$B$4<=$G6),1,0)) | Q6: =IF(OR($F6="",$G6=""),0,IF(AND($F6<=DATE(README!$B$5,12,31),$G6>=DATE(README!$B$5,1,1)),1,0)) | R6: GUP-VEH0011 | S6: 45477 | T6: 548 | U6: VEHICLE | V6: T | W6: VIVEK B
A7: TN57AC3636 | B7: SOCKS | C7: ROAD TAX | D7: GREEN TAX | E7: YEARLY | F7: 45383 | G7: 45747 | H7: =IF(OR($F7="",$G7=""),"",$G7-$F7+1) | I7: =IF($F7="","",IF(MONTH($F7)>=4,YEAR($F7)&"-"&TEXT(YEAR($F7)+1-2000,"00"),YEAR($F7)-1&"-"&TEXT(YEAR($F7)-2000,"00"))) | J7: 190 | K7: =IFERROR($L7/$J7,"") | L7: 190 | M7: =IFERROR($L7/$H7,"") | N7: 45481 | O7: =IF($N7="","No","Yes") | P7: =IF(OR($F7="",$G7=""),0,IF(AND($F7<=README!$B$4,README!$B$4<=$G7),1,0)) | Q7: =IF(OR($F7="",$G7=""),0,IF(AND($F7<=DATE(README!$B$5,12,31),$G7>=DATE(README!$B$5,1,1)),1,0)) | R7: GUP-VEH0011 | S7: 45477 | T7: 548 | U7: VEHICLE | V7: T | W7: VIVEK B
A8: TN57AC3636 | B8: SOCKS | C8: ROAD TAX | D8: ROAD TAX | E8: YEARLY | F8: 45383 | G8: 45747 | H8: =IF(OR($F8="",$G8=""),"",$G8-$F8+1) | I8: =IF($F8="","",IF(MONTH($F8)>=4,YEAR($F8)&"-"&TEXT(YEAR($F8)+1-2000,"00"),YEAR($F8)-1&"-"&TEXT(YEAR($F8)-2000,"00"))) | J8: 24846 | K8: =IFERROR($L8/$J8,"") | L8: 24846 | M8: =IFERROR($L8/$H8,"") | N8: 45481 | O8: =IF($N8="","No","Yes") | P8: =IF(OR($F8="",$G8=""),0,IF(AND($F8<=README!$B$4,README!$B$4<=$G8),1,0)) | Q8: =IF(OR($F8="",$G8=""),0,IF(AND($F8<=DATE(README!$B$5,12,31),$G8>=DATE(README!$B$5,1,1)),1,0)) | R8: GUP-VEH0011 | S8: 45477 | T8: 548 | U8: VEHICLE | V8: T | W8: VIVEK B
A9: TN57AC3636 | B9: SOCKS | C9: RTO EXPENSE | D9: RTO EXPENSE | E9: YEARLY | F9: 45383 | G9: 45747 | H9: =IF(OR($F9="",$G9=""),"",$G9-$F9+1) | I9: =IF($F9="","",IF(MONTH($F9)>=4,YEAR($F9)&"-"&TEXT(YEAR($F9)+1-2000,"00"),YEAR($F9)-1&"-"&TEXT(YEAR($F9)-2000,"00"))) | J9: 7500 | K9: =IFERROR($L9/$J9,"") | L9: 7500 | M9: =IFERROR($L9/$H9,"") | N9: 45638 | O9: =IF($N9="","No","Yes") | P9: =IF(OR($F9="",$G9=""),0,IF(AND($F9<=README!$B$4,README!$B$4<=$G9),1,0)) | Q9: =IF(OR($F9="",$G9=""),0,IF(AND($F9<=DATE(README!$B$5,12,31),$G9>=DATE(README!$B$5,1,1)),1,0)) | R9: GUP-VEH0010 | S9: 45475 | T9: 547 | U9: VEHICLE | V9: T | W9: VIVEK B
A10: TN57AC3636 | B10: SOCKS | C10: TYRE | D10: TYRE | E10: YEARLY | F10: 45383 | G10: 45747 | H10: =IF(OR($F10="",$G10=""),"",$G10-$F10+1) | I10: =IF($F10="","",IF(MONTH($F10)>=4,YEAR($F10)&"-"&TEXT(YEAR($F10)+1-2000,"00"),YEAR($F10)-1&"-"&TEXT(YEAR($F10)-2000,"00"))) | J10: 19200 | K10: =IFERROR($L10/$J10,"") | L10: 19200 | M10: =IFERROR($L10/$H10,"") | N10: 45443 | O10: =IF($N10="","No","Yes") | P10: =IF(OR($F10="",$G10=""),0,IF(AND($F10<=README!$B$4,README!$B$4<=$G10),1,0)) | Q10: =IF(OR($F10="",$G10=""),0,IF(AND($F10<=DATE(README!$B$5,12,31),$G10>=DATE(README!$B$5,1,1)),1,0)) | R10: GUP-VEH0006 | S10: 45442 | T10: 522 | U10: VEHICLE | V10: T | W10: VIVEK B
A11: TN57AC3636 | B11: SOCKS | C11: VEHICLE INSURANCE | D11: VEHICLE INSURANCE | E11: YEARLY | F11: 45383 | G11: 45747 | H11: =IF(OR($F11="",$G11=""),"",$G11-$F11+1) | I11: =IF($F11="","",IF(MONTH($F11)>=4,YEAR($F11)&"-"&TEXT(YEAR($F11)+1-2000,"00"),YEAR($F11)-1&"-"&TEXT(YEAR($F11)-2000,"00"))) | J11: 59316 | K11: =IFERROR($L11/$J11,"") | L11: 59316 | M11: =IFERROR($L11/$H11,"") | N11: 45632 | O11: =IF($N11="","No","Yes") | P11: =IF(OR($F11="",$G11=""),0,IF(AND($F11<=README!$B$4,README!$B$4<=$G11),1,0)) | Q11: =IF(OR($F11="",$G11=""),0,IF(AND($F11<=DATE(README!$B$5,12,31),$G11>=DATE(README!$B$5,1,1)),1,0)) | R11: GUP-VEH0013 | S11: 45478 | T11: 550 | U11: VEHICLE | V11: T | W11: VIVEK B
A12: TN57AC3636 | B12: SOCKS | C12: FC WORK | D12: FC WORK | E12: YEARLY | F12: 45748 | G12: 46112 | H12: =IF(OR($F12="",$G12=""),"",$G12-$F12+1) | I12: =IF($F12="","",IF(MONTH($F12)>=4,YEAR($F12)&"-"&TEXT(YEAR($F12)+1-2000,"00"),YEAR($F12)-1&"-"&TEXT(YEAR($F12)-2000,"00"))) | J12: 40020 | K12: =IFERROR($L12/$J12,"") | L12: 40020 | M12: =IFERROR($L12/$H12,"") | N12: 46028 | O12: =IF($N12="","No","Yes") | P12: =IF(OR($F12="",$G12=""),0,IF(AND($F12<=README!$B$4,README!$B$4<=$G12),1,0)) | Q12: =IF(OR($F12="",$G12=""),0,IF(AND($F12<=DATE(README!$B$5,12,31),$G12>=DATE(README!$B$5,1,1)),1,0)) | R12: GUP-VEH0021 | S12: 45832 | T12: 654 | U12: VEHICLE | V12: T | W12: VIVEK B
A13: TN57AC3636 | B13: SOCKS | C13: ROAD TAX | D13: GREEN TAX | E13: QUARTER - I | F13: 45748 | G13: 45838 | H13: =IF(OR($F13="",$G13=""),"",$G13-$F13+1) | I13: =IF($F13="","",IF(MONTH($F13)>=4,YEAR($F13)&"-"&TEXT(YEAR($F13)+1-2000,"00"),YEAR($F13)-1&"-"&TEXT(YEAR($F13)-2000,"00"))) | J13: 190 | K13: =IFERROR($L13/$J13,"") | L13: 190 | M13: =IFERROR($L13/$H13,"") | N13: 46030 | O13: =IF($N13="","No","Yes") | P13: =IF(OR($F13="",$G13=""),0,IF(AND($F13<=README!$B$4,README!$B$4<=$G13),1,0)) | Q13: =IF(OR($F13="",$G13=""),0,IF(AND($F13<=DATE(README!$B$5,12,31),$G13>=DATE(README!$B$5,1,1)),1,0)) | R13: GUP-VEH0014 | S13: 45748 | T13: 609 | U13: VEHICLE | V13: T | W13: VIVEK B
... A61: TN57AF3636 | B61: SOCKS | C61: ROAD TAX | D61: ROAD TAX | E61: YEARLY | F61: 45383 | G61: 45747 | H61: =IF(OR($F61="",$G61=""),"",$G61-$F61+1) | I61: =IF($F61="","",IF(MONTH($F61)>=4,YEAR($F61)&"-"&TEXT(YEAR($F61)+1-2000,"00"),YEAR($F61)-1&"-"&TEXT(YEAR($F61)-2000,"00"))) | J61: 24846 | K61: =IFERROR($L61/$J61,"") | L61: 24846 | M61: =IFERROR($L61/$H61,"") | N61: 45481 | O61: =IF($N61="","No","Yes") | P61: =IF(OR($F61="",$G61=""),0,IF(AND($F61<=README!$B$4,README!$B$4<=$G61),1,0)) | Q61: =IF(OR($F61="",$G61=""),0,IF(AND($F61<=DATE(README!$B$5,12,31),$G61>=DATE(README!$B$5,1,1)),1,0)) | R61: GUP-VEH0011 | S61: 45477 | T61: 548 | U61: VEHICLE | V61: T | W61: VIVEK B
A62: TN57AF3636 | B62: SOCKS | C62: TYRE | D62: TYRE | E62: YEARLY | F62: 45383 | G62: 45747 | H62: =IF(OR($F62="",$G62=""),"",$G62-$F62+1) | I62: =IF($F62="","",IF(MONTH($F62)>=4,YEAR($F62)&"-"&TEXT(YEAR($F62)+1-2000,"00"),YEAR($F62)-1&"-"&TEXT(YEAR($F62)-2000,"00"))) | J62: 19200 | K62: =IFERROR($L62/$J62,"") | L62: 0 | M62: =IFERROR($L62/$H62,"") | O62: =IF($N62="","No","Yes") | P62: =IF(OR($F62="",$G62=""),0,IF(AND($F62<=README!$B$4,README!$B$4<=$G62),1,0)) | Q62: =IF(OR($F62="",$G62=""),0,IF(AND($F62<=DATE(README!$B$5,12,31),$G62>=DATE(README!$B$5,1,1)),1,0)) | R62: GUP-VEH0006 | S62: 45442 | T62: 522 | U62: VEHICLE | V62: T | W62: VIVEK B
A63: TN57AF3636 | B63: SOCKS | C63: VEHICLE INSURANCE | D63: VEHICLE INSURANCE | E63: YEARLY | F63: 45383 | G63: 45747 | H63: =IF(OR($F63="",$G63=""),"",$G63-$F63+1) | I63: =IF($F63="","",IF(MONTH($F63)>=4,YEAR($F63)&"-"&TEXT(YEAR($F63)+1-2000,"00"),YEAR($F63)-1&"-"&TEXT(YEAR($F63)-2000,"00"))) | J63: 59895 | K63: =IFERROR($L63/$J63,"") | L63: 59895 | M63: =IFERROR($L63/$H63,"") | N63: 45632 | O63: =IF($N63="","No","Yes") | P63: =IF(OR($F63="",$G63=""),0,IF(AND($F63<=README!$B$4,README!$B$4<=$G63),1,0)) | Q63: =IF(OR($F63="",$G63=""),0,IF(AND($F63<=DATE(README!$B$5,12,31),$G63>=DATE(README!$B$5,1,1)),1,0)) | R63: GUP-VEH0013 | S63: 45478 | T63: 550 | U63: VEHICLE | V63: T | W63: VIVEK B
A64: TN57AF3636 | B64: SOCKS | C64: FC WORK | D64: FC WORK | E64: YEARLY | F64: 45748 | G64: 46112 | H64: =IF(OR($F64="",$G64=""),"",$G64-$F64+1) | I64: =IF($F64="","",IF(MONTH($F64)>=4,YEAR($F64)&"-"&TEXT(YEAR($F64)+1-2000,"00"),YEAR($F64)-1&"-"&TEXT(YEAR($F64)-2000,"00"))) | J64: 91656.71 | K64: =IFERROR($L64/$J64,"") | L64: 91656.71 | M64: =IFERROR($L64/$H64,"") | N64: 45847 | O64: =IF($N64="","No","Yes") | P64: =IF(OR($F64="",$G64=""),0,IF(AND($F64<=README!$B$4,README!$B$4<=$G64),1,0)) | Q64: =IF(OR($F64="",$G64=""),0,IF(AND($F64<=DATE(README!$B$5,12,31),$G64>=DATE(README!$B$5,1,1)),1,0)) | R64: GUP-VEH0021 | S64: 45832 | T64: 654 | U64: VEHICLE | V64: T | W64: VIVEK B
A65: TN57AF3636 | B65: SOCKS | C65: ROAD TAX | D65: GREEN TAX | E65: QUARTER - I | F65: 45748 | G65: 45838 | H65: =IF(OR($F65="",$G65=""),"",$G65-$F65+1) | I65: =IF($F65="","",IF(MONTH($F65)>=4,YEAR($F65)&"-"&TEXT(YEAR($F65)+1-2000,"00"),YEAR($F65)-1&"-"&TEXT(YEAR($F65)-2000,"00"))) | J65: 190 | K65: =IFERROR($L65/$J65,"") | L65: 190 | M65: =IFERROR($L65/$H65,"") | N65: 46030 | O65: =IF($N65="","No","Yes") | P65: =IF(OR($F65="",$G65=""),0,IF(AND($F65<=README!$B$4,README!$B$4<=$G65),1,0)) | Q65: =IF(OR($F65="",$G65=""),0,IF(AND($F65<=DATE(README!$B$5,12,31),$G65>=DATE(README!$B$5,1,1)),1,0)) | R65: GUP-VEH0014 | S65: 45748 | T65: 609 | U65: VEHICLE | V65: T | W65: VIVEK B
A66: TN57AF3636 | B66: SOCKS | C66: ROAD TAX | D66: ROAD TAX | E66: QUARTER - I | F66: 45748 | G66: 45838 | H66: =IF(OR($F66="",$G66=""),"",$G66-$F66+1) | I66: =IF($F66="","",IF(MONTH($F66)>=4,YEAR($F66)&"-"&TEXT(YEAR($F66)+1-2000,"00"),YEAR($F66)-1&"-"&TEXT(YEAR($F66)-2000,"00"))) | J66: 24846 | K66: =IFERROR($L66/$J66,"") | L66: 24846 | M66: =IFERROR($L66/$H66,"") | N66: 46030 | O66: =IF($N66="","No","Yes") | P66: =IF(OR($F66="",$G66=""),0,IF(AND($F66<=README!$B$4,README!$B$4<=$G66),1,0)) | Q66: =IF(OR($F66="",$G66=""),0,IF(AND($F66<=DATE(README!$B$5,12,31),$G66>=DATE(README!$B$5,1,1)),1,0)) | R66: GUP-VEH0014 | S66: 45748 | T66: 609 | U66: VEHICLE | V66: T | W66: VIVEK B
A67: TN57AF3636 | B67: SOCKS | C67: RTO EXPENSE | D67: RTO EXPENSE | E67: YEARLY | F67: 45748 | G67: 46112 | H67: =IF(OR($F67="",$G67=""),"",$G67-$F67+1) | I67: =IF($F67="","",IF(MONTH($F67)>=4,YEAR($F67)&"-"&TEXT(YEAR($F67)+1-2000,"00"),YEAR($F67)-1&"-"&TEXT(YEAR($F67)-2000,"00"))) | J67: 7500 | K67: =IFERROR($L67/$J67,"") | L67: 7500 | M67: =IFERROR($L67/$H67,"") | N67: 45834 | O67: =IF($N67="","No","Yes") | P67: =IF(OR($F67="",$G67=""),0,IF(AND($F67<=README!$B$4,README!$B$4<=$G67),1,0)) | Q67: =IF(OR($F67="",$G67=""),0,IF(AND($F67<=DATE(README!$B$5,12,31),$G67>=DATE(README!$B$5,1,1)),1,0)) | R67: GUP-VEH0022 | S67: 45834 | T67: 655 | U67: VEHICLE | V67: T | W67: VIVEK B
A68: TN57AF3636 | B68: SOCKS | C68: TYRE | D68: TYRE | E68: YEARLY | F68: 45748 | G68: 46112 | H68: =IF(OR($F68="",$G68=""),"",$G68-$F68+1) | I68: =IF($F68="","",IF(MONTH($F68)>=4,YEAR($F68)&"-"&TEXT(YEAR($F68)+1-2000,"00"),YEAR($F68)-1&"-"&TEXT(YEAR($F68)-2000,"00"))) | J68: 19200 | K68: =IFERROR($L68/$J68,"") | L68: 19200 | M68: =IFERROR($L68/$H68,"") | N68: 45986 | O68: =IF($N68="","No","Yes") | P68: =IF(OR($F68="",$G68=""),0,IF(AND($F68<=README!$B$4,README!$B$4<=$G68),1,0)) | Q68: =IF(OR($F68="",$G68=""),0,IF(AND($F68<=DATE(README!$B$5,12,31),$G68>=DATE(README!$B$5,1,1)),1,0)) | R68: GUP-VEH0025 | S68: 45957 | T68: 726 | U68: VEHICLE | V68: T | W68: VIVEK B
A69: TN57AF3636 | B69: SOCKS | C69: VEHICLE INSURANCE | D69: VEHICLE INSURANCE | E69: YEARLY | F69: 45748 | G69: 46112 | H69: =IF(OR($F69="",$G69=""),"",$G69-$F69+1) | I69: =IF($F69="","",IF(MONTH($F69)>=4,YEAR($F69)&"-"&TEXT(YEAR($F69)+1-2000,"00"),YEAR($F69)-1&"-"&TEXT(YEAR($F69)-2000,"00"))) | J69: 59627 | K69: =IFERROR($L69/$J69,"") | L69: 59627 | M69: =IFERROR($L69/$H69,"") | N69: 45994 | O69: =IF($N69="","No","Yes") | P69: =IF(OR($F69="",$G69=""),0,IF(AND($F69<=README!$B$4,README!$B$4<=$G69),1,0)) | Q69: =IF(OR($F69="",$G69=""),0,IF(AND($F69<=DATE(README!$B$5,12,31),$G69>=DATE(README!$B$5,1,1)),1,0)) | R69: GUP-VEH0020 | S69: 45799 | T69: 645 | U69: VEHICLE | V69: T | W69: VIVEK B
A70: TN57AF3636 | B70: SOCKS | C70: ROAD TAX | D70: ROAD TAX | E70: QUARTER - II | F70: 45839 | G70: 45930 | H70: =IF(OR($F70="",$G70=""),"",$G70-$F70+1) | I70: =IF($F70="","",IF(MONTH($F70)>=4,YEAR($F70)&"-"&TEXT(YEAR($F70)+1-2000,"00"),YEAR($F70)-1&"-"&TEXT(YEAR($F70)-2000,"00"))) | J70: 24846 | K70: =IFERROR($L70/$J70,"") | L70: 24846 | M70: =IFERROR($L70/$H70,"") | N70: 46030 | O70: =IF($N70="","No","Yes") | P70: =IF(OR($F70="",$G70=""),0,IF(AND($F70<=README!$B$4,README!$B$4<=$G70),1,0)) | Q70: =IF(OR($F70="",$G70=""),0,IF(AND($F70<=DATE(README!$B$5,12,31),$G70>=DATE(README!$B$5,1,1)),1,0)) | R70: GUP-VEH0014 | S70: 45748 | T70: 609 | U70: VEHICLE | V70: T | W70: VIVEK B
A71: TN57AF3636 | B71: SOCKS | C71: ROAD TAX | D71: ROAD TAX | E71: QUARTER - III | F71: 45931 | G71: 46022 | H71: =IF(OR($F71="",$G71=""),"",$G71-$F71+1) | I71: =IF($F71="","",IF(MONTH($F71)>=4,YEAR($F71)&"-"&TEXT(YEAR($F71)+1-2000,"00"),YEAR($F71)-1&"-"&TEXT(YEAR($F71)-2000,"00"))) | J71: 24856 | K71: =IFERROR($L71/$J71,"") | L71: 24856 | M71: =IFERROR($L71/$H71,"") | N71: 46030 | O71: =IF($N71="","No","Yes") | P71: =IF(OR($F71="",$G71=""),0,IF(AND($F71<=README!$B$4,README!$B$4<=$G71),1,0)) | Q71: =IF(OR($F71="",$G71=""),0,IF(AND($F71<=DATE(README!$B$5,12,31),$G71>=DATE(README!$B$5,1,1)),1,0)) | R71: GUP-VEH0014 | S71: 45748 | T71: 609 | U71: VEHICLE | V71: T | W71: VIVEK B
A72: TN57AF3636 | B72: SOCKS | C72: ROAD TAX | D72: ROAD TAX | E72: QUARTER - IV | F72: 46023 | G72: 46112 | H72: =IF(OR($F72="",$G72=""),"",$G72-$F72+1) | I72: =IF($F72="","",IF(MONTH($F72)>=4,YEAR($F72)&"-"&TEXT(YEAR($F72)+1-2000,"00"),YEAR($F72)-1&"-"&TEXT(YEAR($F72)-2000,"00"))) | J72: 24846 | K72: =IFERROR($L72/$J72,"") | L72: 24846 | M72: =IFERROR($L72/$H72,"") | N72: 46030 | O72: =IF($N72="","No","Yes") | P72: =IF(OR($F72="",$G72=""),0,IF(AND($F72<=README!$B$4,README!$B$4<=$G72),1,0)) | Q72: =IF(OR($F72="",$G72=""),0,IF(AND($F72<=DATE(README!$B$5,12,31),$G72>=DATE(README!$B$5,1,1)),1,0)) | R72: GUP-VEH0014 | S72: 45748 | T72: 609 | U72: VEHICLE | V72: T | W72: VIVEK B
A73: TN57AF3636 | B73: SOCKS | C73: ROAD TAX | D73: ROAD TAX | E73: QUARTER - I | F73: 46113 | G73: 46203 | H73: =IF(OR($F73="",$G73=""),"",$G73-$F73+1) | I73: =IF($F73="","",IF(MONTH($F73)>=4,YEAR($F73)&"-"&TEXT(YEAR($F73)+1-2000,"00"),YEAR($F73)-1&"-"&TEXT(YEAR($F73)-2000,"00"))) | J73: 24250 | K73: =IFERROR($L73/$J73,"") | L73: 24250 | M73: =IFERROR($L73/$H73,"") | N73: 46088 | O73: =IF($N73="","No","Yes") | P73: =IF(OR($F73="",$G73=""),0,IF(AND($F73<=README!$B$4,README!$B$4<=$G73),1,0)) | Q73: =IF(OR($F73="",$G73=""),0,IF(AND($F73<=DATE(README!$B$5,12,31),$G73>=DATE(README!$B$5,1,1)),1,0)) | R73: GUP-VEH0030 | S73: 46113 | T73: 796 | U73: VEHICLE | V73: T | W73: VIVEK B
A74: TN57AF3636 | B74: SOCKS | C74: ROAD TAX | D74: ROAD TAX | E74: QUARTER - II | F74: 46204 | G74: 46295 | H74: =IF(OR($F74="",$G74=""),"",$G74-$F74+1) | I74: =IF($F74="","",IF(MONTH($F74)>=4,YEAR($F74)&"-"&TEXT(YEAR($F74)+1-2000,"00"),YEAR($F74)-1&"-"&TEXT(YEAR($F74)-2000,"00"))) | J74: 24250 | K74: =IFERROR($L74/$J74,"") | L74: 24250 | M74: =IFERROR($L74/$H74,"") | N74: 46196 | O74: =IF($N74="","No","Yes") | P74: =IF(OR($F74="",$G74=""),0,IF(AND($F74<=README!$B$4,README!$B$4<=$G74),1,0)) | Q74: =IF(OR($F74="",$G74=""),0,IF(AND($F74<=DATE(README!$B$5,12,31),$G74>=DATE(README!$B$5,1,1)),1,0)) | R74: GUP-VEH0030 | S74: 46113 | T74: 796 | U74: VEHICLE | V74: T | W74: VIVEK B
... A76: TN57AH3636 | B76: SOCKS | C76: RTO EXPENSE | D76: RTO EXPENSE | E76: YEARLY | F76: 45383 | G76: 45747 | H76: =IF(OR($F76="",$G76=""),"",$G76-$F76+1) | I76: =IF($F76="","",IF(MONTH($F76)>=4,YEAR($F76)&"-"&TEXT(YEAR($F76)+1-2000,"00"),YEAR($F76)-1&"-"&TEXT(YEAR($F76)-2000,"00"))) | J76: 7000 | K76: =IFERROR($L76/$J76,"") | L76: 7000 | M76: =IFERROR($L76/$H76,"") | N76: 45481 | O76: =IF($N76="","No","Yes") | P76: =IF(OR($F76="",$G76=""),0,IF(AND($F76<=README!$B$4,README!$B$4<=$G76),1,0)) | Q76: =IF(OR($F76="",$G76=""),0,IF(AND($F76<=DATE(README!$B$5,12,31),$G76>=DATE(README!$B$5,1,1)),1,0)) | R76: GUP-VEH0010 | S76: 45475 | T76: 547 | U76: VEHICLE | V76: T | W76: VIVEK B
A77: TN57AH3636 | B77: SOCKS | C77: TYRE | D77: TYRE | E77: YEARLY | F77: 45383 | G77: 45747 | H77: =IF(OR($F77="",$G77=""),"",$G77-$F77+1) | I77: =IF($F77="","",IF(MONTH($F77)>=4,YEAR($F77)&"-"&TEXT(YEAR($F77)+1-2000,"00"),YEAR($F77)-1&"-"&TEXT(YEAR($F77)-2000,"00"))) | J77: 35300 | K77: =IFERROR($L77/$J77,"") | L77: 0 | M77: =IFERROR($L77/$H77,"") | O77: =IF($N77="","No","Yes") | P77: =IF(OR($F77="",$G77=""),0,IF(AND($F77<=README!$B$4,README!$B$4<=$G77),1,0)) | Q77: =IF(OR($F77="",$G77=""),0,IF(AND($F77<=DATE(README!$B$5,12,31),$G77>=DATE(README!$B$5,1,1)),1,0)) | R77: GUP-VEH0006 | S77: 45442 | T77: 522 | U77: VEHICLE | V77: T | W77: VIVEK B
A78: TN57AH3636 | B78: SOCKS | C78: VEHICLE INSURANCE | D78: VEHICLE INSURANCE | E78: YEARLY | F78: 45383 | G78: 45747 | H78: =IF(OR($F78="",$G78=""),"",$G78-$F78+1) | I78: =IF($F78="","",IF(MONTH($F78)>=4,YEAR($F78)&"-"&TEXT(YEAR($F78)+1-2000,"00"),YEAR($F78)-1&"-"&TEXT(YEAR($F78)-2000,"00"))) | J78: 40888 | K78: =IFERROR($L78/$J78,"") | L78: 40888 | M78: =IFERROR($L78/$H78,"") | N78: 45612 | O78: =IF($N78="","No","Yes") | P78: =IF(OR($F78="",$G78=""),0,IF(AND($F78<=README!$B$4,README!$B$4<=$G78),1,0)) | Q78: =IF(OR($F78="",$G78=""),0,IF(AND($F78<=DATE(README!$B$5,12,31),$G78>=DATE(README!$B$5,1,1)),1,0)) | R78: GUP-VEH0013 | S78: 45478 | T78: 550 | U78: VEHICLE | V78: T | W78: VIVEK B
A79: TN57AH3636 | B79: SOCKS | C79: FC WORK | D79: FC WORK | E79: YEARLY | F79: 45748 | G79: 46112 | H79: =IF(OR($F79="",$G79=""),"",$G79-$F79+1) | I79: =IF($F79="","",IF(MONTH($F79)>=4,YEAR($F79)&"-"&TEXT(YEAR($F79)+1-2000,"00"),YEAR($F79)-1&"-"&TEXT(YEAR($F79)-2000,"00"))) | J79: 67000 | K79: =IFERROR($L79/$J79,"") | L79: 67000 | M79: =IFERROR($L79/$H79,"") | N79: 45854 | O79: =IF($N79="","No","Yes") | P79: =IF(OR($F79="",$G79=""),0,IF(AND($F79<=README!$B$4,README!$B$4<=$G79),1,0)) | Q79: =IF(OR($F79="",$G79=""),0,IF(AND($F79<=DATE(README!$B$5,12,31),$G79>=DATE(README!$B$5,1,1)),1,0)) | R79: GUP-VEH0021 | S79: 45832 | T79: 654 | U79: VEHICLE | V79: T | W79: VIVEK B
A80: TN57AH3636 | B80: SOCKS | C80: ROAD TAX | D80: GREEN TAX | E80: QUARTER - I | F80: 45748 | G80: 45838 | H80: =IF(OR($F80="",$G80=""),"",$G80-$F80+1) | I80: =IF($F80="","",IF(MONTH($F80)>=4,YEAR($F80)&"-"&TEXT(YEAR($F80)+1-2000,"00"),YEAR($F80)-1&"-"&TEXT(YEAR($F80)-2000,"00"))) | J80: 760 | K80: =IFERROR($L80/$J80,"") | L80: 760 | M80: =IFERROR($L80/$H80,"") | N80: 46030 | O80: =IF($N80="","No","Yes") | P80: =IF(OR($F80="",$G80=""),0,IF(AND($F80<=README!$B$4,README!$B$4<=$G80),1,0)) | Q80: =IF(OR($F80="",$G80=""),0,IF(AND($F80<=DATE(README!$B$5,12,31),$G80>=DATE(README!$B$5,1,1)),1,0)) | R80: GUP-VEH0014 | S80: 45748 | T80: 609 | U80: VEHICLE | V80: T | W80: VIVEK B
A81: TN57AH3636 | B81: SOCKS | C81: ROAD TAX | D81: ROAD TAX | E81: QUARTER - I | F81: 45748 | G81: 45838 | H81: =IF(OR($F81="",$G81=""),"",$G81-$F81+1) | I81: =IF($F81="","",IF(MONTH($F81)>=4,YEAR($F81)&"-"&TEXT(YEAR($F81)+1-2000,"00"),YEAR($F81)-1&"-"&TEXT(YEAR($F81)-2000,"00"))) | J81: 17092 | K81: =IFERROR($L81/$J81,"") | L81: 17092 | M81: =IFERROR($L81/$H81,"") | N81: 46030 | O81: =IF($N81="","No","Yes") | P81: =IF(OR($F81="",$G81=""),0,IF(AND($F81<=README!$B$4,README!$B$4<=$G81),1,0)) | Q81: =IF(OR($F81="",$G81=""),0,IF(AND($F81<=DATE(README!$B$5,12,31),$G81>=DATE(README!$B$5,1,1)),1,0)) | R81: GUP-VEH0014 | S81: 45748 | T81: 609 | U81: VEHICLE | V81: T | W81: VIVEK B
A82: TN57AH3636 | B82: SOCKS | C82: RTO EXPENSE | D82: RTO EXPENSE | E82: YEARLY | F82: 45748 | G82: 46112 | H82: =IF(OR($F82="",$G82=""),"",$G82-$F82+1) | I82: =IF($F82="","",IF(MONTH($F82)>=4,YEAR($F82)&"-"&TEXT(YEAR($F82)+1-2000,"00"),YEAR($F82)-1&"-"&TEXT(YEAR($F82)-2000,"00"))) | J82: 6500 | K82: =IFERROR($L82/$J82,"") | L82: 6500 | M82: =IFERROR($L82/$H82,"") | N82: 45854 | O82: =IF($N82="","No","Yes") | P82: =IF(OR($F82="",$G82=""),0,IF(AND($F82<=README!$B$4,README!$B$4<=$G82),1,0)) | Q82: =IF(OR($F82="",$G82=""),0,IF(AND($F82<=DATE(README!$B$5,12,31),$G82>=DATE(README!$B$5,1,1)),1,0)) | R82: GUP-VEH0022 | S82: 45834 | T82: 655 | U82: VEHICLE | V82: T | W82: VIVEK B
A83: TN57AH3636 | B83: SOCKS | C83: TYRE | D83: TYRE | E83: YEARLY | F83: 45748 | G83: 46112 | H83: =IF(OR($F83="",$G83=""),"",$G83-$F83+1) | I83: =IF($F83="","",IF(MONTH($F83)>=4,YEAR($F83)&"-"&TEXT(YEAR($F83)+1-2000,"00"),YEAR($F83)-1&"-"&TEXT(YEAR($F83)-2000,"00"))) | J83: 37500 | K83: =IFERROR($L83/$J83,"") | L83: 37500 | M83: =IFERROR($L83/$H83,"") | N83: 45957 | O83: =IF($N83="","No","Yes") | P83: =IF(OR($F83="",$G83=""),0,IF(AND($F83<=README!$B$4,README!$B$4<=$G83),1,0)) | Q83: =IF(OR($F83="",$G83=""),0,IF(AND($F83<=DATE(README!$B$5,12,31),$G83>=DATE(README!$B$5,1,1)),1,0)) | R83: GUP-VEH0025 | S83: 45957 | T83: 726 | U83: VEHICLE | V83: T | W83: VIVEK B
A84: TN57AH3636 | B84: SOCKS | C84: VEHICLE INSURANCE | D84: VEHICLE INSURANCE | E84: YEARLY | F84: 45748 | G84: 46112 | H84: =IF(OR($F84="",$G84=""),"",$G84-$F84+1) | I84: =IF($F84="","",IF(MONTH($F84)>=4,YEAR($F84)&"-"&TEXT(YEAR($F84)+1-2000,"00"),YEAR($F84)-1&"-"&TEXT(YEAR($F84)-2000,"00"))) | J84: 40270 | K84: =IFERROR($L84/$J84,"") | L84: 40270 | M84: =IFERROR($L84/$H84,"") | N84: 45966 | O84: =IF($N84="","No","Yes") | P84: =IF(OR($F84="",$G84=""),0,IF(AND($F84<=README!$B$4,README!$B$4<=$G84),1,0)) | Q84: =IF(OR($F84="",$G84=""),0,IF(AND($F84<=DATE(README!$B$5,12,31),$G84>=DATE(README!$B$5,1,1)),1,0)) | R84: GUP-VEH0020 | S84: 45799 | T84: 645 | U84: VEHICLE | V84: T | W84: VIVEK B
A85: TN57AH3636 | B85: SOCKS | C85: ROAD TAX | D85: GREEN TAX | E85: QUARTER - II | F85: 45839 | G85: 45930 | H85: =IF(OR($F85="",$G85=""),"",$G85-$F85+1) | I85: =IF($F85="","",IF(MONTH($F85)>=4,YEAR($F85)&"-"&TEXT(YEAR($F85)+1-2000,"00"),YEAR($F85)-1&"-"&TEXT(YEAR($F85)-2000,"00"))) | J85: 190 | K85: =IFERROR($L85/$J85,"") | L85: 190 | M85: =IFERROR($L85/$H85,"") | N85: 46030 | O85: =IF($N85="","No","Yes") | P85: =IF(OR($F85="",$G85=""),0,IF(AND($F85<=README!$B$4,README!$B$4<=$G85),1,0)) | Q85: =IF(OR($F85="",$G85=""),0,IF(AND($F85<=DATE(README!$B$5,12,31),$G85>=DATE(README!$B$5,1,1)),1,0)) | R85: GUP-VEH0014 | S85: 45748 | T85: 609 | U85: VEHICLE | V85: T | W85: VIVEK B
A86: TN57AH3636 | B86: SOCKS | C86: ROAD TAX | D86: ROAD TAX | E86: QUARTER - II | F86: 45839 | G86: 45930 | H86: =IF(OR($F86="",$G86=""),"",$G86-$F86+1) | I86: =IF($F86="","",IF(MONTH($F86)>=4,YEAR($F86)&"-"&TEXT(YEAR($F86)+1-2000,"00"),YEAR($F86)-1&"-"&TEXT(YEAR($F86)-2000,"00"))) | J86: 4545 | K86: =IFERROR($L86/$J86,"") | L86: 4545 | M86: =IFERROR($L86/$H86,"") | N86: 46030 | O86: =IF($N86="","No","Yes") | P86: =IF(OR($F86="",$G86=""),0,IF(AND($F86<=README!$B$4,README!$B$4<=$G86),1,0)) | Q86: =IF(OR($F86="",$G86=""),0,IF(AND($F86<=DATE(README!$B$5,12,31),$G86>=DATE(README!$B$5,1,1)),1,0)) | R86: GUP-VEH0014 | S86: 45748 | T86: 609 | U86: VEHICLE | V86: T | W86: VIVEK B
A87: TN57AH3636 | B87: SOCKS | C87: ROAD TAX | D87: ROAD TAX | E87: QUARTER - III | F87: 45931 | G87: 46022 | H87: =IF(OR($F87="",$G87=""),"",$G87-$F87+1) | I87: =IF($F87="","",IF(MONTH($F87)>=4,YEAR($F87)&"-"&TEXT(YEAR($F87)+1-2000,"00"),YEAR($F87)-1&"-"&TEXT(YEAR($F87)-2000,"00"))) | J87: 4555 | K87: =IFERROR($L87/$J87,"") | L87: 4555 | M87: =IFERROR($L87/$H87,"") | N87: 46030 | O87: =IF($N87="","No","Yes") | P87: =IF(OR($F87="",$G87=""),0,IF(AND($F87<=README!$B$4,README!$B$4<=$G87),1,0)) | Q87: =IF(OR($F87="",$G87=""),0,IF(AND($F87<=DATE(README!$B$5,12,31),$G87>=DATE(README!$B$5,1,1)),1,0)) | R87: GUP-VEH0014 | S87: 45748 | T87: 609 | U87: VEHICLE | V87: T | W87: VIVEK B
A88: TN57AH3636 | B88: GENERAL | C88: VEHICLE OUTSIDE SERVICES | D88: ELETRICAL WORK - VEHICLE | E88: NOVEMBER | F88: 45962 | G88: 45991 | H88: =IF(OR($F88="",$G88=""),"",$G88-$F88+1) | I88: =IF($F88="","",IF(MONTH($F88)>=4,YEAR($F88)&"-"&TEXT(YEAR($F88)+1-2000,"00"),YEAR($F88)-1&"-"&TEXT(YEAR($F88)-2000,"00"))) | J88: 4704 | K88: =IFERROR($L88/$J88,"") | L88: 4704 | M88: =IFERROR($L88/$H88,"") | N88: 45986 | O88: =IF($N88="","No","Yes") | P88: =IF(OR($F88="",$G88=""),0,IF(AND($F88<=README!$B$4,README!$B$4<=$G88),1,0)) | Q88: =IF(OR($F88="",$G88=""),0,IF(AND($F88<=DATE(README!$B$5,12,31),$G88>=DATE(README!$B$5,1,1)),1,0)) | R88: GUP-VEH0019 | S88: 45777 | T88: 638 | U88: VEHICLE | V88: T | W88: VIVEK B
A89: TN57AH3636 | B89: SOCKS | C89: ROAD TAX | D89: ROAD TAX | E89: QUARTER - IV | F89: 46023 | G89: 46112 | H89: =IF(OR($F89="",$G89=""),"",$G89-$F89+1) | I89: =IF($F89="","",IF(MONTH($F89)>=4,YEAR($F89)&"-"&TEXT(YEAR($F89)+1-2000,"00"),YEAR($F89)-1&"-"&TEXT(YEAR($F89)-2000,"00"))) | J89: 4555 | K89: =IFERROR($L89/$J89,"") | L89: 4555 | M89: =IFERROR($L89/$H89,"") | N89: 46030 | O89: =IF($N89="","No","Yes") | P89: =IF(OR($F89="",$G89=""),0,IF(AND($F89<=README!$B$4,README!$B$4<=$G89),1,0)) | Q89: =IF(OR($F89="",$G89=""),0,IF(AND($F89<=DATE(README!$B$5,12,31),$G89>=DATE(README!$B$5,1,1)),1,0)) | R89: GUP-VEH0014 | S89: 45748 | T89: 609 | U89: VEHICLE | V89: T | W89: VIVEK B
... A137: TN57BC3636 | B137: SOCKS | C137: RTO EXPENSE | D137: RTO EXPENSE | E137: YEARLY | F137: 45383 | G137: 45747 | H137: =IF(OR($F137="",$G137=""),"",$G137-$F137+1) | I137: =IF($F137="","",IF(MONTH($F137)>=4,YEAR($F137)&"-"&TEXT(YEAR($F137)+1-2000,"00"),YEAR($F137)-1&"-"&TEXT(YEAR($F137)-2000,"00"))) | J137: 7500 | K137: =IFERROR($L137/$J137,"") | L137: 7500 | M137: =IFERROR($L137/$H137,"") | N137: 45638 | O137: =IF($N137="","No","Yes") | P137: =IF(OR($F137="",$G137=""),0,IF(AND($F137<=README!$B$4,README!$B$4<=$G137),1,0)) | Q137: =IF(OR($F137="",$G137=""),0,IF(AND($F137<=DATE(README!$B$5,12,31),$G137>=DATE(README!$B$5,1,1)),1,0)) | R137: GUP-VEH0010 | S137: 45475 | T137: 547 | U137: VEHICLE | V137: T | W137: VIVEK B
A138: TN57BC3636 | B138: SOCKS | C138: TYRE | D138: TYRE | E138: YEARLY | F138: 45383 | G138: 45747 | H138: =IF(OR($F138="",$G138=""),"",$G138-$F138+1) | I138: =IF($F138="","",IF(MONTH($F138)>=4,YEAR($F138)&"-"&TEXT(YEAR($F138)+1-2000,"00"),YEAR($F138)-1&"-"&TEXT(YEAR($F138)-2000,"00"))) | J138: 21800 | K138: =IFERROR($L138/$J138,"") | L138: 0 | M138: =IFERROR($L138/$H138,"") | O138: =IF($N138="","No","Yes") | P138: =IF(OR($F138="",$G138=""),0,IF(AND($F138<=README!$B$4,README!$B$4<=$G138),1,0)) | Q138: =IF(OR($F138="",$G138=""),0,IF(AND($F138<=DATE(README!$B$5,12,31),$G138>=DATE(README!$B$5,1,1)),1,0)) | R138: GUP-VEH0006 | S138: 45442 | T138: 522 | U138: VEHICLE | V138: T | W138: VIVEK B
A139: TN57BC3636 | B139: SOCKS | C139: VEHICLE INSURANCE | D139: VEHICLE INSURANCE | E139: YEARLY | F139: 45383 | G139: 45747 | H139: =IF(OR($F139="",$G139=""),"",$G139-$F139+1) | I139: =IF($F139="","",IF(MONTH($F139)>=4,YEAR($F139)&"-"&TEXT(YEAR($F139)+1-2000,"00"),YEAR($F139)-1&"-"&TEXT(YEAR($F139)-2000,"00"))) | J139: 71861 | K139: =IFERROR($L139/$J139,"") | L139: 71861 | M139: =IFERROR($L139/$H139,"") | N139: 45565 | O139: =IF($N139="","No","Yes") | P139: =IF(OR($F139="",$G139=""),0,IF(AND($F139<=README!$B$4,README!$B$4<=$G139),1,0)) | Q139: =IF(OR($F139="",$G139=""),0,IF(AND($F139<=DATE(README!$B$5,12,31),$G139>=DATE(README!$B$5,1,1)),1,0)) | R139: GUP-VEH0013 | S139: 45478 | T139: 550 | U139: VEHICLE | V139: T | W139: VIVEK B
A140: TN57BC3636 | B140: SOCKS | C140: FC WORK | D140: FC WORK | E140: YEARLY | F140: 45748 | G140: 46112 | H140: =IF(OR($F140="",$G140=""),"",$G140-$F140+1) | I140: =IF($F140="","",IF(MONTH($F140)>=4,YEAR($F140)&"-"&TEXT(YEAR($F140)+1-2000,"00"),YEAR($F140)-1&"-"&TEXT(YEAR($F140)-2000,"00"))) | J140: 58100 | K140: =IFERROR($L140/$J140,"") | L140: 58100 | M140: =IFERROR($L140/$H140,"") | N140: 46028 | O140: =IF($N140="","No","Yes") | P140: =IF(OR($F140="",$G140=""),0,IF(AND($F140<=README!$B$4,README!$B$4<=$G140),1,0)) | Q140: =IF(OR($F140="",$G140=""),0,IF(AND($F140<=DATE(README!$B$5,12,31),$G140>=DATE(README!$B$5,1,1)),1,0)) | R140: GUP-VEH0021 | S140: 45832 | T140: 654 | U140: VEHICLE | V140: T | W140: VIVEK B
A141: TN57BC3636 | B141: SOCKS | C141: ROAD TAX | D141: GREEN TAX | E141: QUARTER - I | F141: 45748 | G141: 45838 | H141: =IF(OR($F141="",$G141=""),"",$G141-$F141+1) | I141: =IF($F141="","",IF(MONTH($F141)>=4,YEAR($F141)&"-"&TEXT(YEAR($F141)+1-2000,"00"),YEAR($F141)-1&"-"&TEXT(YEAR($F141)-2000,"00"))) | J141: 190 | K141: =IFERROR($L141/$J141,"") | L141: 190 | M141: =IFERROR($L141/$H141,"") | N141: 46030 | O141: =IF($N141="","No","Yes") | P141: =IF(OR($F141="",$G141=""),0,IF(AND($F141<=README!$B$4,README!$B$4<=$G141),1,0)) | Q141: =IF(OR($F141="",$G141=""),0,IF(AND($F141<=DATE(README!$B$5,12,31),$G141>=DATE(README!$B$5,1,1)),1,0)) | R141: GUP-VEH0014 | S141: 45748 | T141: 609 | U141: VEHICLE | V141: T | W141: VIVEK B
A142: TN57BC3636 | B142: SOCKS | C142: ROAD TAX | D142: ROAD TAX | E142: QUARTER - I | F142: 45748 | G142: 45838 | H142: =IF(OR($F142="",$G142=""),"",$G142-$F142+1) | I142: =IF($F142="","",IF(MONTH($F142)>=4,YEAR($F142)&"-"&TEXT(YEAR($F142)+1-2000,"00"),YEAR($F142)-1&"-"&TEXT(YEAR($F142)-2000,"00"))) | J142: 30300 | K142: =IFERROR($L142/$J142,"") | L142: 30300 | M142: =IFERROR($L142/$H142,"") | N142: 46030 | O142: =IF($N142="","No","Yes") | P142: =IF(OR($F142="",$G142=""),0,IF(AND($F142<=README!$B$4,README!$B$4<=$G142),1,0)) | Q142: =IF(OR($F142="",$G142=""),0,IF(AND($F142<=DATE(README!$B$5,12,31),$G142>=DATE(README!$B$5,1,1)),1,0)) | R142: GUP-VEH0014 | S142: 45748 | T142: 609 | U142: VEHICLE | V142: T | W142: VIVEK B
A143: TN57BC3636 | B143: SOCKS | C143: RTO EXPENSE | D143: GREEN TAX | E143: YEARLY | F143: 45748 | G143: 46112 | H143: =IF(OR($F143="",$G143=""),"",$G143-$F143+1) | I143: =IF($F143="","",IF(MONTH($F143)>=4,YEAR($F143)&"-"&TEXT(YEAR($F143)+1-2000,"00"),YEAR($F143)-1&"-"&TEXT(YEAR($F143)-2000,"00"))) | J143: 758 | K143: =IFERROR($L143/$J143,"") | L143: 758 | M143: =IFERROR($L143/$H143,"") | N143: 46020 | O143: =IF($N143="","No","Yes") | P143: =IF(OR($F143="",$G143=""),0,IF(AND($F143<=README!$B$4,README!$B$4<=$G143),1,0)) | Q143: =IF(OR($F143="",$G143=""),0,IF(AND($F143<=DATE(README!$B$5,12,31),$G143>=DATE(README!$B$5,1,1)),1,0)) | R143: GUP-VEH0022 | S143: 45834 | T143: 655 | U143: VEHICLE | V143: T | W143: VIVEK B
A144: TN57BC3636 | B144: SOCKS | C144: TYRE | D144: TYRE | E144: YEARLY | F144: 45748 | G144: 46112 | H144: =IF(OR($F144="",$G144=""),"",$G144-$F144+1) | I144: =IF($F144="","",IF(MONTH($F144)>=4,YEAR($F144)&"-"&TEXT(YEAR($F144)+1-2000,"00"),YEAR($F144)-1&"-"&TEXT(YEAR($F144)-2000,"00"))) | J144: 21800 | K144: =IFERROR($L144/$J144,"") | L144: 21800 | M144: =IFERROR($L144/$H144,"") | N144: 45986 | O144: =IF($N144="","No","Yes") | P144: =IF(OR($F144="",$G144=""),0,IF(AND($F144<=README!$B$4,README!$B$4<=$G144),1,0)) | Q144: =IF(OR($F144="",$G144=""),0,IF(AND($F144<=DATE(README!$B$5,12,31),$G144>=DATE(README!$B$5,1,1)),1,0)) | R144: GUP-VEH0025 | S144: 45957 | T144: 726 | U144: VEHICLE | V144: T | W144: VIVEK B
A145: TN57BC3636 | B145: SOCKS | C145: VEHICLE INSURANCE | D145: VEHICLE INSURANCE | E145: YEARLY | F145: 45748 | G145: 46112 | H145: =IF(OR($F145="",$G145=""),"",$G145-$F145+1) | I145: =IF($F145="","",IF(MONTH($F145)>=4,YEAR($F145)&"-"&TEXT(YEAR($F145)+1-2000,"00"),YEAR($F145)-1&"-"&TEXT(YEAR($F145)-2000,"00"))) | J145: 71651 | K145: =IFERROR($L145/$J145,"") | L145: 71651 | M145: =IFERROR($L145/$H145,"") | N145: 45930 | O145: =IF($N145="","No","Yes") | P145: =IF(OR($F145="",$G145=""),0,IF(AND($F145<=README!$B$4,README!$B$4<=$G145),1,0)) | Q145: =IF(OR($F145="",$G145=""),0,IF(AND($F145<=DATE(README!$B$5,12,31),$G145>=DATE(README!$B$5,1,1)),1,0)) | R145: GUP-VEH0020 | S145: 45799 | T145: 645 | U145: VEHICLE | V145: T | W145: VIVEK B
A146: TN57BC3636 | B146: GENERAL | C146: VEHICLE OUTSIDE SERVICES | D146: MAINTENANCE SERVICE | E146: YEARLY | F146: 45748 | G146: 46112 | H146: =IF(OR($F146="",$G146=""),"",$G146-$F146+1) | I146: =IF($F146="","",IF(MONTH($F146)>=4,YEAR($F146)&"-"&TEXT(YEAR($F146)+1-2000,"00"),YEAR($F146)-1&"-"&TEXT(YEAR($F146)-2000,"00"))) | J146: 3050 | K146: =IFERROR($L146/$J146,"") | L146: 3050 | M146: =IFERROR($L146/$H146,"") | N146: 45811 | O146: =IF($N146="","No","Yes") | P146: =IF(OR($F146="",$G146=""),0,IF(AND($F146<=README!$B$4,README!$B$4<=$G146),1,0)) | Q146: =IF(OR($F146="",$G146=""),0,IF(AND($F146<=DATE(README!$B$5,12,31),$G146>=DATE(README!$B$5,1,1)),1,0)) | R146: GUP-VEH0019 | S146: 45777 | T146: 638 | U146: VEHICLE | V146: T | W146: VIVEK B
A147: TN57BC3636 | B147: GENERAL | C147: VEHICLE OUTSIDE SERVICES | D147: MAINTENANCE SERVICE - 2 | E147: YEARLY | F147: 45748 | G147: 46112 | H147: =IF(OR($F147="",$G147=""),"",$G147-$F147+1) | I147: =IF($F147="","",IF(MONTH($F147)>=4,YEAR($F147)&"-"&TEXT(YEAR($F147)+1-2000,"00"),YEAR($F147)-1&"-"&TEXT(YEAR($F147)-2000,"00"))) | J147: 7100 | K147: =IFERROR($L147/$J147,"") | L147: 7100 | M147: =IFERROR($L147/$H147,"") | N147: 45934 | O147: =IF($N147="","No","Yes") | P147: =IF(OR($F147="",$G147=""),0,IF(AND($F147<=README!$B$4,README!$B$4<=$G147),1,0)) | Q147: =IF(OR($F147="",$G147=""),0,IF(AND($F147<=DATE(README!$B$5,12,31),$G147>=DATE(README!$B$5,1,1)),1,0)) | R147: GUP-VEH0019 | S147: 45777 | T147: 638 | U147: VEHICLE | V147: T | W147: VIVEK B
A148: TN57BC3636 | B148: SOCKS | C148: ROAD TAX | D148: ROAD TAX | E148: QUARTER - II | F148: 45839 | G148: 45930 | H148: =IF(OR($F148="",$G148=""),"",$G148-$F148+1) | I148: =IF($F148="","",IF(MONTH($F148)>=4,YEAR($F148)&"-"&TEXT(YEAR($F148)+1-2000,"00"),YEAR($F148)-1&"-"&TEXT(YEAR($F148)-2000,"00"))) | J148: 30300 | K148: =IFERROR($L148/$J148,"") | L148: 30300 | M148: =IFERROR($L148/$H148,"") | N148: 46030 | O148: =IF($N148="","No","Yes") | P148: =IF(OR($F148="",$G148=""),0,IF(AND($F148<=README!$B$4,README!$B$4<=$G148),1,0)) | Q148: =IF(OR($F148="",$G148=""),0,IF(AND($F148<=DATE(README!$B$5,12,31),$G148>=DATE(README!$B$5,1,1)),1,0)) | R148: GUP-VEH0014 | S148: 45748 | T148: 609 | U148: VEHICLE | V148: T | W148: VIVEK B
A149: TN57BC3636 | B149: SOCKS | C149: ROAD TAX | D149: ROAD TAX | E149: QUARTER - III | F149: 45931 | G149: 46022 | H149: =IF(OR($F149="",$G149=""),"",$G149-$F149+1) | I149: =IF($F149="","",IF(MONTH($F149)>=4,YEAR($F149)&"-"&TEXT(YEAR($F149)+1-2000,"00"),YEAR($F149)-1&"-"&TEXT(YEAR($F149)-2000,"00"))) | J149: 30310 | K149: =IFERROR($L149/$J149,"") | L149: 30310 | M149: =IFERROR($L149/$H149,"") | N149: 46030 | O149: =IF($N149="","No","Yes") | P149: =IF(OR($F149="",$G149=""),0,IF(AND($F149<=README!$B$4,README!$B$4<=$G149),1,0)) | Q149: =IF(OR($F149="",$G149=""),0,IF(AND($F149<=DATE(README!$B$5,12,31),$G149>=DATE(README!$B$5,1,1)),1,0)) | R149: GUP-VEH0014 | S149: 45748 | T149: 609 | U149: VEHICLE | V149: T | W149: VIVEK B
A150: TN57BC3636 | B150: SOCKS | C150: RTO EXPENSE | D150: RTO EXPENSE | E150: DECEMBER | F150: 45992 | G150: 46022 | H150: =IF(OR($F150="",$G150=""),"",$G150-$F150+1) | I150: =IF($F150="","",IF(MONTH($F150)>=4,YEAR($F150)&"-"&TEXT(YEAR($F150)+1-2000,"00"),YEAR($F150)-1&"-"&TEXT(YEAR($F150)-2000,"00"))) | J150: 7500 | K150: =IFERROR($L150/$J150,"") | L150: 7500 | M150: =IFERROR($L150/$H150,"") | N150: 46015 | O150: =IF($N150="","No","Yes") | P150: =IF(OR($F150="",$G150=""),0,IF(AND($F150<=README!$B$4,README!$B$4<=$G150),1,0)) | Q150: =IF(OR($F150="",$G150=""),0,IF(AND($F150<=DATE(README!$B$5,12,31),$G150>=DATE(README!$B$5,1,1)),1,0)) | R150: GUP-VEH0022 | S150: 45834 | T150: 655 | U150: VEHICLE | V150: T | W150: VIVEK B
... A256: TN57BP5356 | B256: SOCKS | C256: VEHICLE INSURANCE | D256: VEHICLE INSURANCE | E256: YEARLY | F256: 45383 | G256: 45747 | H256: =IF(OR($F256="",$G256=""),"",$G256-$F256+1) | I256: =IF($F256="","",IF(MONTH($F256)>=4,YEAR($F256)&"-"&TEXT(YEAR($F256)+1-2000,"00"),YEAR($F256)-1&"-"&TEXT(YEAR($F256)-2000,"00"))) | J256: 29702 | K256: =IFERROR($L256/$J256,"") | L256: 29702 | M256: =IFERROR($L256/$H256,"") | N256: 45775 | O256: =IF($N256="","No","Yes") | P256: =IF(OR($F256="",$G256=""),0,IF(AND($F256<=README!$B$4,README!$B$4<=$G256),1,0)) | Q256: =IF(OR($F256="",$G256=""),0,IF(AND($F256<=DATE(README!$B$5,12,31),$G256>=DATE(README!$B$5,1,1)),1,0)) | R256: GUP-VEH0013 | S256: 45478 | T256: 550 | U256: VEHICLE | V256: T | W256: VIVEK B
A257: TN57BP5356 | B257: SOCKS | C257: VEHICLE INSURANCE | D257: VEHICLE INSURANCE | E257: YEARLY | F257: 45748 | G257: 46112 | H257: =IF(OR($F257="",$G257=""),"",$G257-$F257+1) | I257: =IF($F257="","",IF(MONTH($F257)>=4,YEAR($F257)&"-"&TEXT(YEAR($F257)+1-2000,"00"),YEAR($F257)-1&"-"&TEXT(YEAR($F257)-2000,"00"))) | J257: 29702 | K257: =IFERROR($L257/$J257,"") | L257: 0 | M257: =IFERROR($L257/$H257,"") | O257: =IF($N257="","No","Yes") | P257: =IF(OR($F257="",$G257=""),0,IF(AND($F257<=README!$B$4,README!$B$4<=$G257),1,0)) | Q257: =IF(OR($F257="",$G257=""),0,IF(AND($F257<=DATE(README!$B$5,12,31),$G257>=DATE(README!$B$5,1,1)),1,0)) | R257: GUP-VEH0020 | S257: 45799 | T257: 645 | U257: VEHICLE | V257: T | W257: VIVEK B
A258: TN57BQ3434 | B258: SOCKS | C258: ADBLU | D258: ADBLU | E258: YEARLY | F258: 45383 | G258: 45747 | H258: =IF(OR($F258="",$G258=""),"",$G258-$F258+1) | I258: =IF($F258="","",IF(MONTH($F258)>=4,YEAR($F258)&"-"&TEXT(YEAR($F258)+1-2000,"00"),YEAR($F258)-1&"-"&TEXT(YEAR($F258)-2000,"00"))) | J258: 61 | K258: =IFERROR($L258/$J258,"") | L258: 2440 | M258: =IFERROR($L258/$H258,"") | N258: 45479 | O258: =IF($N258="","No","Yes") | P258: =IF(OR($F258="",$G258=""),0,IF(AND($F258<=README!$B$4,README!$B$4<=$G258),1,0)) | Q258: =IF(OR($F258="",$G258=""),0,IF(AND($F258<=DATE(README!$B$5,12,31),$G258>=DATE(README!$B$5,1,1)),1,0)) | R258: GUP-VEH0008 | S258: 45461 | T258: 541 | U258: VEHICLE | V258: T | W258: VIVEK B
A259: TN57BQ3434 | B259: SOCKS | C259: ADBLU | D259: ADBLU | E259: YEARLY | F259: 45383 | G259: 45747 | H259: =IF(OR($F259="",$G259=""),"",$G259-$F259+1) | I259: =IF($F259="","",IF(MONTH($F259)>=4,YEAR($F259)&"-"&TEXT(YEAR($F259)+1-2000,"00"),YEAR($F259)-1&"-"&TEXT(YEAR($F259)-2000,"00"))) | J259: 61 | K259: =IFERROR($L259/$J259,"") | L259: 2440 | M259: =IFERROR($L259/$H259,"") | N259: 45623 | O259: =IF($N259="","No","Yes") | P259: =IF(OR($F259="",$G259=""),0,IF(AND($F259<=README!$B$4,README!$B$4<=$G259),1,0)) | Q259: =IF(OR($F259="",$G259=""),0,IF(AND($F259<=DATE(README!$B$5,12,31),$G259>=DATE(README!$B$5,1,1)),1,0)) | R259: GUP-VEH0008 | S259: 45461 | T259: 541 | U259: VEHICLE | V259: T | W259: VIVEK B
A260: TN57BQ3434 | B260: SOCKS | C260: ADBLU | D260: ADBLU | E260: YEARLY | F260: 45383 | G260: 45747 | H260: =IF(OR($F260="",$G260=""),"",$G260-$F260+1) | I260: =IF($F260="","",IF(MONTH($F260)>=4,YEAR($F260)&"-"&TEXT(YEAR($F260)+1-2000,"00"),YEAR($F260)-1&"-"&TEXT(YEAR($F260)-2000,"00"))) | J260: 61 | K260: =IFERROR($L260/$J260,"") | L260: 2440 | M260: =IFERROR($L260/$H260,"") | N260: 45602 | O260: =IF($N260="","No","Yes") | P260: =IF(OR($F260="",$G260=""),0,IF(AND($F260<=README!$B$4,README!$B$4<=$G260),1,0)) | Q260: =IF(OR($F260="",$G260=""),0,IF(AND($F260<=DATE(README!$B$5,12,31),$G260>=DATE(README!$B$5,1,1)),1,0)) | R260: GUP-VEH0008 | S260: 45461 | T260: 541 | U260: VEHICLE | V260: T | W260: VIVEK B
A261: TN57BQ3434 | B261: SOCKS | C261: ADBLU | D261: ADBLU | E261: YEARLY | F261: 45383 | G261: 45747 | H261: =IF(OR($F261="",$G261=""),"",$G261-$F261+1) | I261: =IF($F261="","",IF(MONTH($F261)>=4,YEAR($F261)&"-"&TEXT(YEAR($F261)+1-2000,"00"),YEAR($F261)-1&"-"&TEXT(YEAR($F261)-2000,"00"))) | J261: 61 | K261: =IFERROR($L261/$J261,"") | L261: 2562 | M261: =IFERROR($L261/$H261,"") | N261: 45700 | O261: =IF($N261="","No","Yes") | P261: =IF(OR($F261="",$G261=""),0,IF(AND($F261<=README!$B$4,README!$B$4<=$G261),1,0)) | Q261: =IF(OR($F261="",$G261=""),0,IF(AND($F261<=DATE(README!$B$5,12,31),$G261>=DATE(README!$B$5,1,1)),1,0)) | R261: GUP-VEH0008 | S261: 45461 | T261: 541 | U261: VEHICLE | V261: T | W261: VIVEK B
A262: TN57BQ3434 | B262: SOCKS | C262: ADBLU | D262: ADBLU | E262: YEARLY | F262: 45383 | G262: 45747 | H262: =IF(OR($F262="",$G262=""),"",$G262-$F262+1) | I262: =IF($F262="","",IF(MONTH($F262)>=4,YEAR($F262)&"-"&TEXT(YEAR($F262)+1-2000,"00"),YEAR($F262)-1&"-"&TEXT(YEAR($F262)-2000,"00"))) | J262: 61 | K262: =IFERROR($L262/$J262,"") | L262: 2562 | M262: =IFERROR($L262/$H262,"") | N262: 45700 | O262: =IF($N262="","No","Yes") | P262: =IF(OR($F262="",$G262=""),0,IF(AND($F262<=README!$B$4,README!$B$4<=$G262),1,0)) | Q262: =IF(OR($F262="",$G262=""),0,IF(AND($F262<=DATE(README!$B$5,12,31),$G262>=DATE(README!$B$5,1,1)),1,0)) | R262: GUP-VEH0008 | S262: 45461 | T262: 541 | U262: VEHICLE | V262: T | W262: VIVEK B
A263: TN57BQ3434 | B263: SOCKS | C263: ROAD TAX | D263: ROAD TAX | E263: YEARLY | F263: 45383 | G263: 45747 | H263: =IF(OR($F263="",$G263=""),"",$G263-$F263+1) | I263: =IF($F263="","",IF(MONTH($F263)>=4,YEAR($F263)&"-"&TEXT(YEAR($F263)+1-2000,"00"),YEAR($F263)-1&"-"&TEXT(YEAR($F263)-2000,"00"))) | J263: 32724 | K263: =IFERROR($L263/$J263,"") | L263: 32724 | M263: =IFERROR($L263/$H263,"") | N263: 45569 | O263: =IF($N263="","No","Yes") | P263: =IF(OR($F263="",$G263=""),0,IF(AND($F263<=README!$B$4,README!$B$4<=$G263),1,0)) | Q263: =IF(OR($F263="",$G263=""),0,IF(AND($F263<=DATE(README!$B$5,12,31),$G263>=DATE(README!$B$5,1,1)),1,0)) | R263: GUP-VEH0011 | S263: 45477 | T263: 548 | U263: VEHICLE | V263: T | W263: VIVEK B
A264: TN57BQ3434 | B264: SOCKS | C264: ROAD TAX | D264: ROAD TAX | E264: YEARLY | F264: 45383 | G264: 45747 | H264: =IF(OR($F264="",$G264=""),"",$G264-$F264+1) | I264: =IF($F264="","",IF(MONTH($F264)>=4,YEAR($F264)&"-"&TEXT(YEAR($F264)+1-2000,"00"),YEAR($F264)-1&"-"&TEXT(YEAR($F264)-2000,"00"))) | J264: 32724 | K264: =IFERROR($L264/$J264,"") | L264: 32724 | M264: =IFERROR($L264/$H264,"") | N264: 45649 | O264: =IF($N264="","No","Yes") | P264: =IF(OR($F264="",$G264=""),0,IF(AND($F264<=README!$B$4,README!$B$4<=$G264),1,0)) | Q264: =IF(OR($F264="",$G264=""),0,IF(AND($F264<=DATE(README!$B$5,12,31),$G264>=DATE(README!$B$5,1,1)),1,0)) | R264: GUP-VEH0011 | S264: 45477 | T264: 548 | U264: VEHICLE | V264: T | W264: VIVEK B
A265: TN57BQ3434 | B265: SOCKS | C265: ROAD TAX | D265: ROAD TAX | E265: YEARLY | F265: 45383 | G265: 45747 | H265: =IF(OR($F265="",$G265=""),"",$G265-$F265+1) | I265: =IF($F265="","",IF(MONTH($F265)>=4,YEAR($F265)&"-"&TEXT(YEAR($F265)+1-2000,"00"),YEAR($F265)-1&"-"&TEXT(YEAR($F265)-2000,"00"))) | J265: 32724 | K265: =IFERROR($L265/$J265,"") | L265: 32724 | M265: =IFERROR($L265/$H265,"") | N265: 45481 | O265: =IF($N265="","No","Yes") | P265: =IF(OR($F265="",$G265=""),0,IF(AND($F265<=README!$B$4,README!$B$4<=$G265),1,0)) | Q265: =IF(OR($F265="",$G265=""),0,IF(AND($F265<=DATE(README!$B$5,12,31),$G265>=DATE(README!$B$5,1,1)),1,0)) | R265: GUP-VEH0011 | S265: 45477 | T265: 548 | U265: VEHICLE | V265: T | W265: VIVEK B
A266: TN57BQ3434 | B266: SOCKS | C266: TYRE | D266: TYRE | E266: YEARLY | F266: 45383 | G266: 45747 | H266: =IF(OR($F266="",$G266=""),"",$G266-$F266+1) | I266: =IF($F266="","",IF(MONTH($F266)>=4,YEAR($F266)&"-"&TEXT(YEAR($F266)+1-2000,"00"),YEAR($F266)-1&"-"&TEXT(YEAR($F266)-2000,"00"))) | J266: 30200 | K266: =IFERROR($L266/$J266,"") | L266: 30200 | M266: =IFERROR($L266/$H266,"") | N266: 45590 | O266: =IF($N266="","No","Yes") | P266: =IF(OR($F266="",$G266=""),0,IF(AND($F266<=README!$B$4,README!$B$4<=$G266),1,0)) | Q266: =IF(OR($F266="",$G266=""),0,IF(AND($F266<=DATE(README!$B$5,12,31),$G266>=DATE(README!$B$5,1,1)),1,0)) | R266: GUP-VEH0006 | S266: 45442 | T266: 522 | U266: VEHICLE | V266: T | W266: VIVEK B
A267: TN57BQ3434 | B267: SOCKS | C267: VEHICLE INSURANCE | D267: VEHICLE INSURANCE | E267: YEARLY | F267: 45383 | G267: 45747 | H267: =IF(OR($F267="",$G267=""),"",$G267-$F267+1) | I267: =IF($F267="","",IF(MONTH($F267)>=4,YEAR($F267)&"-"&TEXT(YEAR($F267)+1-2000,"00"),YEAR($F267)-1&"-"&TEXT(YEAR($F267)-2000,"00"))) | J267: 79453 | K267: =IFERROR($L267/$J267,"") | L267: 79453 | M267: =IFERROR($L267/$H267,"") | N267: 45541 | O267: =IF($N267="","No","Yes") | P267: =IF(OR($F267="",$G267=""),0,IF(AND($F267<=README!$B$4,README!$B$4<=$G267),1,0)) | Q267: =IF(OR($F267="",$G267=""),0,IF(AND($F267<=DATE(README!$B$5,12,31),$G267>=DATE(README!$B$5,1,1)),1,0)) | R267: GUP-VEH0013 | S267: 45478 | T267: 550 | U267: VEHICLE | V267: T | W267: VIVEK B
A268: TN57BQ3434 | B268: SOCKS | C268: ROAD TAX | D268: ROAD TAX | E268: QUARTER - I | F268: 45748 | G268: 45838 | H268: =IF(OR($F268="",$G268=""),"",$G268-$F268+1) | I268: =IF($F268="","",IF(MONTH($F268)>=4,YEAR($F268)&"-"&TEXT(YEAR($F268)+1-2000,"00"),YEAR($F268)-1&"-"&TEXT(YEAR($F268)-2000,"00"))) | J268: 32724 | K268: =IFERROR($L268/$J268,"") | L268: 32724 | M268: =IFERROR($L268/$H268,"") | N268: 46030 | O268: =IF($N268="","No","Yes") | P268: =IF(OR($F268="",$G268=""),0,IF(AND($F268<=README!$B$4,README!$B$4<=$G268),1,0)) | Q268: =IF(OR($F268="",$G268=""),0,IF(AND($F268<=DATE(README!$B$5,12,31),$G268>=DATE(README!$B$5,1,1)),1,0)) | R268: GUP-VEH0014 | S268: 45748 | T268: 609 | U268: VEHICLE | V268: T | W268: VIVEK B
A269: TN57BQ3434 | B269: SOCKS | C269: RTO EXPENSE | D269: RTO EXPENSE | E269: YEARLY | F269: 45748 | G269: 46112 | H269: =IF(OR($F269="",$G269=""),"",$G269-$F269+1) | I269: =IF($F269="","",IF(MONTH($F269)>=4,YEAR($F269)&"-"&TEXT(YEAR($F269)+1-2000,"00"),YEAR($F269)-1&"-"&TEXT(YEAR($F269)-2000,"00"))) | J269: 10400 | K269: =IFERROR($L269/$J269,"") | L269: 10400 | M269: =IFERROR($L269/$H269,"") | N269: 46028 | O269: =IF($N269="","No","Yes") | P269: =IF(OR($F269="",$G269=""),0,IF(AND($F269<=README!$B$4,README!$B$4<=$G269),1,0)) | Q269: =IF(OR($F269="",$G269=""),0,IF(AND($F269<=DATE(README!$B$5,12,31),$G269>=DATE(README!$B$5,1,1)),1,0)) | R269: GUP-VEH0022 | S269: 45834 | T269: 655 | U269: VEHICLE | V269: T | W269: VIVEK B
... A283: TN57BQ3636 | B283: SOCKS | C283: RTO EXPENSE | D283: ADDITIONAL DISTRICT PERMIT | E283: YEARLY | F283: 45383 | G283: 45747 | H283: =IF(OR($F283="",$G283=""),"",$G283-$F283+1) | I283: =IF($F283="","",IF(MONTH($F283)>=4,YEAR($F283)&"-"&TEXT(YEAR($F283)+1-2000,"00"),YEAR($F283)-1&"-"&TEXT(YEAR($F283)-2000,"00"))) | J283: 7000 | K283: =IFERROR($L283/$J283,"") | L283: 7000 | M283: =IFERROR($L283/$H283,"") | N283: 45699 | O283: =IF($N283="","No","Yes") | P283: =IF(OR($F283="",$G283=""),0,IF(AND($F283<=README!$B$4,README!$B$4<=$G283),1,0)) | Q283: =IF(OR($F283="",$G283=""),0,IF(AND($F283<=DATE(README!$B$5,12,31),$G283>=DATE(README!$B$5,1,1)),1,0)) | R283: GUP-VEH0010 | S283: 45475 | T283: 547 | U283: VEHICLE | V283: T | W283: VIVEK B
A284: TN57BQ3636 | B284: SOCKS | C284: TYRE | D284: TYRE | E284: YEARLY | F284: 45383 | G284: 45747 | H284: =IF(OR($F284="",$G284=""),"",$G284-$F284+1) | I284: =IF($F284="","",IF(MONTH($F284)>=4,YEAR($F284)&"-"&TEXT(YEAR($F284)+1-2000,"00"),YEAR($F284)-1&"-"&TEXT(YEAR($F284)-2000,"00"))) | J284: 19200 | K284: =IFERROR($L284/$J284,"") | L284: 0 | M284: =IFERROR($L284/$H284,"") | O284: =IF($N284="","No","Yes") | P284: =IF(OR($F284="",$G284=""),0,IF(AND($F284<=README!$B$4,README!$B$4<=$G284),1,0)) | Q284: =IF(OR($F284="",$G284=""),0,IF(AND($F284<=DATE(README!$B$5,12,31),$G284>=DATE(README!$B$5,1,1)),1,0)) | R284: GUP-VEH0006 | S284: 45442 | T284: 522 | U284: VEHICLE | V284: T | W284: VIVEK B
A285: TN57BQ3636 | B285: SOCKS | C285: VEHICLE INSURANCE | D285: VEHICLE INSURANCE | E285: YEARLY | F285: 45383 | G285: 45747 | H285: =IF(OR($F285="",$G285=""),"",$G285-$F285+1) | I285: =IF($F285="","",IF(MONTH($F285)>=4,YEAR($F285)&"-"&TEXT(YEAR($F285)+1-2000,"00"),YEAR($F285)-1&"-"&TEXT(YEAR($F285)-2000,"00"))) | J285: 58327 | K285: =IFERROR($L285/$J285,"") | L285: 58327 | M285: =IFERROR($L285/$H285,"") | N285: 45664 | O285: =IF($N285="","No","Yes") | P285: =IF(OR($F285="",$G285=""),0,IF(AND($F285<=README!$B$4,README!$B$4<=$G285),1,0)) | Q285: =IF(OR($F285="",$G285=""),0,IF(AND($F285<=DATE(README!$B$5,12,31),$G285>=DATE(README!$B$5,1,1)),1,0)) | R285: GUP-VEH0013 | S285: 45478 | T285: 550 | U285: VEHICLE | V285: T | W285: VIVEK B
A286: TN57BQ3636 | B286: SOCKS | C286: VEHICLE OUTSIDE SERVICES | D286: GLASS STICKERS | E286: YEARLY | F286: 45383 | G286: 45747 | H286: =IF(OR($F286="",$G286=""),"",$G286-$F286+1) | I286: =IF($F286="","",IF(MONTH($F286)>=4,YEAR($F286)&"-"&TEXT(YEAR($F286)+1-2000,"00"),YEAR($F286)-1&"-"&TEXT(YEAR($F286)-2000,"00"))) | J286: 1770 | K286: =IFERROR($L286/$J286,"") | L286: 1770 | M286: =IFERROR($L286/$H286,"") | N286: 45649 | O286: =IF($N286="","No","Yes") | P286: =IF(OR($F286="",$G286=""),0,IF(AND($F286<=README!$B$4,README!$B$4<=$G286),1,0)) | Q286: =IF(OR($F286="",$G286=""),0,IF(AND($F286<=DATE(README!$B$5,12,31),$G286>=DATE(README!$B$5,1,1)),1,0)) | R286: GUP-VEH0012 | S286: 45477 | T286: 549 | U286: VEHICLE | V286: T | W286: VIVEK B
A287: TN57BQ3636 | B287: SOCKS | C287: ROAD TAX | D287: ROAD TAX | E287: QUARTER - I | F287: 45748 | G287: 45838 | H287: =IF(OR($F287="",$G287=""),"",$G287-$F287+1) | I287: =IF($F287="","",IF(MONTH($F287)>=4,YEAR($F287)&"-"&TEXT(YEAR($F287)+1-2000,"00"),YEAR($F287)-1&"-"&TEXT(YEAR($F287)-2000,"00"))) | J287: 21816 | K287: =IFERROR($L287/$J287,"") | L287: 21816 | M287: =IFERROR($L287/$H287,"") | N287: 46030 | O287: =IF($N287="","No","Yes") | P287: =IF(OR($F287="",$G287=""),0,IF(AND($F287<=README!$B$4,README!$B$4<=$G287),1,0)) | Q287: =IF(OR($F287="",$G287=""),0,IF(AND($F287<=DATE(README!$B$5,12,31),$G287>=DATE(README!$B$5,1,1)),1,0)) | R287: GUP-VEH0014 | S287: 45748 | T287: 609 | U287: VEHICLE | V287: T | W287: VIVEK B
A288: TN57BQ3636 | B288: SOCKS | C288: ROAD TAX | D288: ROAD TAX | E288: QUARTER - II | F288: 45839 | G288: 45930 | H288: =IF(OR($F288="",$G288=""),"",$G288-$F288+1) | I288: =IF($F288="","",IF(MONTH($F288)>=4,YEAR($F288)&"-"&TEXT(YEAR($F288)+1-2000,"00"),YEAR($F288)-1&"-"&TEXT(YEAR($F288)-2000,"00"))) | J288: 21816 | K288: =IFERROR($L288/$J288,"") | L288: 21816 | M288: =IFERROR($L288/$H288,"") | N288: 46030 | O288: =IF($N288="","No","Yes") | P288: =IF(OR($F288="",$G288=""),0,IF(AND($F288<=README!$B$4,README!$B$4<=$G288),1,0)) | Q288: =IF(OR($F288="",$G288=""),0,IF(AND($F288<=DATE(README!$B$5,12,31),$G288>=DATE(README!$B$5,1,1)),1,0)) | R288: GUP-VEH0014 | S288: 45748 | T288: 609 | U288: VEHICLE | V288: T | W288: VIVEK B
A289: TN57BQ3636 | B289: SOCKS | C289: ROAD TAX | D289: ROAD TAX | E289: QUARTER - III | F289: 45931 | G289: 46022 | H289: =IF(OR($F289="",$G289=""),"",$G289-$F289+1) | I289: =IF($F289="","",IF(MONTH($F289)>=4,YEAR($F289)&"-"&TEXT(YEAR($F289)+1-2000,"00"),YEAR($F289)-1&"-"&TEXT(YEAR($F289)-2000,"00"))) | J289: 21826 | K289: =IFERROR($L289/$J289,"") | L289: 21826 | M289: =IFERROR($L289/$H289,"") | N289: 46030 | O289: =IF($N289="","No","Yes") | P289: =IF(OR($F289="",$G289=""),0,IF(AND($F289<=README!$B$4,README!$B$4<=$G289),1,0)) | Q289: =IF(OR($F289="",$G289=""),0,IF(AND($F289<=DATE(README!$B$5,12,31),$G289>=DATE(README!$B$5,1,1)),1,0)) | R289: GUP-VEH0014 | S289: 45748 | T289: 609 | U289: VEHICLE | V289: T | W289: VIVEK B
A290: TN57BQ3636 | B290: SOCKS | C290: ROAD TAX | D290: ROAD TAX | E290: QUARTER - IV | F290: 46023 | G290: 46112 | H290: =IF(OR($F290="",$G290=""),"",$G290-$F290+1) | I290: =IF($F290="","",IF(MONTH($F290)>=4,YEAR($F290)&"-"&TEXT(YEAR($F290)+1-2000,"00"),YEAR($F290)-1&"-"&TEXT(YEAR($F290)-2000,"00"))) | J290: 21826 | K290: =IFERROR($L290/$J290,"") | L290: 21826 | M290: =IFERROR($L290/$H290,"") | N290: 46030 | O290: =IF($N290="","No","Yes") | P290: =IF(OR($F290="",$G290=""),0,IF(AND($F290<=README!$B$4,README!$B$4<=$G290),1,0)) | Q290: =IF(OR($F290="",$G290=""),0,IF(AND($F290<=DATE(README!$B$5,12,31),$G290>=DATE(README!$B$5,1,1)),1,0)) | R290: GUP-VEH0014 | S290: 45748 | T290: 609 | U290: VEHICLE | V290: T | W290: VIVEK B
A291: TN57BQ3636 | B291: SOCKS | C291: VEHICLE INSURANCE | D291: VEHICLE INSURANCE | E291: JANUARY | F291: 46023 | G291: 46053 | H291: =IF(OR($F291="",$G291=""),"",$G291-$F291+1) | I291: =IF($F291="","",IF(MONTH($F291)>=4,YEAR($F291)&"-"&TEXT(YEAR($F291)+1-2000,"00"),YEAR($F291)-1&"-"&TEXT(YEAR($F291)-2000,"00"))) | J291: 58159 | K291: =IFERROR($L291/$J291,"") | L291: 58159 | M291: =IFERROR($L291/$H291,"") | N291: 46056 | O291: =IF($N291="","No","Yes") | P291: =IF(OR($F291="",$G291=""),0,IF(AND($F291<=README!$B$4,README!$B$4<=$G291),1,0)) | Q291: =IF(OR($F291="",$G291=""),0,IF(AND($F291<=DATE(README!$B$5,12,31),$G291>=DATE(README!$B$5,1,1)),1,0)) | R291: GUP-VEH0020 | S291: 45799 | T291: 645 | U291: VEHICLE | V291: T | W291: VIVEK B
A292: TN57BQ3636 | B292: GENERAL | C292: VEHICLE OUTSIDE SERVICES | D292: MAINTENANCE SERVICE | E292: JANUARY | F292: 46023 | G292: 46053 | H292: =IF(OR($F292="",$G292=""),"",$G292-$F292+1) | I292: =IF($F292="","",IF(MONTH($F292)>=4,YEAR($F292)&"-"&TEXT(YEAR($F292)+1-2000,"00"),YEAR($F292)-1&"-"&TEXT(YEAR($F292)-2000,"00"))) | J292: 4633 | K292: =IFERROR($L292/$J292,"") | L292: 4633 | M292: =IFERROR($L292/$H292,"") | N292: 46050 | O292: =IF($N292="","No","Yes") | P292: =IF(OR($F292="",$G292=""),0,IF(AND($F292<=README!$B$4,README!$B$4<=$G292),1,0)) | Q292: =IF(OR($F292="",$G292=""),0,IF(AND($F292<=DATE(README!$B$5,12,31),$G292>=DATE(README!$B$5,1,1)),1,0)) | R292: GUP-VEH0019 | S292: 45777 | T292: 638 | U292: VEHICLE | V292: T | W292: VIVEK B
A293: TN57BQ3636 | B293: SOCKS | C293: TYRE | D293: TYRE | E293: FEBRUARY | F293: 46054 | G293: 46081 | H293: =IF(OR($F293="",$G293=""),"",$G293-$F293+1) | I293: =IF($F293="","",IF(MONTH($F293)>=4,YEAR($F293)&"-"&TEXT(YEAR($F293)+1-2000,"00"),YEAR($F293)-1&"-"&TEXT(YEAR($F293)-2000,"00"))) | J293: 19200 | K293: =IFERROR($L293/$J293,"") | L293: 19200 | M293: =IFERROR($L293/$H293,"") | N293: 46072 | O293: =IF($N293="","No","Yes") | P293: =IF(OR($F293="",$G293=""),0,IF(AND($F293<=README!$B$4,README!$B$4<=$G293),1,0)) | Q293: =IF(OR($F293="",$G293=""),0,IF(AND($F293<=DATE(README!$B$5,12,31),$G293>=DATE(README!$B$5,1,1)),1,0)) | R293: GUP-VEH0025 | S293: 45957 | T293: 726 | U293: VEHICLE | V293: T | W293: VIVEK B
A294: TN57BQ3636 | B294: SOCKS | C294: FC WORK | D294: FC WORK | E294: YEARLY | F294: 46113 | G294: 46477 | H294: =IF(OR($F294="",$G294=""),"",$G294-$F294+1) | I294: =IF($F294="","",IF(MONTH($F294)>=4,YEAR($F294)&"-"&TEXT(YEAR($F294)+1-2000,"00"),YEAR($F294)-1&"-"&TEXT(YEAR($F294)-2000,"00"))) | J294: 121150 | K294: =IFERROR($L294/$J294,"") | L294: 121150 | M294: =IFERROR($L294/$H294,"") | N294: 46186 | O294: =IF($N294="","No","Yes") | P294: =IF(OR($F294="",$G294=""),0,IF(AND($F294<=README!$B$4,README!$B$4<=$G294),1,0)) | Q294: =IF(OR($F294="",$G294=""),0,IF(AND($F294<=DATE(README!$B$5,12,31),$G294>=DATE(README!$B$5,1,1)),1,0)) | R294: GUP-VEH0032 | S294: 46118 | T294: 813 | U294: VEHICLE | V294: T | W294: VIVEK B
A295: TN57BQ3636 | B295: SOCKS | C295: ROAD TAX | D295: ROAD TAX | E295: QUARTER - I | F295: 46113 | G295: 46203 | H295: =IF(OR($F295="",$G295=""),"",$G295-$F295+1) | I295: =IF($F295="","",IF(MONTH($F295)>=4,YEAR($F295)&"-"&TEXT(YEAR($F295)+1-2000,"00"),YEAR($F295)-1&"-"&TEXT(YEAR($F295)-2000,"00"))) | J295: 21826 | K295: =IFERROR($L295/$J295,"") | L295: 21826 | M295: =IFERROR($L295/$H295,"") | N295: 46088 | O295: =IF($N295="","No","Yes") | P295: =IF(OR($F295="",$G295=""),0,IF(AND($F295<=README!$B$4,README!$B$4<=$G295),1,0)) | Q295: =IF(OR($F295="",$G295=""),0,IF(AND($F295<=DATE(README!$B$5,12,31),$G295>=DATE(README!$B$5,1,1)),1,0)) | R295: GUP-VEH0030 | S295: 46113 | T295: 796 | U295: VEHICLE | V295: T | W295: VIVEK B
A296: TN57BQ3636 | B296: SOCKS | C296: RTO EXPENSE | D296: RTO EXPENSES - FC | E296: YEARLY | F296: 46113 | G296: 46477 | H296: =IF(OR($F296="",$G296=""),"",$G296-$F296+1) | I296: =IF($F296="","",IF(MONTH($F296)>=4,YEAR($F296)&"-"&TEXT(YEAR($F296)+1-2000,"00"),YEAR($F296)-1&"-"&TEXT(YEAR($F296)-2000,"00"))) | J296: 7500 | K296: =IFERROR($L296/$J296,"") | L296: 7500 | M296: =IFERROR($L296/$H296,"") | N296: 46121 | O296: =IF($N296="","No","Yes") | P296: =IF(OR($F296="",$G296=""),0,IF(AND($F296<=README!$B$4,README!$B$4<=$G296),1,0)) | Q296: =IF(OR($F296="",$G296=""),0,IF(AND($F296<=DATE(README!$B$5,12,31),$G296>=DATE(README!$B$5,1,1)),1,0)) | R296: GUP-VEH0033 | S296: 46118 | T296: 814 | U296: VEHICLE | V296: T | W296: VIVEK B
... A326: TN57BS3142 | B326: WOVEN | C326: VEHICLE INSURANCE | D326: VEHICLE INSURANCE | E326: YEARLY | F326: 45748 | G326: 46112 | H326: =IF(OR($F326="",$G326=""),"",$G326-$F326+1) | I326: =IF($F326="","",IF(MONTH($F326)>=4,YEAR($F326)&"-"&TEXT(YEAR($F326)+1-2000,"00"),YEAR($F326)-1&"-"&TEXT(YEAR($F326)-2000,"00"))) | J326: 34475 | K326: =IFERROR($L326/$J326,"") | L326: 34475 | M326: =IFERROR($L326/$H326,"") | N326: 45864 | O326: =IF($N326="","No","Yes") | P326: =IF(OR($F326="",$G326=""),0,IF(AND($F326<=README!$B$4,README!$B$4<=$G326),1,0)) | Q326: =IF(OR($F326="",$G326=""),0,IF(AND($F326<=DATE(README!$B$5,12,31),$G326>=DATE(README!$B$5,1,1)),1,0)) | R326: GUT-VEH0019 | S326: 45799 | T326: 5 | U326: VEHICLE | V326: T | W326: VIVEK B
A327: TN57BS3142 | C327: VEHICLE OUTSIDE SERVICES | D327: MAINTENANCE SERVICE | E327: YEARLY | F327: 45748 | G327: 46112 | H327: =IF(OR($F327="",$G327=""),"",$G327-$F327+1) | I327: =IF($F327="","",IF(MONTH($F327)>=4,YEAR($F327)&"-"&TEXT(YEAR($F327)+1-2000,"00"),YEAR($F327)-1&"-"&TEXT(YEAR($F327)-2000,"00"))) | J327: 12704 | K327: =IFERROR($L327/$J327,"") | L327: 12704 | M327: =IFERROR($L327/$H327,"") | N327: 45875 | O327: =IF($N327="","No","Yes") | P327: =IF(OR($F327="",$G327=""),0,IF(AND($F327<=README!$B$4,README!$B$4<=$G327),1,0)) | Q327: =IF(OR($F327="",$G327=""),0,IF(AND($F327<=DATE(README!$B$5,12,31),$G327>=DATE(README!$B$5,1,1)),1,0)) | R327: GUT-VEH0021 | S327: 45812 | T327: 5 | U327: VEHICLE | V327: T | W327: VIVEK B
A328: TN57BS3142 | C328: VEHICLE OUTSIDE SERVICES | D328: MAINTENANCE SERVICE - 2 | E328: FEBRUARY | F328: 46054 | G328: 46081 | H328: =IF(OR($F328="",$G328=""),"",$G328-$F328+1) | I328: =IF($F328="","",IF(MONTH($F328)>=4,YEAR($F328)&"-"&TEXT(YEAR($F328)+1-2000,"00"),YEAR($F328)-1&"-"&TEXT(YEAR($F328)-2000,"00"))) | J328: 9712 | K328: =IFERROR($L328/$J328,"") | L328: 9712 | M328: =IFERROR($L328/$H328,"") | N328: 46065 | O328: =IF($N328="","No","Yes") | P328: =IF(OR($F328="",$G328=""),0,IF(AND($F328<=README!$B$4,README!$B$4<=$G328),1,0)) | Q328: =IF(OR($F328="",$G328=""),0,IF(AND($F328<=DATE(README!$B$5,12,31),$G328>=DATE(README!$B$5,1,1)),1,0)) | R328: GUT-VEH0021 | S328: 45812 | T328: 5 | U328: VEHICLE | V328: T | W328: VIVEK B
A329: TN57BS3142 | B329: WOVEN | C329: VEHICLE INSURANCE | D329: VEHICLE INSURANCE | E329: YEARLY | F329: 46113 | G329: 46477 | H329: =IF(OR($F329="",$G329=""),"",$G329-$F329+1) | I329: =IF($F329="","",IF(MONTH($F329)>=4,YEAR($F329)&"-"&TEXT(YEAR($F329)+1-2000,"00"),YEAR($F329)-1&"-"&TEXT(YEAR($F329)-2000,"00"))) | J329: 34474 | K329: =IFERROR($L329/$J329,"") | L329: 34474 | M329: =IFERROR($L329/$H329,"") | N329: 46219 | O329: =IF($N329="","No","Yes") | P329: =IF(OR($F329="",$G329=""),0,IF(AND($F329<=README!$B$4,README!$B$4<=$G329),1,0)) | Q329: =IF(OR($F329="",$G329=""),0,IF(AND($F329<=DATE(README!$B$5,12,31),$G329>=DATE(README!$B$5,1,1)),1,0)) | R329: GUT-VEH0035 | S329: 46162 | T329: 5 | U329: VEHICLE | V329: T | W329: VIVEK B
A330: TN57BS3434 | B330: WOVEN | C330: ADBLU | D330: ADBLU | E330: YEARLY | F330: 45383 | G330: 45747 | H330: =IF(OR($F330="",$G330=""),"",$G330-$F330+1) | I330: =IF($F330="","",IF(MONTH($F330)>=4,YEAR($F330)&"-"&TEXT(YEAR($F330)+1-2000,"00"),YEAR($F330)-1&"-"&TEXT(YEAR($F330)-2000,"00"))) | J330: 61 | K330: =IFERROR($L330/$J330,"") | L330: 3172 | M330: =IFERROR($L330/$H330,"") | N330: 45602 | O330: =IF($N330="","No","Yes") | P330: =IF(OR($F330="",$G330=""),0,IF(AND($F330<=README!$B$4,README!$B$4<=$G330),1,0)) | Q330: =IF(OR($F330="",$G330=""),0,IF(AND($F330<=DATE(README!$B$5,12,31),$G330>=DATE(README!$B$5,1,1)),1,0)) | R330: GUT-VEH0008 | S330: 45475 | T330: 3 | U330: VEHICLE | V330: T | W330: VIVEK B
A331: TN57BS3434 | B331: WOVEN | C331: ADBLU | D331: ADBLU | E331: YEARLY | F331: 45383 | G331: 45747 | H331: =IF(OR($F331="",$G331=""),"",$G331-$F331+1) | I331: =IF($F331="","",IF(MONTH($F331)>=4,YEAR($F331)&"-"&TEXT(YEAR($F331)+1-2000,"00"),YEAR($F331)-1&"-"&TEXT(YEAR($F331)-2000,"00"))) | J331: 61 | K331: =IFERROR($L331/$J331,"") | L331: 3172 | M331: =IFERROR($L331/$H331,"") | N331: 45623 | O331: =IF($N331="","No","Yes") | P331: =IF(OR($F331="",$G331=""),0,IF(AND($F331<=README!$B$4,README!$B$4<=$G331),1,0)) | Q331: =IF(OR($F331="",$G331=""),0,IF(AND($F331<=DATE(README!$B$5,12,31),$G331>=DATE(README!$B$5,1,1)),1,0)) | R331: GUT-VEH0008 | S331: 45475 | T331: 3 | U331: VEHICLE | V331: T | W331: VIVEK B
A332: TN57BS3434 | B332: WOVEN | C332: ADBLU | D332: ADBLU | E332: YEARLY | F332: 45383 | G332: 45747 | H332: =IF(OR($F332="",$G332=""),"",$G332-$F332+1) | I332: =IF($F332="","",IF(MONTH($F332)>=4,YEAR($F332)&"-"&TEXT(YEAR($F332)+1-2000,"00"),YEAR($F332)-1&"-"&TEXT(YEAR($F332)-2000,"00"))) | J332: 61 | K332: =IFERROR($L332/$J332,"") | L332: 3172 | M332: =IFERROR($L332/$H332,"") | N332: 45479 | O332: =IF($N332="","No","Yes") | P332: =IF(OR($F332="",$G332=""),0,IF(AND($F332<=README!$B$4,README!$B$4<=$G332),1,0)) | Q332: =IF(OR($F332="",$G332=""),0,IF(AND($F332<=DATE(README!$B$5,12,31),$G332>=DATE(README!$B$5,1,1)),1,0)) | R332: GUT-VEH0008 | S332: 45475 | T332: 3 | U332: VEHICLE | V332: T | W332: VIVEK B
A333: TN57BS3434 | B333: WOVEN | C333: ADBLU | D333: ADBLU | E333: YEARLY | F333: 45383 | G333: 45747 | H333: =IF(OR($F333="",$G333=""),"",$G333-$F333+1) | I333: =IF($F333="","",IF(MONTH($F333)>=4,YEAR($F333)&"-"&TEXT(YEAR($F333)+1-2000,"00"),YEAR($F333)-1&"-"&TEXT(YEAR($F333)-2000,"00"))) | J333: 61 | K333: =IFERROR($L333/$J333,"") | L333: 3172 | M333: =IFERROR($L333/$H333,"") | N333: 45700 | O333: =IF($N333="","No","Yes") | P333: =IF(OR($F333="",$G333=""),0,IF(AND($F333<=README!$B$4,README!$B$4<=$G333),1,0)) | Q333: =IF(OR($F333="",$G333=""),0,IF(AND($F333<=DATE(README!$B$5,12,31),$G333>=DATE(README!$B$5,1,1)),1,0)) | R333: GUT-VEH0008 | S333: 45475 | T333: 3 | U333: VEHICLE | V333: T | W333: VIVEK B
A334: TN57BS3434 | B334: WOVEN | C334: ADBLU | D334: ADBLU | E334: YEARLY | F334: 45383 | G334: 45747 | H334: =IF(OR($F334="",$G334=""),"",$G334-$F334+1) | I334: =IF($F334="","",IF(MONTH($F334)>=4,YEAR($F334)&"-"&TEXT(YEAR($F334)+1-2000,"00"),YEAR($F334)-1&"-"&TEXT(YEAR($F334)-2000,"00"))) | J334: 61 | K334: =IFERROR($L334/$J334,"") | L334: 3172 | M334: =IFERROR($L334/$H334,"") | N334: 45700 | O334: =IF($N334="","No","Yes") | P334: =IF(OR($F334="",$G334=""),0,IF(AND($F334<=README!$B$4,README!$B$4<=$G334),1,0)) | Q334: =IF(OR($F334="",$G334=""),0,IF(AND($F334<=DATE(README!$B$5,12,31),$G334>=DATE(README!$B$5,1,1)),1,0)) | R334: GUT-VEH0008 | S334: 45475 | T334: 3 | U334: VEHICLE | V334: T | W334: VIVEK B
A335: TN57BS3434 | B335: WOVEN | C335: FC WORK | D335: FC WORK | E335: YEARLY | F335: 45383 | G335: 45747 | H335: =IF(OR($F335="",$G335=""),"",$G335-$F335+1) | I335: =IF($F335="","",IF(MONTH($F335)>=4,YEAR($F335)&"-"&TEXT(YEAR($F335)+1-2000,"00"),YEAR($F335)-1&"-"&TEXT(YEAR($F335)-2000,"00"))) | J335: 35000 | K335: =IFERROR($L335/$J335,"") | L335: 35000 | M335: =IFERROR($L335/$H335,"") | N335: 45638 | O335: =IF($N335="","No","Yes") | P335: =IF(OR($F335="",$G335=""),0,IF(AND($F335<=README!$B$4,README!$B$4<=$G335),1,0)) | Q335: =IF(OR($F335="",$G335=""),0,IF(AND($F335<=DATE(README!$B$5,12,31),$G335>=DATE(README!$B$5,1,1)),1,0)) | R335: GUT-VEH0009 | S335: 45475 | T335: 3 | U335: VEHICLE | V335: T | W335: VIVEK B
A336: TN57BS3434 | B336: WOVEN | C336: ROAD TAX | D336: ROAD TAX | E336: YEARLY | F336: 45383 | G336: 45747 | H336: =IF(OR($F336="",$G336=""),"",$G336-$F336+1) | I336: =IF($F336="","",IF(MONTH($F336)>=4,YEAR($F336)&"-"&TEXT(YEAR($F336)+1-2000,"00"),YEAR($F336)-1&"-"&TEXT(YEAR($F336)-2000,"00"))) | J336: 32724 | K336: =IFERROR($L336/$J336,"") | L336: 32724 | M336: =IFERROR($L336/$H336,"") | N336: 45727 | O336: =IF($N336="","No","Yes") | P336: =IF(OR($F336="",$G336=""),0,IF(AND($F336<=README!$B$4,README!$B$4<=$G336),1,0)) | Q336: =IF(OR($F336="",$G336=""),0,IF(AND($F336<=DATE(README!$B$5,12,31),$G336>=DATE(README!$B$5,1,1)),1,0)) | R336: GUT-VEH0016 | S336: 46023 | T336: 5 | U336: VEHICLE | V336: T | W336: VIVEK B
A337: TN57BS3434 | B337: WOVEN | C337: ROAD TAX | D337: ROAD TAX | E337: YEARLY | F337: 45383 | G337: 45747 | H337: =IF(OR($F337="",$G337=""),"",$G337-$F337+1) | I337: =IF($F337="","",IF(MONTH($F337)>=4,YEAR($F337)&"-"&TEXT(YEAR($F337)+1-2000,"00"),YEAR($F337)-1&"-"&TEXT(YEAR($F337)-2000,"00"))) | J337: 32734 | K337: =IFERROR($L337/$J337,"") | L337: 32734 | M337: =IFERROR($L337/$H337,"") | N337: 45910 | O337: =IF($N337="","No","Yes") | P337: =IF(OR($F337="",$G337=""),0,IF(AND($F337<=README!$B$4,README!$B$4<=$G337),1,0)) | Q337: =IF(OR($F337="",$G337=""),0,IF(AND($F337<=DATE(README!$B$5,12,31),$G337>=DATE(README!$B$5,1,1)),1,0)) | R337: GUT-VEH0016 | S337: 46023 | T337: 5 | U337: VEHICLE | V337: T | W337: VIVEK B
A338: TN57BS3434 | B338: WOVEN | C338: ROAD TAX | D338: ROAD TAX | E338: YEARLY | F338: 45383 | G338: 45747 | H338: =IF(OR($F338="",$G338=""),"",$G338-$F338+1) | I338: =IF($F338="","",IF(MONTH($F338)>=4,YEAR($F338)&"-"&TEXT(YEAR($F338)+1-2000,"00"),YEAR($F338)-1&"-"&TEXT(YEAR($F338)-2000,"00"))) | J338: 32724 | K338: =IFERROR($L338/$J338,"") | L338: 32724 | M338: =IFERROR($L338/$H338,"") | N338: 45840 | O338: =IF($N338="","No","Yes") | P338: =IF(OR($F338="",$G338=""),0,IF(AND($F338<=README!$B$4,README!$B$4<=$G338),1,0)) | Q338: =IF(OR($F338="",$G338=""),0,IF(AND($F338<=DATE(README!$B$5,12,31),$G338>=DATE(README!$B$5,1,1)),1,0)) | R338: GUT-VEH0016 | S338: 46023 | T338: 5 | U338: VEHICLE | V338: T | W338: VIVEK B
A339: TN57BS3434 | B339: WOVEN | C339: ROAD TAX | D339: ROAD TAX | E339: YEARLY | F339: 45383 | G339: 45747 | H339: =IF(OR($F339="",$G339=""),"",$G339-$F339+1) | I339: =IF($F339="","",IF(MONTH($F339)>=4,YEAR($F339)&"-"&TEXT(YEAR($F339)+1-2000,"00"),YEAR($F339)-1&"-"&TEXT(YEAR($F339)-2000,"00"))) | J339: 32724 | K339: =IFERROR($L339/$J339,"") | L339: 32724 | M339: =IFERROR($L339/$H339,"") | N339: 45569 | O339: =IF($N339="","No","Yes") | P339: =IF(OR($F339="",$G339=""),0,IF(AND($F339<=README!$B$4,README!$B$4<=$G339),1,0)) | Q339: =IF(OR($F339="",$G339=""),0,IF(AND($F339<=DATE(README!$B$5,12,31),$G339>=DATE(README!$B$5,1,1)),1,0)) | R339: GUT-VEH0011 | S339: 45475 | T339: 3 | U339: VEHICLE | V339: T | W339: VIVEK B
A340: TN57BS3434 | B340: WOVEN | C340: ROAD TAX | D340: ROAD TAX | E340: YEARLY | F340: 45383 | G340: 45747 | H340: =IF(OR($F340="",$G340=""),"",$G340-$F340+1) | I340: =IF($F340="","",IF(MONTH($F340)>=4,YEAR($F340)&"-"&TEXT(YEAR($F340)+1-2000,"00"),YEAR($F340)-1&"-"&TEXT(YEAR($F340)-2000,"00"))) | J340: 32724 | K340: =IFERROR($L340/$J340,"") | L340: 32724 | M340: =IFERROR($L340/$H340,"") | N340: 45481 | O340: =IF($N340="","No","Yes") | P340: =IF(OR($F340="",$G340=""),0,IF(AND($F340<=README!$B$4,README!$B$4<=$G340),1,0)) | Q340: =IF(OR($F340="",$G340=""),0,IF(AND($F340<=DATE(README!$B$5,12,31),$G340>=DATE(README!$B$5,1,1)),1,0)) | R340: GUT-VEH0011 | S340: 45475 | T340: 3 | U340: VEHICLE | V340: T | W340: VIVEK B
... A348: TN57BS3434 | B348: WOVEN | C348: VEHICLE INSURANCE | D348: VEHICLE INSURANCE | E348: YEARLY | F348: 45748 | G348: 46112 | H348: =IF(OR($F348="",$G348=""),"",$G348-$F348+1) | I348: =IF($F348="","",IF(MONTH($F348)>=4,YEAR($F348)&"-"&TEXT(YEAR($F348)+1-2000,"00"),YEAR($F348)-1&"-"&TEXT(YEAR($F348)-2000,"00"))) | J348: 79218 | K348: =IFERROR($L348/$J348,"") | L348: 79218 | M348: =IFERROR($L348/$H348,"") | N348: 45930 | O348: =IF($N348="","No","Yes") | P348: =IF(OR($F348="",$G348=""),0,IF(AND($F348<=README!$B$4,README!$B$4<=$G348),1,0)) | Q348: =IF(OR($F348="",$G348=""),0,IF(AND($F348<=DATE(README!$B$5,12,31),$G348>=DATE(README!$B$5,1,1)),1,0)) | R348: GUT-VEH0019 | S348: 45799 | T348: 5 | U348: VEHICLE | V348: T | W348: VIVEK B
A349: TN57BS3434 | C349: VEHICLE OUTSIDE SERVICES | D349: TINKERING WORK - ACCIDENT | E349: YEARLY | F349: 45748 | G349: 46112 | H349: =IF(OR($F349="",$G349=""),"",$G349-$F349+1) | I349: =IF($F349="","",IF(MONTH($F349)>=4,YEAR($F349)&"-"&TEXT(YEAR($F349)+1-2000,"00"),YEAR($F349)-1&"-"&TEXT(YEAR($F349)-2000,"00"))) | J349: 6500 | K349: =IFERROR($L349/$J349,"") | L349: 6500 | M349: =IFERROR($L349/$H349,"") | N349: 45954 | O349: =IF($N349="","No","Yes") | P349: =IF(OR($F349="",$G349=""),0,IF(AND($F349<=README!$B$4,README!$B$4<=$G349),1,0)) | Q349: =IF(OR($F349="",$G349=""),0,IF(AND($F349<=DATE(README!$B$5,12,31),$G349>=DATE(README!$B$5,1,1)),1,0)) | R349: GUT-VEH0021 | S349: 45812 | T349: 5 | U349: VEHICLE | V349: T | W349: VIVEK B
...

Sheet ByVehicle
A1: Vehicle | B1: Division | C1: ADBLU | D1: FC WORK | E1: ROAD TAX | F1: RTO EXPENSE | G1: TYRE | H1: VEHICLE INSURANCE | I1: VEHICLE OUTSIDE SERVICES | J1: FY total | K1: FY lines | L1: Active on as-of | M1: All-time total | N1: All-time lines
A2: TN57AC3636 | B2: SOCKS | C2: =SUMIFS(CostLines!$L$2:$L$1055,CostLines!$A$2:$A$1055,$A2,CostLines!$C$2:$C$1055,C$1,CostLines!$I$2:$I$1055,README!$B$6) | D2: =SUMIFS(CostLines!$L$2:$L$1055,CostLines!$A$2:$A$1055,$A2,CostLines!$C$2:$C$1055,D$1,CostLines!$I$2:$I$1055,README!$B$6) | E2: =SUMIFS(CostLines!$L$2:$L$1055,CostLines!$A$2:$A$1055,$A2,CostLines!$C$2:$C$1055,E$1,CostLines!$I$2:$I$1055,README!$B$6) | F2: =SUMIFS(CostLines!$L$2:$L$1055,CostLines!$A$2:$A$1055,$A2,CostLines!$C$2:$C$1055,F$1,CostLines!$I$2:$I$1055,README!$B$6) | G2: =SUMIFS(CostLines!$L$2:$L$1055,CostLines!$A$2:$A$1055,$A2,CostLines!$C$2:$C$1055,G$1,CostLines!$I$2:$I$1055,README!$B$6) | H2: =SUMIFS(CostLines!$L$2:$L$1055,CostLines!$A$2:$A$1055,$A2,CostLines!$C$2:$C$1055,H$1,CostLines!$I$2:$I$1055,README!$B$6) | I2: =SUMIFS(CostLines!$L$2:$L$1055,CostLines!$A$2:$A$1055,$A2,CostLines!$C$2:$C$1055,I$1,CostLines!$I$2:$I$1055,README!$B$6) | J2: =SUM(C2:I2) | K2: =COUNTIFS(CostLines!$A$2:$A$1055,$A2,CostLines!$I$2:$I$1055,README!$B$6) | L2: =SUMIFS(CostLines!$L$2:$L$1055,CostLines!$A$2:$A$1055,$A2,CostLines!$P$2:$P$1055,1) | M2: =SUMIFS(CostLines!$L$2:$L$1055,CostLines!$A$2:$A$1055,$A2) | N2: =COUNTIFS(CostLines!$A$2:$A$1055,$A2)
A3: TN57AE3636 | B3: SOCKS | C3: =SUMIFS(CostLines!$L$2:$L$1055,CostLines!$A$2:$A$1055,$A3,CostLines!$C$2:$C$1055,C$1,CostLines!$I$2:$I$1055,README!$B$6) | D3: =SUMIFS(CostLines!$L$2:$L$1055,CostLines!$A$2:$A$1055,$A3,CostLines!$C$2:$C$1055,D$1,CostLines!$I$2:$I$1055,README!$B$6) | E3: =SUMIFS(CostLines!$L$2:$L$1055,CostLines!$A$2:$A$1055,$A3,CostLines!$C$2:$C$1055,E$1,CostLines!$I$2:$I$1055,README!$B$6) | F3: =SUMIFS(CostLines!$L$2:$L$1055,CostLines!$A$2:$A$1055,$A3,CostLines!$C$2:$C$1055,F$1,CostLines!$I$2:$I$1055,README!$B$6) | G3: =SUMIFS(CostLines!$L$2:$L$1055,CostLines!$A$2:$A$1055,$A3,CostLines!$C$2:$C$1055,G$1,CostLines!$I$2:$I$1055,README!$B$6) | H3: =SUMIFS(CostLines!$L$2:$L$1055,CostLines!$A$2:$A$1055,$A3,CostLines!$C$2:$C$1055,H$1,CostLines!$I$2:$I$1055,README!$B$6) | I3: =SUMIFS(CostLines!$L$2:$L$1055,CostLines!$A$2:$A$1055,$A3,CostLines!$C$2:$C$1055,I$1,CostLines!$I$2:$I$1055,README!$B$6) | J3: =SUM(C3:I3) | K3: =COUNTIFS(CostLines!$A$2:$A$1055,$A3,CostLines!$I$2:$I$1055,README!$B$6) | L3: =SUMIFS(CostLines!$L$2:$L$1055,CostLines!$A$2:$A$1055,$A3,CostLines!$P$2:$P$1055,1) | M3: =SUMIFS(CostLines!$L$2:$L$1055,CostLines!$A$2:$A$1055,$A3) | N3: =COUNTIFS(CostLines!$A$2:$A$1055,$A3)
A4: TN57AE9806 | B4: SOCKS | C4: =SUMIFS(CostLines!$L$2:$L$1055,CostLines!$A$2:$A$1055,$A4,CostLines!$C$2:$C$1055,C$1,CostLines!$I$2:$I$1055,README!$B$6) | D4: =SUMIFS(CostLines!$L$2:$L$1055,CostLines!$A$2:$A$1055,$A4,CostLines!$C$2:$C$1055,D$1,CostLines!$I$2:$I$1055,README!$B$6) | E4: =SUMIFS(CostLines!$L$2:$L$1055,CostLines!$A$2:$A$1055,$A4,CostLines!$C$2:$C$1055,E$1,CostLines!$I$2:$I$1055,README!$B$6) | F4: =SUMIFS(CostLines!$L$2:$L$1055,CostLines!$A$2:$A$1055,$A4,CostLines!$C$2:$C$1055,F$1,CostLines!$I$2:$I$1055,README!$B$6) | G4: =SUMIFS(CostLines!$L$2:$L$1055,CostLines!$A$2:$A$1055,$A4,CostLines!$C$2:$C$1055,G$1,CostLines!$I$2:$I$1055,README!$B$6) | H4: =SUMIFS(CostLines!$L$2:$L$1055,CostLines!$A$2:$A$1055,$A4,CostLines!$C$2:$C$1055,H$1,CostLines!$I$2:$I$1055,README!$B$6) | I4: =SUMIFS(CostLines!$L$2:$L$1055,CostLines!$A$2:$A$1055,$A4,CostLines!$C$2:$C$1055,I$1,CostLines!$I$2:$I$1055,README!$B$6) | J4: =SUM(C4:I4) | K4: =COUNTIFS(CostLines!$A$2:$A$1055,$A4,CostLines!$I$2:$I$1055,README!$B$6) | L4: =SUMIFS(CostLines!$L$2:$L$1055,CostLines!$A$2:$A$1055,$A4,CostLines!$P$2:$P$1055,1) | M4: =SUMIFS(CostLines!$L$2:$L$1055,CostLines!$A$2:$A$1055,$A4) | N4: =COUNTIFS(CostLines!$A$2:$A$1055,$A4)
A5: TN57AF3636 | B5: SOCKS | C5: =SUMIFS(CostLines!$L$2:$L$1055,CostLines!$A$2:$A$1055,$A5,CostLines!$C$2:$C$1055,C$1,CostLines!$I$2:$I$1055,README!$B$6) | D5: =SUMIFS(CostLines!$L$2:$L$1055,CostLines!$A$2:$A$1055,$A5,CostLines!$C$2:$C$1055,D$1,CostLines!$I$2:$I$1055,README!$B$6) | E5: =SUMIFS(CostLines!$L$2:$L$1055,CostLines!$A$2:$A$1055,$A5,CostLines!$C$2:$C$1055,E$1,CostLines!$I$2:$I$1055,README!$B$6) | F5: =SUMIFS(CostLines!$L$2:$L$1055,CostLines!$A$2:$A$1055,$A5,CostLines!$C$2:$C$1055,F$1,CostLines!$I$2:$I$1055,README!$B$6) | G5: =SUMIFS(CostLines!$L$2:$L$1055,CostLines!$A$2:$A$1055,$A5,CostLines!$C$2:$C$1055,G$1,CostLines!$I$2:$I$1055,README!$B$6) | H5: =SUMIFS(CostLines!$L$2:$L$1055,CostLines!$A$2:$A$1055,$A5,CostLines!$C$2:$C$1055,H$1,CostLines!$I$2:$I$1055,README!$B$6) | I5: =SUMIFS(CostLines!$L$2:$L$1055,CostLines!$A$2:$A$1055,$A5,CostLines!$C$2:$C$1055,I$1,CostLines!$I$2:$I$1055,README!$B$6) | J5: =SUM(C5:I5) | K5: =COUNTIFS(CostLines!$A$2:$A$1055,$A5,CostLines!$I$2:$I$1055,README!$B$6) | L5: =SUMIFS(CostLines!$L$2:$L$1055,CostLines!$A$2:$A$1055,$A5,CostLines!$P$2:$P$1055,1) | M5: =SUMIFS(CostLines!$L$2:$L$1055,CostLines!$A$2:$A$1055,$A5) | N5: =COUNTIFS(CostLines!$A$2:$A$1055,$A5)
A6: TN57AH3636 | B6: SOCKS | C6: =SUMIFS(CostLines!$L$2:$L$1055,CostLines!$A$2:$A$1055,$A6,CostLines!$C$2:$C$1055,C$1,CostLines!$I$2:$I$1055,README!$B$6) | D6: =SUMIFS(CostLines!$L$2:$L$1055,CostLines!$A$2:$A$1055,$A6,CostLines!$C$2:$C$1055,D$1,CostLines!$I$2:$I$1055,README!$B$6) | E6: =SUMIFS(CostLines!$L$2:$L$1055,CostLines!$A$2:$A$1055,$A6,CostLines!$C$2:$C$1055,E$1,CostLines!$I$2:$I$1055,README!$B$6) | F6: =SUMIFS(CostLines!$L$2:$L$1055,CostLines!$A$2:$A$1055,$A6,CostLines!$C$2:$C$1055,F$1,CostLines!$I$2:$I$1055,README!$B$6) | G6: =SUMIFS(CostLines!$L$2:$L$1055,CostLines!$A$2:$A$1055,$A6,CostLines!$C$2:$C$1055,G$1,CostLines!$I$2:$I$1055,README!$B$6) | H6: =SUMIFS(CostLines!$L$2:$L$1055,CostLines!$A$2:$A$1055,$A6,CostLines!$C$2:$C$1055,H$1,CostLines!$I$2:$I$1055,README!$B$6) | I6: =SUMIFS(CostLines!$L$2:$L$1055,CostLines!$A$2:$A$1055,$A6,CostLines!$C$2:$C$1055,I$1,CostLines!$I$2:$I$1055,README!$B$6) | J6: =SUM(C6:I6) | K6: =COUNTIFS(CostLines!$A$2:$A$1055,$A6,CostLines!$I$2:$I$1055,README!$B$6) | L6: =SUMIFS(CostLines!$L$2:$L$1055,CostLines!$A$2:$A$1055,$A6,CostLines!$P$2:$P$1055,1) | M6: =SUMIFS(CostLines!$L$2:$L$1055,CostLines!$A$2:$A$1055,$A6) | N6: =COUNTIFS(CostLines!$A$2:$A$1055,$A6)
A7: TN57AK3636 | B7: GENERAL | C7: =SUMIFS(CostLines!$L$2:$L$1055,CostLines!$A$2:$A$1055,$A7,CostLines!$C$2:$C$1055,C$1,CostLines!$I$2:$I$1055,README!$B$6) | D7: =SUMIFS(CostLines!$L$2:$L$1055,CostLines!$A$2:$A$1055,$A7,CostLines!$C$2:$C$1055,D$1,CostLines!$I$2:$I$1055,README!$B$6) | E7: =SUMIFS(CostLines!$L$2:$L$1055,CostLines!$A$2:$A$1055,$A7,CostLines!$C$2:$C$1055,E$1,CostLines!$I$2:$I$1055,README!$B$6) | F7: =SUMIFS(CostLines!$L$2:$L$1055,CostLines!$A$2:$A$1055,$A7,CostLines!$C$2:$C$1055,F$1,CostLines!$I$2:$I$1055,README!$B$6) | G7: =SUMIFS(CostLines!$L$2:$L$1055,CostLines!$A$2:$A$1055,$A7,CostLines!$C$2:$C$1055,G$1,CostLines!$I$2:$I$1055,README!$B$6) | H7: =SUMIFS(CostLines!$L$2:$L$1055,CostLines!$A$2:$A$1055,$A7,CostLines!$C$2:$C$1055,H$1,CostLines!$I$2:$I$1055,README!$B$6) | I7: =SUMIFS(CostLines!$L$2:$L$1055,CostLines!$A$2:$A$1055,$A7,CostLines!$C$2:$C$1055,I$1,CostLines!$I$2:$I$1055,README!$B$6) | J7: =SUM(C7:I7) | K7: =COUNTIFS(CostLines!$A$2:$A$1055,$A7,CostLines!$I$2:$I$1055,README!$B$6) | L7: =SUMIFS(CostLines!$L$2:$L$1055,CostLines!$A$2:$A$1055,$A7,CostLines!$P$2:$P$1055,1) | M7: =SUMIFS(CostLines!$L$2:$L$1055,CostLines!$A$2:$A$1055,$A7) | N7: =COUNTIFS(CostLines!$A$2:$A$1055,$A7)
A8: TN57AM3636 | B8: SOCKS | C8: =SUMIFS(CostLines!$L$2:$L$1055,CostLines!$A$2:$A$1055,$A8,CostLines!$C$2:$C$1055,C$1,CostLines!$I$2:$I$1055,README!$B$6) | D8: =SUMIFS(CostLines!$L$2:$L$1055,CostLines!$A$2:$A$1055,$A8,CostLines!$C$2:$C$1055,D$1,CostLines!$I$2:$I$1055,README!$B$6) | E8: =SUMIFS(CostLines!$L$2:$L$1055,CostLines!$A$2:$A$1055,$A8,CostLines!$C$2:$C$1055,E$1,CostLines!$I$2:$I$1055,README!$B$6) | F8: =SUMIFS(CostLines!$L$2:$L$1055,CostLines!$A$2:$A$1055,$A8,CostLines!$C$2:$C$1055,F$1,CostLines!$I$2:$I$1055,README!$B$6) | G8: =SUMIFS(CostLines!$L$2:$L$1055,CostLines!$A$2:$A$1055,$A8,CostLines!$C$2:$C$1055,G$1,CostLines!$I$2:$I$1055,README!$B$6) | H8: =SUMIFS(CostLines!$L$2:$L$1055,CostLines!$A$2:$A$1055,$A8,CostLines!$C$2:$C$1055,H$1,CostLines!$I$2:$I$1055,README!$B$6) | I8: =SUMIFS(CostLines!$L$2:$L$1055,CostLines!$A$2:$A$1055,$A8,CostLines!$C$2:$C$1055,I$1,CostLines!$I$2:$I$1055,README!$B$6) | J8: =SUM(C8:I8) | K8: =COUNTIFS(CostLines!$A$2:$A$1055,$A8,CostLines!$I$2:$I$1055,README!$B$6) | L8: =SUMIFS(CostLines!$L$2:$L$1055,CostLines!$A$2:$A$1055,$A8,CostLines!$P$2:$P$1055,1) | M8: =SUMIFS(CostLines!$L$2:$L$1055,CostLines!$A$2:$A$1055,$A8) | N8: =COUNTIFS(CostLines!$A$2:$A$1055,$A8)
A9: TN57AU3636 | B9: SOCKS | C9: =SUMIFS(CostLines!$L$2:$L$1055,CostLines!$A$2:$A$1055,$A9,CostLines!$C$2:$C$1055,C$1,CostLines!$I$2:$I$1055,README!$B$6) | D9: =SUMIFS(CostLines!$L$2:$L$1055,CostLines!$A$2:$A$1055,$A9,CostLines!$C$2:$C$1055,D$1,CostLines!$I$2:$I$1055,README!$B$6) | E9: =SUMIFS(CostLines!$L$2:$L$1055,CostLines!$A$2:$A$1055,$A9,CostLines!$C$2:$C$1055,E$1,CostLines!$I$2:$I$1055,README!$B$6) | F9: =SUMIFS(CostLines!$L$2:$L$1055,CostLines!$A$2:$A$1055,$A9,CostLines!$C$2:$C$1055,F$1,CostLines!$I$2:$I$1055,README!$B$6) | G9: =SUMIFS(CostLines!$L$2:$L$1055,CostLines!$A$2:$A$1055,$A9,CostLines!$C$2:$C$1055,G$1,CostLines!$I$2:$I$1055,README!$B$6) | H9: =SUMIFS(CostLines!$L$2:$L$1055,CostLines!$A$2:$A$1055,$A9,CostLines!$C$2:$C$1055,H$1,CostLines!$I$2:$I$1055,README!$B$6) | I9: =SUMIFS(CostLines!$L$2:$L$1055,CostLines!$A$2:$A$1055,$A9,CostLines!$C$2:$C$1055,I$1,CostLines!$I$2:$I$1055,README!$B$6) | J9: =SUM(C9:I9) | K9: =COUNTIFS(CostLines!$A$2:$A$1055,$A9,CostLines!$I$2:$I$1055,README!$B$6) | L9: =SUMIFS(CostLines!$L$2:$L$1055,CostLines!$A$2:$A$1055,$A9,CostLines!$P$2:$P$1055,1) | M9: =SUMIFS(CostLines!$L$2:$L$1055,CostLines!$A$2:$A$1055,$A9) | N9: =COUNTIFS(CostLines!$A$2:$A$1055,$A9)
A10: TN57BC3636 | B10: SOCKS | C10: =SUMIFS(CostLines!$L$2:$L$1055,CostLines!$A$2:$A$1055,$A10,CostLines!$C$2:$C$1055,C$1,CostLines!$I$2:$I$1055,README!$B$6) | D10: =SUMIFS(CostLines!$L$2:$L$1055,CostLines!$A$2:$A$1055,$A10,CostLines!$C$2:$C$1055,D$1,CostLines!$I$2:$I$1055,README!$B$6) | E10: =SUMIFS(CostLines!$L$2:$L$1055,CostLines!$A$2:$A$1055,$A10,CostLines!$C$2:$C$1055,E$1,CostLines!$I$2:$I$1055,README!$B$6) | F10: =SUMIFS(CostLines!$L$2:$L$1055,CostLines!$A$2:$A$1055,$A10,CostLines!$C$2:$C$1055,F$1,CostLines!$I$2:$I$1055,README!$B$6) | G10: =SUMIFS(CostLines!$L$2:$L$1055,CostLines!$A$2:$A$1055,$A10,CostLines!$C$2:$C$1055,G$1,CostLines!$I$2:$I$1055,README!$B$6) | H10: =SUMIFS(CostLines!$L$2:$L$1055,CostLines!$A$2:$A$1055,$A10,CostLines!$C$2:$C$1055,H$1,CostLines!$I$2:$I$1055,README!$B$6) | I10: =SUMIFS(CostLines!$L$2:$L$1055,CostLines!$A$2:$A$1055,$A10,CostLines!$C$2:$C$1055,I$1,CostLines!$I$2:$I$1055,README!$B$6) | J10: =SUM(C10:I10) | K10: =COUNTIFS(CostLines!$A$2:$A$1055,$A10,CostLines!$I$2:$I$1055,README!$B$6) | L10: =SUMIFS(CostLines!$L$2:$L$1055,CostLines!$A$2:$A$1055,$A10,CostLines!$P$2:$P$1055,1) | M10: =SUMIFS(CostLines!$L$2:$L$1055,CostLines!$A$2:$A$1055,$A10) | N10: =COUNTIFS(CostLines!$A$2:$A$1055,$A10)
A11: TN57BE3636 | B11: SOCKS | C11: =SUMIFS(CostLines!$L$2:$L$1055,CostLines!$A$2:$A$1055,$A11,CostLines!$C$2:$C$1055,C$1,CostLines!$I$2:$I$1055,README!$B$6) | D11: =SUMIFS(CostLines!$L$2:$L$1055,CostLines!$A$2:$A$1055,$A11,CostLines!$C$2:$C$1055,D$1,CostLines!$I$2:$I$1055,README!$B$6) | E11: =SUMIFS(CostLines!$L$2:$L$1055,CostLines!$A$2:$A$1055,$A11,CostLines!$C$2:$C$1055,E$1,CostLines!$I$2:$I$1055,README!$B$6) | F11: =SUMIFS(CostLines!$L$2:$L$1055,CostLines!$A$2:$A$1055,$A11,CostLines!$C$2:$C$1055,F$1,CostLines!$I$2:$I$1055,README!$B$6) | G11: =SUMIFS(CostLines!$L$2:$L$1055,CostLines!$A$2:$A$1055,$A11,CostLines!$C$2:$C$1055,G$1,CostLines!$I$2:$I$1055,README!$B$6) | H11: =SUMIFS(CostLines!$L$2:$L$1055,CostLines!$A$2:$A$1055,$A11,CostLines!$C$2:$C$1055,H$1,CostLines!$I$2:$I$1055,README!$B$6) | I11: =SUMIFS(CostLines!$L$2:$L$1055,CostLines!$A$2:$A$1055,$A11,CostLines!$C$2:$C$1055,I$1,CostLines!$I$2:$I$1055,README!$B$6) | J11: =SUM(C11:I11) | K11: =COUNTIFS(CostLines!$A$2:$A$1055,$A11,CostLines!$I$2:$I$1055,README!$B$6) | L11: =SUMIFS(CostLines!$L$2:$L$1055,CostLines!$A$2:$A$1055,$A11,CostLines!$P$2:$P$1055,1) | M11: =SUMIFS(CostLines!$L$2:$L$1055,CostLines!$A$2:$A$1055,$A11) | N11: =COUNTIFS(CostLines!$A$2:$A$1055,$A11)
A12: TN57BH3636 | B12: SOCKS | C12: =SUMIFS(CostLines!$L$2:$L$1055,CostLines!$A$2:$A$1055,$A12,CostLines!$C$2:$C$1055,C$1,CostLines!$I$2:$I$1055,README!$B$6) | D12: =SUMIFS(CostLines!$L$2:$L$1055,CostLines!$A$2:$A$1055,$A12,CostLines!$C$2:$C$1055,D$1,CostLines!$I$2:$I$1055,README!$B$6) | E12: =SUMIFS(CostLines!$L$2:$L$1055,CostLines!$A$2:$A$1055,$A12,CostLines!$C$2:$C$1055,E$1,CostLines!$I$2:$I$1055,README!$B$6) | F12: =SUMIFS(CostLines!$L$2:$L$1055,CostLines!$A$2:$A$1055,$A12,CostLines!$C$2:$C$1055,F$1,CostLines!$I$2:$I$1055,README!$B$6) | G12: =SUMIFS(CostLines!$L$2:$L$1055,CostLines!$A$2:$A$1055,$A12,CostLines!$C$2:$C$1055,G$1,CostLines!$I$2:$I$1055,README!$B$6) | H12: =SUMIFS(CostLines!$L$2:$L$1055,CostLines!$A$2:$A$1055,$A12,CostLines!$C$2:$C$1055,H$1,CostLines!$I$2:$I$1055,README!$B$6) | I12: =SUMIFS(CostLines!$L$2:$L$1055,CostLines!$A$2:$A$1055,$A12,CostLines!$C$2:$C$1055,I$1,CostLines!$I$2:$I$1055,README!$B$6) | J12: =SUM(C12:I12) | K12: =COUNTIFS(CostLines!$A$2:$A$1055,$A12,CostLines!$I$2:$I$1055,README!$B$6) | L12: =SUMIFS(CostLines!$L$2:$L$1055,CostLines!$A$2:$A$1055,$A12,CostLines!$P$2:$P$1055,1) | M12: =SUMIFS(CostLines!$L$2:$L$1055,CostLines!$A$2:$A$1055,$A12) | N12: =COUNTIFS(CostLines!$A$2:$A$1055,$A12)
A13: TN57BL3636 | B13: SOCKS | C13: =SUMIFS(CostLines!$L$2:$L$1055,CostLines!$A$2:$A$1055,$A13,CostLines!$C$2:$C$1055,C$1,CostLines!$I$2:$I$1055,README!$B$6) | D13: =SUMIFS(CostLines!$L$2:$L$1055,CostLines!$A$2:$A$1055,$A13,CostLines!$C$2:$C$1055,D$1,CostLines!$I$2:$I$1055,README!$B$6) | E13: =SUMIFS(CostLines!$L$2:$L$1055,CostLines!$A$2:$A$1055,$A13,CostLines!$C$2:$C$1055,E$1,CostLines!$I$2:$I$1055,README!$B$6) | F13: =SUMIFS(CostLines!$L$2:$L$1055,CostLines!$A$2:$A$1055,$A13,CostLines!$C$2:$C$1055,F$1,CostLines!$I$2:$I$1055,README!$B$6) | G13: =SUMIFS(CostLines!$L$2:$L$1055,CostLines!$A$2:$A$1055,$A13,CostLines!$C$2:$C$1055,G$1,CostLines!$I$2:$I$1055,README!$B$6) | H13: =SUMIFS(CostLines!$L$2:$L$1055,CostLines!$A$2:$A$1055,$A13,CostLines!$C$2:$C$1055,H$1,CostLines!$I$2:$I$1055,README!$B$6) | I13: =SUMIFS(CostLines!$L$2:$L$1055,CostLines!$A$2:$A$1055,$A13,CostLines!$C$2:$C$1055,I$1,CostLines!$I$2:$I$1055,README!$B$6) | J13: =SUM(C13:I13) | K13: =COUNTIFS(CostLines!$A$2:$A$1055,$A13,CostLines!$I$2:$I$1055,README!$B$6) | L13: =SUMIFS(CostLines!$L$2:$L$1055,CostLines!$A$2:$A$1055,$A13,CostLines!$P$2:$P$1055,1) | M13: =SUMIFS(CostLines!$L$2:$L$1055,CostLines!$A$2:$A$1055,$A13) | N13: =COUNTIFS(CostLines!$A$2:$A$1055,$A13)
... A43: TN57CL3636 | B43: GENERAL | C43: =SUMIFS(CostLines!$L$2:$L$1055,CostLines!$A$2:$A$1055,$A43,CostLines!$C$2:$C$1055,C$1,CostLines!$I$2:$I$1055,README!$B$6) | D43: =SUMIFS(CostLines!$L$2:$L$1055,CostLines!$A$2:$A$1055,$A43,CostLines!$C$2:$C$1055,D$1,CostLines!$I$2:$I$1055,README!$B$6) | E43: =SUMIFS(CostLines!$L$2:$L$1055,CostLines!$A$2:$A$1055,$A43,CostLines!$C$2:$C$1055,E$1,CostLines!$I$2:$I$1055,README!$B$6) | F43: =SUMIFS(CostLines!$L$2:$L$1055,CostLines!$A$2:$A$1055,$A43,CostLines!$C$2:$C$1055,F$1,CostLines!$I$2:$I$1055,README!$B$6) | G43: =SUMIFS(CostLines!$L$2:$L$1055,CostLines!$A$2:$A$1055,$A43,CostLines!$C$2:$C$1055,G$1,CostLines!$I$2:$I$1055,README!$B$6) | H43: =SUMIFS(CostLines!$L$2:$L$1055,CostLines!$A$2:$A$1055,$A43,CostLines!$C$2:$C$1055,H$1,CostLines!$I$2:$I$1055,README!$B$6) | I43: =SUMIFS(CostLines!$L$2:$L$1055,CostLines!$A$2:$A$1055,$A43,CostLines!$C$2:$C$1055,I$1,CostLines!$I$2:$I$1055,README!$B$6) | J43: =SUM(C43:I43) | K43: =COUNTIFS(CostLines!$A$2:$A$1055,$A43,CostLines!$I$2:$I$1055,README!$B$6) | L43: =SUMIFS(CostLines!$L$2:$L$1055,CostLines!$A$2:$A$1055,$A43,CostLines!$P$2:$P$1055,1) | M43: =SUMIFS(CostLines!$L$2:$L$1055,CostLines!$A$2:$A$1055,$A43) | N43: =COUNTIFS(CostLines!$A$2:$A$1055,$A43)
A44: TN57CM3636 | C44: =SUMIFS(CostLines!$L$2:$L$1055,CostLines!$A$2:$A$1055,$A44,CostLines!$C$2:$C$1055,C$1,CostLines!$I$2:$I$1055,README!$B$6) | D44: =SUMIFS(CostLines!$L$2:$L$1055,CostLines!$A$2:$A$1055,$A44,CostLines!$C$2:$C$1055,D$1,CostLines!$I$2:$I$1055,README!$B$6) | E44: =SUMIFS(CostLines!$L$2:$L$1055,CostLines!$A$2:$A$1055,$A44,CostLines!$C$2:$C$1055,E$1,CostLines!$I$2:$I$1055,README!$B$6) | F44: =SUMIFS(CostLines!$L$2:$L$1055,CostLines!$A$2:$A$1055,$A44,CostLines!$C$2:$C$1055,F$1,CostLines!$I$2:$I$1055,README!$B$6) | G44: =SUMIFS(CostLines!$L$2:$L$1055,CostLines!$A$2:$A$1055,$A44,CostLines!$C$2:$C$1055,G$1,CostLines!$I$2:$I$1055,README!$B$6) | H44: =SUMIFS(CostLines!$L$2:$L$1055,CostLines!$A$2:$A$1055,$A44,CostLines!$C$2:$C$1055,H$1,CostLines!$I$2:$I$1055,README!$B$6) | I44: =SUMIFS(CostLines!$L$2:$L$1055,CostLines!$A$2:$A$1055,$A44,CostLines!$C$2:$C$1055,I$1,CostLines!$I$2:$I$1055,README!$B$6) | J44: =SUM(C44:I44) | K44: =COUNTIFS(CostLines!$A$2:$A$1055,$A44,CostLines!$I$2:$I$1055,README!$B$6) | L44: =SUMIFS(CostLines!$L$2:$L$1055,CostLines!$A$2:$A$1055,$A44,CostLines!$P$2:$P$1055,1) | M44: =SUMIFS(CostLines!$L$2:$L$1055,CostLines!$A$2:$A$1055,$A44) | N44: =COUNTIFS(CostLines!$A$2:$A$1055,$A44)
A45: TN58BJ3434 | B45: WOVEN | C45: =SUMIFS(CostLines!$L$2:$L$1055,CostLines!$A$2:$A$1055,$A45,CostLines!$C$2:$C$1055,C$1,CostLines!$I$2:$I$1055,README!$B$6) | D45: =SUMIFS(CostLines!$L$2:$L$1055,CostLines!$A$2:$A$1055,$A45,CostLines!$C$2:$C$1055,D$1,CostLines!$I$2:$I$1055,README!$B$6) | E45: =SUMIFS(CostLines!$L$2:$L$1055,CostLines!$A$2:$A$1055,$A45,CostLines!$C$2:$C$1055,E$1,CostLines!$I$2:$I$1055,README!$B$6) | F45: =SUMIFS(CostLines!$L$2:$L$1055,CostLines!$A$2:$A$1055,$A45,CostLines!$C$2:$C$1055,F$1,CostLines!$I$2:$I$1055,README!$B$6) | G45: =SUMIFS(CostLines!$L$2:$L$1055,CostLines!$A$2:$A$1055,$A45,CostLines!$C$2:$C$1055,G$1,CostLines!$I$2:$I$1055,README!$B$6) | H45: =SUMIFS(CostLines!$L$2:$L$1055,CostLines!$A$2:$A$1055,$A45,CostLines!$C$2:$C$1055,H$1,CostLines!$I$2:$I$1055,README!$B$6) | I45: =SUMIFS(CostLines!$L$2:$L$1055,CostLines!$A$2:$A$1055,$A45,CostLines!$C$2:$C$1055,I$1,CostLines!$I$2:$I$1055,README!$B$6) | J45: =SUM(C45:I45) | K45: =COUNTIFS(CostLines!$A$2:$A$1055,$A45,CostLines!$I$2:$I$1055,README!$B$6) | L45: =SUMIFS(CostLines!$L$2:$L$1055,CostLines!$A$2:$A$1055,$A45,CostLines!$P$2:$P$1055,1) | M45: =SUMIFS(CostLines!$L$2:$L$1055,CostLines!$A$2:$A$1055,$A45) | N45: =COUNTIFS(CostLines!$A$2:$A$1055,$A45)
A46: TN58BJ3636 | B46: SOCKS | C46: =SUMIFS(CostLines!$L$2:$L$1055,CostLines!$A$2:$A$1055,$A46,CostLines!$C$2:$C$1055,C$1,CostLines!$I$2:$I$1055,README!$B$6) | D46: =SUMIFS(CostLines!$L$2:$L$1055,CostLines!$A$2:$A$1055,$A46,CostLines!$C$2:$C$1055,D$1,CostLines!$I$2:$I$1055,README!$B$6) | E46: =SUMIFS(CostLines!$L$2:$L$1055,CostLines!$A$2:$A$1055,$A46,CostLines!$C$2:$C$1055,E$1,CostLines!$I$2:$I$1055,README!$B$6) | F46: =SUMIFS(CostLines!$L$2:$L$1055,CostLines!$A$2:$A$1055,$A46,CostLines!$C$2:$C$1055,F$1,CostLines!$I$2:$I$1055,README!$B$6) | G46: =SUMIFS(CostLines!$L$2:$L$1055,CostLines!$A$2:$A$1055,$A46,CostLines!$C$2:$C$1055,G$1,CostLines!$I$2:$I$1055,README!$B$6) | H46: =SUMIFS(CostLines!$L$2:$L$1055,CostLines!$A$2:$A$1055,$A46,CostLines!$C$2:$C$1055,H$1,CostLines!$I$2:$I$1055,README!$B$6) | I46: =SUMIFS(CostLines!$L$2:$L$1055,CostLines!$A$2:$A$1055,$A46,CostLines!$C$2:$C$1055,I$1,CostLines!$I$2:$I$1055,README!$B$6) | J46: =SUM(C46:I46) | K46: =COUNTIFS(CostLines!$A$2:$A$1055,$A46,CostLines!$I$2:$I$1055,README!$B$6) | L46: =SUMIFS(CostLines!$L$2:$L$1055,CostLines!$A$2:$A$1055,$A46,CostLines!$P$2:$P$1055,1) | M46: =SUMIFS(CostLines!$L$2:$L$1055,CostLines!$A$2:$A$1055,$A46) | N46: =COUNTIFS(CostLines!$A$2:$A$1055,$A46)
A47: TN58BK3434 | B47: WOVEN | C47: =SUMIFS(CostLines!$L$2:$L$1055,CostLines!$A$2:$A$1055,$A47,CostLines!$C$2:$C$1055,C$1,CostLines!$I$2:$I$1055,README!$B$6) | D47: =SUMIFS(CostLines!$L$2:$L$1055,CostLines!$A$2:$A$1055,$A47,CostLines!$C$2:$C$1055,D$1,CostLines!$I$2:$I$1055,README!$B$6) | E47: =SUMIFS(CostLines!$L$2:$L$1055,CostLines!$A$2:$A$1055,$A47,CostLines!$C$2:$C$1055,E$1,CostLines!$I$2:$I$1055,README!$B$6) | F47: =SUMIFS(CostLines!$L$2:$L$1055,CostLines!$A$2:$A$1055,$A47,CostLines!$C$2:$C$1055,F$1,CostLines!$I$2:$I$1055,README!$B$6) | G47: =SUMIFS(CostLines!$L$2:$L$1055,CostLines!$A$2:$A$1055,$A47,CostLines!$C$2:$C$1055,G$1,CostLines!$I$2:$I$1055,README!$B$6) | H47: =SUMIFS(CostLines!$L$2:$L$1055,CostLines!$A$2:$A$1055,$A47,CostLines!$C$2:$C$1055,H$1,CostLines!$I$2:$I$1055,README!$B$6) | I47: =SUMIFS(CostLines!$L$2:$L$1055,CostLines!$A$2:$A$1055,$A47,CostLines!$C$2:$C$1055,I$1,CostLines!$I$2:$I$1055,README!$B$6) | J47: =SUM(C47:I47) | K47: =COUNTIFS(CostLines!$A$2:$A$1055,$A47,CostLines!$I$2:$I$1055,README!$B$6) | L47: =SUMIFS(CostLines!$L$2:$L$1055,CostLines!$A$2:$A$1055,$A47,CostLines!$P$2:$P$1055,1) | M47: =SUMIFS(CostLines!$L$2:$L$1055,CostLines!$A$2:$A$1055,$A47) | N47: =COUNTIFS(CostLines!$A$2:$A$1055,$A47)
A48: TN58BK3636 | B48: SOCKS | C48: =SUMIFS(CostLines!$L$2:$L$1055,CostLines!$A$2:$A$1055,$A48,CostLines!$C$2:$C$1055,C$1,CostLines!$I$2:$I$1055,README!$B$6) | D48: =SUMIFS(CostLines!$L$2:$L$1055,CostLines!$A$2:$A$1055,$A48,CostLines!$C$2:$C$1055,D$1,CostLines!$I$2:$I$1055,README!$B$6) | E48: =SUMIFS(CostLines!$L$2:$L$1055,CostLines!$A$2:$A$1055,$A48,CostLines!$C$2:$C$1055,E$1,CostLines!$I$2:$I$1055,README!$B$6) | F48: =SUMIFS(CostLines!$L$2:$L$1055,CostLines!$A$2:$A$1055,$A48,CostLines!$C$2:$C$1055,F$1,CostLines!$I$2:$I$1055,README!$B$6) | G48: =SUMIFS(CostLines!$L$2:$L$1055,CostLines!$A$2:$A$1055,$A48,CostLines!$C$2:$C$1055,G$1,CostLines!$I$2:$I$1055,README!$B$6) | H48: =SUMIFS(CostLines!$L$2:$L$1055,CostLines!$A$2:$A$1055,$A48,CostLines!$C$2:$C$1055,H$1,CostLines!$I$2:$I$1055,README!$B$6) | I48: =SUMIFS(CostLines!$L$2:$L$1055,CostLines!$A$2:$A$1055,$A48,CostLines!$C$2:$C$1055,I$1,CostLines!$I$2:$I$1055,README!$B$6) | J48: =SUM(C48:I48) | K48: =COUNTIFS(CostLines!$A$2:$A$1055,$A48,CostLines!$I$2:$I$1055,README!$B$6) | L48: =SUMIFS(CostLines!$L$2:$L$1055,CostLines!$A$2:$A$1055,$A48,CostLines!$P$2:$P$1055,1) | M48: =SUMIFS(CostLines!$L$2:$L$1055,CostLines!$A$2:$A$1055,$A48) | N48: =COUNTIFS(CostLines!$A$2:$A$1055,$A48)
A49: TN58BL3434 | B49: WOVEN | C49: =SUMIFS(CostLines!$L$2:$L$1055,CostLines!$A$2:$A$1055,$A49,CostLines!$C$2:$C$1055,C$1,CostLines!$I$2:$I$1055,README!$B$6) | D49: =SUMIFS(CostLines!$L$2:$L$1055,CostLines!$A$2:$A$1055,$A49,CostLines!$C$2:$C$1055,D$1,CostLines!$I$2:$I$1055,README!$B$6) | E49: =SUMIFS(CostLines!$L$2:$L$1055,CostLines!$A$2:$A$1055,$A49,CostLines!$C$2:$C$1055,E$1,CostLines!$I$2:$I$1055,README!$B$6) | F49: =SUMIFS(CostLines!$L$2:$L$1055,CostLines!$A$2:$A$1055,$A49,CostLines!$C$2:$C$1055,F$1,CostLines!$I$2:$I$1055,README!$B$6) | G49: =SUMIFS(CostLines!$L$2:$L$1055,CostLines!$A$2:$A$1055,$A49,CostLines!$C$2:$C$1055,G$1,CostLines!$I$2:$I$1055,README!$B$6) | H49: =SUMIFS(CostLines!$L$2:$L$1055,CostLines!$A$2:$A$1055,$A49,CostLines!$C$2:$C$1055,H$1,CostLines!$I$2:$I$1055,README!$B$6) | I49: =SUMIFS(CostLines!$L$2:$L$1055,CostLines!$A$2:$A$1055,$A49,CostLines!$C$2:$C$1055,I$1,CostLines!$I$2:$I$1055,README!$B$6) | J49: =SUM(C49:I49) | K49: =COUNTIFS(CostLines!$A$2:$A$1055,$A49,CostLines!$I$2:$I$1055,README!$B$6) | L49: =SUMIFS(CostLines!$L$2:$L$1055,CostLines!$A$2:$A$1055,$A49,CostLines!$P$2:$P$1055,1) | M49: =SUMIFS(CostLines!$L$2:$L$1055,CostLines!$A$2:$A$1055,$A49) | N49: =COUNTIFS(CostLines!$A$2:$A$1055,$A49)
A50: TN58BL3636 | B50: SOCKS | C50: =SUMIFS(CostLines!$L$2:$L$1055,CostLines!$A$2:$A$1055,$A50,CostLines!$C$2:$C$1055,C$1,CostLines!$I$2:$I$1055,README!$B$6) | D50: =SUMIFS(CostLines!$L$2:$L$1055,CostLines!$A$2:$A$1055,$A50,CostLines!$C$2:$C$1055,D$1,CostLines!$I$2:$I$1055,README!$B$6) | E50: =SUMIFS(CostLines!$L$2:$L$1055,CostLines!$A$2:$A$1055,$A50,CostLines!$C$2:$C$1055,E$1,CostLines!$I$2:$I$1055,README!$B$6) | F50: =SUMIFS(CostLines!$L$2:$L$1055,CostLines!$A$2:$A$1055,$A50,CostLines!$C$2:$C$1055,F$1,CostLines!$I$2:$I$1055,README!$B$6) | G50: =SUMIFS(CostLines!$L$2:$L$1055,CostLines!$A$2:$A$1055,$A50,CostLines!$C$2:$C$1055,G$1,CostLines!$I$2:$I$1055,README!$B$6) | H50: =SUMIFS(CostLines!$L$2:$L$1055,CostLines!$A$2:$A$1055,$A50,CostLines!$C$2:$C$1055,H$1,CostLines!$I$2:$I$1055,README!$B$6) | I50: =SUMIFS(CostLines!$L$2:$L$1055,CostLines!$A$2:$A$1055,$A50,CostLines!$C$2:$C$1055,I$1,CostLines!$I$2:$I$1055,README!$B$6) | J50: =SUM(C50:I50) | K50: =COUNTIFS(CostLines!$A$2:$A$1055,$A50,CostLines!$I$2:$I$1055,README!$B$6) | L50: =SUMIFS(CostLines!$L$2:$L$1055,CostLines!$A$2:$A$1055,$A50,CostLines!$P$2:$P$1055,1) | M50: =SUMIFS(CostLines!$L$2:$L$1055,CostLines!$A$2:$A$1055,$A50) | N50: =COUNTIFS(CostLines!$A$2:$A$1055,$A50)
A51: TN58BM3434 | B51: WOVEN | C51: =SUMIFS(CostLines!$L$2:$L$1055,CostLines!$A$2:$A$1055,$A51,CostLines!$C$2:$C$1055,C$1,CostLines!$I$2:$I$1055,README!$B$6) | D51: =SUMIFS(CostLines!$L$2:$L$1055,CostLines!$A$2:$A$1055,$A51,CostLines!$C$2:$C$1055,D$1,CostLines!$I$2:$I$1055,README!$B$6) | E51: =SUMIFS(CostLines!$L$2:$L$1055,CostLines!$A$2:$A$1055,$A51,CostLines!$C$2:$C$1055,E$1,CostLines!$I$2:$I$1055,README!$B$6) | F51: =SUMIFS(CostLines!$L$2:$L$1055,CostLines!$A$2:$A$1055,$A51,CostLines!$C$2:$C$1055,F$1,CostLines!$I$2:$I$1055,README!$B$6) | G51: =SUMIFS(CostLines!$L$2:$L$1055,CostLines!$A$2:$A$1055,$A51,CostLines!$C$2:$C$1055,G$1,CostLines!$I$2:$I$1055,README!$B$6) | H51: =SUMIFS(CostLines!$L$2:$L$1055,CostLines!$A$2:$A$1055,$A51,CostLines!$C$2:$C$1055,H$1,CostLines!$I$2:$I$1055,README!$B$6) | I51: =SUMIFS(CostLines!$L$2:$L$1055,CostLines!$A$2:$A$1055,$A51,CostLines!$C$2:$C$1055,I$1,CostLines!$I$2:$I$1055,README!$B$6) | J51: =SUM(C51:I51) | K51: =COUNTIFS(CostLines!$A$2:$A$1055,$A51,CostLines!$I$2:$I$1055,README!$B$6) | L51: =SUMIFS(CostLines!$L$2:$L$1055,CostLines!$A$2:$A$1055,$A51,CostLines!$P$2:$P$1055,1) | M51: =SUMIFS(CostLines!$L$2:$L$1055,CostLines!$A$2:$A$1055,$A51) | N51: =COUNTIFS(CostLines!$A$2:$A$1055,$A51)
A52: TN58BM3636 | B52: SOCKS | C52: =SUMIFS(CostLines!$L$2:$L$1055,CostLines!$A$2:$A$1055,$A52,CostLines!$C$2:$C$1055,C$1,CostLines!$I$2:$I$1055,README!$B$6) | D52: =SUMIFS(CostLines!$L$2:$L$1055,CostLines!$A$2:$A$1055,$A52,CostLines!$C$2:$C$1055,D$1,CostLines!$I$2:$I$1055,README!$B$6) | E52: =SUMIFS(CostLines!$L$2:$L$1055,CostLines!$A$2:$A$1055,$A52,CostLines!$C$2:$C$1055,E$1,CostLines!$I$2:$I$1055,README!$B$6) | F52: =SUMIFS(CostLines!$L$2:$L$1055,CostLines!$A$2:$A$1055,$A52,CostLines!$C$2:$C$1055,F$1,CostLines!$I$2:$I$1055,README!$B$6) | G52: =SUMIFS(CostLines!$L$2:$L$1055,CostLines!$A$2:$A$1055,$A52,CostLines!$C$2:$C$1055,G$1,CostLines!$I$2:$I$1055,README!$B$6) | H52: =SUMIFS(CostLines!$L$2:$L$1055,CostLines!$A$2:$A$1055,$A52,CostLines!$C$2:$C$1055,H$1,CostLines!$I$2:$I$1055,README!$B$6) | I52: =SUMIFS(CostLines!$L$2:$L$1055,CostLines!$A$2:$A$1055,$A52,CostLines!$C$2:$C$1055,I$1,CostLines!$I$2:$I$1055,README!$B$6) | J52: =SUM(C52:I52) | K52: =COUNTIFS(CostLines!$A$2:$A$1055,$A52,CostLines!$I$2:$I$1055,README!$B$6) | L52: =SUMIFS(CostLines!$L$2:$L$1055,CostLines!$A$2:$A$1055,$A52,CostLines!$P$2:$P$1055,1) | M52: =SUMIFS(CostLines!$L$2:$L$1055,CostLines!$A$2:$A$1055,$A52) | N52: =COUNTIFS(CostLines!$A$2:$A$1055,$A52)
A53: TN58BP3434 | B53: WOVEN | C53: =SUMIFS(CostLines!$L$2:$L$1055,CostLines!$A$2:$A$1055,$A53,CostLines!$C$2:$C$1055,C$1,CostLines!$I$2:$I$1055,README!$B$6) | D53: =SUMIFS(CostLines!$L$2:$L$1055,CostLines!$A$2:$A$1055,$A53,CostLines!$C$2:$C$1055,D$1,CostLines!$I$2:$I$1055,README!$B$6) | E53: =SUMIFS(CostLines!$L$2:$L$1055,CostLines!$A$2:$A$1055,$A53,CostLines!$C$2:$C$1055,E$1,CostLines!$I$2:$I$1055,README!$B$6) | F53: =SUMIFS(CostLines!$L$2:$L$1055,CostLines!$A$2:$A$1055,$A53,CostLines!$C$2:$C$1055,F$1,CostLines!$I$2:$I$1055,README!$B$6) | G53: =SUMIFS(CostLines!$L$2:$L$1055,CostLines!$A$2:$A$1055,$A53,CostLines!$C$2:$C$1055,G$1,CostLines!$I$2:$I$1055,README!$B$6) | H53: =SUMIFS(CostLines!$L$2:$L$1055,CostLines!$A$2:$A$1055,$A53,CostLines!$C$2:$C$1055,H$1,CostLines!$I$2:$I$1055,README!$B$6) | I53: =SUMIFS(CostLines!$L$2:$L$1055,CostLines!$A$2:$A$1055,$A53,CostLines!$C$2:$C$1055,I$1,CostLines!$I$2:$I$1055,README!$B$6) | J53: =SUM(C53:I53) | K53: =COUNTIFS(CostLines!$A$2:$A$1055,$A53,CostLines!$I$2:$I$1055,README!$B$6) | L53: =SUMIFS(CostLines!$L$2:$L$1055,CostLines!$A$2:$A$1055,$A53,CostLines!$P$2:$P$1055,1) | M53: =SUMIFS(CostLines!$L$2:$L$1055,CostLines!$A$2:$A$1055,$A53) | N53: =COUNTIFS(CostLines!$A$2:$A$1055,$A53)
A54: TN58BP3636 | B54: WOVEN | C54: =SUMIFS(CostLines!$L$2:$L$1055,CostLines!$A$2:$A$1055,$A54,CostLines!$C$2:$C$1055,C$1,CostLines!$I$2:$I$1055,README!$B$6) | D54: =SUMIFS(CostLines!$L$2:$L$1055,CostLines!$A$2:$A$1055,$A54,CostLines!$C$2:$C$1055,D$1,CostLines!$I$2:$I$1055,README!$B$6) | E54: =SUMIFS(CostLines!$L$2:$L$1055,CostLines!$A$2:$A$1055,$A54,CostLines!$C$2:$C$1055,E$1,CostLines!$I$2:$I$1055,README!$B$6) | F54: =SUMIFS(CostLines!$L$2:$L$1055,CostLines!$A$2:$A$1055,$A54,CostLines!$C$2:$C$1055,F$1,CostLines!$I$2:$I$1055,README!$B$6) | G54: =SUMIFS(CostLines!$L$2:$L$1055,CostLines!$A$2:$A$1055,$A54,CostLines!$C$2:$C$1055,G$1,CostLines!$I$2:$I$1055,README!$B$6) | H54: =SUMIFS(CostLines!$L$2:$L$1055,CostLines!$A$2:$A$1055,$A54,CostLines!$C$2:$C$1055,H$1,CostLines!$I$2:$I$1055,README!$B$6) | I54: =SUMIFS(CostLines!$L$2:$L$1055,CostLines!$A$2:$A$1055,$A54,CostLines!$C$2:$C$1055,I$1,CostLines!$I$2:$I$1055,README!$B$6) | J54: =SUM(C54:I54) | K54: =COUNTIFS(CostLines!$A$2:$A$1055,$A54,CostLines!$I$2:$I$1055,README!$B$6) | L54: =SUMIFS(CostLines!$L$2:$L$1055,CostLines!$A$2:$A$1055,$A54,CostLines!$P$2:$P$1055,1) | M54: =SUMIFS(CostLines!$L$2:$L$1055,CostLines!$A$2:$A$1055,$A54) | N54: =COUNTIFS(CostLines!$A$2:$A$1055,$A54)
A55: TN58BQ3434 | B55: SOCKS | C55: =SUMIFS(CostLines!$L$2:$L$1055,CostLines!$A$2:$A$1055,$A55,CostLines!$C$2:$C$1055,C$1,CostLines!$I$2:$I$1055,README!$B$6) | D55: =SUMIFS(CostLines!$L$2:$L$1055,CostLines!$A$2:$A$1055,$A55,CostLines!$C$2:$C$1055,D$1,CostLines!$I$2:$I$1055,README!$B$6) | E55: =SUMIFS(CostLines!$L$2:$L$1055,CostLines!$A$2:$A$1055,$A55,CostLines!$C$2:$C$1055,E$1,CostLines!$I$2:$I$1055,README!$B$6) | F55: =SUMIFS(CostLines!$L$2:$L$1055,CostLines!$A$2:$A$1055,$A55,CostLines!$C$2:$C$1055,F$1,CostLines!$I$2:$I$1055,README!$B$6) | G55: =SUMIFS(CostLines!$L$2:$L$1055,CostLines!$A$2:$A$1055,$A55,CostLines!$C$2:$C$1055,G$1,CostLines!$I$2:$I$1055,README!$B$6) | H55: =SUMIFS(CostLines!$L$2:$L$1055,CostLines!$A$2:$A$1055,$A55,CostLines!$C$2:$C$1055,H$1,CostLines!$I$2:$I$1055,README!$B$6) | I55: =SUMIFS(CostLines!$L$2:$L$1055,CostLines!$A$2:$A$1055,$A55,CostLines!$C$2:$C$1055,I$1,CostLines!$I$2:$I$1055,README!$B$6) | J55: =SUM(C55:I55) | K55: =COUNTIFS(CostLines!$A$2:$A$1055,$A55,CostLines!$I$2:$I$1055,README!$B$6) | L55: =SUMIFS(CostLines!$L$2:$L$1055,CostLines!$A$2:$A$1055,$A55,CostLines!$P$2:$P$1055,1) | M55: =SUMIFS(CostLines!$L$2:$L$1055,CostLines!$A$2:$A$1055,$A55) | N55: =COUNTIFS(CostLines!$A$2:$A$1055,$A55)
A56: TN58BQ3636 | B56: WOVEN | C56: =SUMIFS(CostLines!$L$2:$L$1055,CostLines!$A$2:$A$1055,$A56,CostLines!$C$2:$C$1055,C$1,CostLines!$I$2:$I$1055,README!$B$6) | D56: =SUMIFS(CostLines!$L$2:$L$1055,CostLines!$A$2:$A$1055,$A56,CostLines!$C$2:$C$1055,D$1,CostLines!$I$2:$I$1055,README!$B$6) | E56: =SUMIFS(CostLines!$L$2:$L$1055,CostLines!$A$2:$A$1055,$A56,CostLines!$C$2:$C$1055,E$1,CostLines!$I$2:$I$1055,README!$B$6) | F56: =SUMIFS(CostLines!$L$2:$L$1055,CostLines!$A$2:$A$1055,$A56,CostLines!$C$2:$C$1055,F$1,CostLines!$I$2:$I$1055,README!$B$6) | G56: =SUMIFS(CostLines!$L$2:$L$1055,CostLines!$A$2:$A$1055,$A56,CostLines!$C$2:$C$1055,G$1,CostLines!$I$2:$I$1055,README!$B$6) | H56: =SUMIFS(CostLines!$L$2:$L$1055,CostLines!$A$2:$A$1055,$A56,CostLines!$C$2:$C$1055,H$1,CostLines!$I$2:$I$1055,README!$B$6) | I56: =SUMIFS(CostLines!$L$2:$L$1055,CostLines!$A$2:$A$1055,$A56,CostLines!$C$2:$C$1055,I$1,CostLines!$I$2:$I$1055,README!$B$6) | J56: =SUM(C56:I56) | K56: =COUNTIFS(CostLines!$A$2:$A$1055,$A56,CostLines!$I$2:$I$1055,README!$B$6) | L56: =SUMIFS(CostLines!$L$2:$L$1055,CostLines!$A$2:$A$1055,$A56,CostLines!$P$2:$P$1055,1) | M56: =SUMIFS(CostLines!$L$2:$L$1055,CostLines!$A$2:$A$1055,$A56) | N56: =COUNTIFS(CostLines!$A$2:$A$1055,$A56)
... A65: TN60AS3636 | B65: WOVEN | C65: =SUMIFS(CostLines!$L$2:$L$1055,CostLines!$A$2:$A$1055,$A65,CostLines!$C$2:$C$1055,C$1,CostLines!$I$2:$I$1055,README!$B$6) | D65: =SUMIFS(CostLines!$L$2:$L$1055,CostLines!$A$2:$A$1055,$A65,CostLines!$C$2:$C$1055,D$1,CostLines!$I$2:$I$1055,README!$B$6) | E65: =SUMIFS(CostLines!$L$2:$L$1055,CostLines!$A$2:$A$1055,$A65,CostLines!$C$2:$C$1055,E$1,CostLines!$I$2:$I$1055,README!$B$6) | F65: =SUMIFS(CostLines!$L$2:$L$1055,CostLines!$A$2:$A$1055,$A65,CostLines!$C$2:$C$1055,F$1,CostLines!$I$2:$I$1055,README!$B$6) | G65: =SUMIFS(CostLines!$L$2:$L$1055,CostLines!$A$2:$A$1055,$A65,CostLines!$C$2:$C$1055,G$1,CostLines!$I$2:$I$1055,README!$B$6) | H65: =SUMIFS(CostLines!$L$2:$L$1055,CostLines!$A$2:$A$1055,$A65,CostLines!$C$2:$C$1055,H$1,CostLines!$I$2:$I$1055,README!$B$6) | I65: =SUMIFS(CostLines!$L$2:$L$1055,CostLines!$A$2:$A$1055,$A65,CostLines!$C$2:$C$1055,I$1,CostLines!$I$2:$I$1055,README!$B$6) | J65: =SUM(C65:I65) | K65: =COUNTIFS(CostLines!$A$2:$A$1055,$A65,CostLines!$I$2:$I$1055,README!$B$6) | L65: =SUMIFS(CostLines!$L$2:$L$1055,CostLines!$A$2:$A$1055,$A65,CostLines!$P$2:$P$1055,1) | M65: =SUMIFS(CostLines!$L$2:$L$1055,CostLines!$A$2:$A$1055,$A65) | N65: =COUNTIFS(CostLines!$A$2:$A$1055,$A65)
B67: Total | C67: =SUM(C2:C65) | D67: =SUM(D2:D65) | E67: =SUM(E2:E65) | F67: =SUM(F2:F65) | G67: =SUM(G2:G65) | H67: =SUM(H2:H65) | I67: =SUM(I2:I65) | J67: =SUM(J2:J65) | ... N67: =SUM(N2:N65)
A69: Every activity column is filtered to the financial year in README!B4:B6 — change the yellow cell and the whole grid moves. 'All-time' columns ignore it. Division is the vehicle's commonest division in the feed; a few buses appear under more than one.

Sheet ByActivity
A1: Proj_Activity_Name | B1: 2024-25 | C1: 2025-26 | D1: 2026-27 | E1: Total | F1: Share | G1: Lines | H1: Vehicles
A2: ADBLU | B2: =SUMIFS(CostLines!$L$2:$L$1055,CostLines!$C$2:$C$1055,$A2,CostLines!$I$2:$I$1055,B$1) | C2: =SUMIFS(CostLines!$L$2:$L$1055,CostLines!$C$2:$C$1055,$A2,CostLines!$I$2:$I$1055,C$1) | D2: =SUMIFS(CostLines!$L$2:$L$1055,CostLines!$C$2:$C$1055,$A2,CostLines!$I$2:$I$1055,D$1) | E2: =SUM(B2:D2) | F2: =IFERROR(E2/E$10,"") | G2: =COUNTIFS(CostLines!$C$2:$C$1055,$A2) | H2: 28
A3: FC WORK | B3: =SUMIFS(CostLines!$L$2:$L$1055,CostLines!$C$2:$C$1055,$A3,CostLines!$I$2:$I$1055,B$1) | C3: =SUMIFS(CostLines!$L$2:$L$1055,CostLines!$C$2:$C$1055,$A3,CostLines!$I$2:$I$1055,C$1) | D3: =SUMIFS(CostLines!$L$2:$L$1055,CostLines!$C$2:$C$1055,$A3,CostLines!$I$2:$I$1055,D$1) | E3: =SUM(B3:D3) | F3: =IFERROR(E3/E$10,"") | G3: =COUNTIFS(CostLines!$C$2:$C$1055,$A3) | H3: 41
A4: ROAD TAX | B4: =SUMIFS(CostLines!$L$2:$L$1055,CostLines!$C$2:$C$1055,$A4,CostLines!$I$2:$I$1055,B$1) | C4: =SUMIFS(CostLines!$L$2:$L$1055,CostLines!$C$2:$C$1055,$A4,CostLines!$I$2:$I$1055,C$1) | D4: =SUMIFS(CostLines!$L$2:$L$1055,CostLines!$C$2:$C$1055,$A4,CostLines!$I$2:$I$1055,D$1) | E4: =SUM(B4:D4) | F4: =IFERROR(E4/E$10,"") | G4: =COUNTIFS(CostLines!$C$2:$C$1055,$A4) | H4: 52
A5: RTO EXPENSE | B5: =SUMIFS(CostLines!$L$2:$L$1055,CostLines!$C$2:$C$1055,$A5,CostLines!$I$2:$I$1055,B$1) | C5: =SUMIFS(CostLines!$L$2:$L$1055,CostLines!$C$2:$C$1055,$A5,CostLines!$I$2:$I$1055,C$1) | D5: =SUMIFS(CostLines!$L$2:$L$1055,CostLines!$C$2:$C$1055,$A5,CostLines!$I$2:$I$1055,D$1) | E5: =SUM(B5:D5) | F5: =IFERROR(E5/E$10,"") | G5: =COUNTIFS(CostLines!$C$2:$C$1055,$A5) | H5: 44
A6: TYRE | B6: =SUMIFS(CostLines!$L$2:$L$1055,CostLines!$C$2:$C$1055,$A6,CostLines!$I$2:$I$1055,B$1) | C6: =SUMIFS(CostLines!$L$2:$L$1055,CostLines!$C$2:$C$1055,$A6,CostLines!$I$2:$I$1055,C$1) | D6: =SUMIFS(CostLines!$L$2:$L$1055,CostLines!$C$2:$C$1055,$A6,CostLines!$I$2:$I$1055,D$1) | E6: =SUM(B6:D6) | F6: =IFERROR(E6/E$10,"") | G6: =COUNTIFS(CostLines!$C$2:$C$1055,$A6) | H6: 44
A7: VEHICLE INSURANCE | B7: =SUMIFS(CostLines!$L$2:$L$1055,CostLines!$C$2:$C$1055,$A7,CostLines!$I$2:$I$1055,B$1) | C7: =SUMIFS(CostLines!$L$2:$L$1055,CostLines!$C$2:$C$1055,$A7,CostLines!$I$2:$I$1055,C$1) | D7: =SUMIFS(CostLines!$L$2:$L$1055,CostLines!$C$2:$C$1055,$A7,CostLines!$I$2:$I$1055,D$1) | E7: =SUM(B7:D7) | F7: =IFERROR(E7/E$10,"") | G7: =COUNTIFS(CostLines!$C$2:$C$1055,$A7) | H7: 57
A8: VEHICLE OUTSIDE SERVICES | B8: =SUMIFS(CostLines!$L$2:$L$1055,CostLines!$C$2:$C$1055,$A8,CostLines!$I$2:$I$1055,B$1) | C8: =SUMIFS(CostLines!$L$2:$L$1055,CostLines!$C$2:$C$1055,$A8,CostLines!$I$2:$I$1055,C$1) | D8: =SUMIFS(CostLines!$L$2:$L$1055,CostLines!$C$2:$C$1055,$A8,CostLines!$I$2:$I$1055,D$1) | E8: =SUM(B8:D8) | F8: =IFERROR(E8/E$10,"") | G8: =COUNTIFS(CostLines!$C$2:$C$1055,$A8) | H8: 57
A10: Total | B10: =SUM(B2:B8) | C10: =SUM(C2:C8) | D10: =SUM(D2:D8) | E10: =SUM(E2:E8) | G10: =SUM(G2:G8)
A12: Financial years run April-March, taken from each line's From_Date. The Vehicles column is a distinct count computed when this sheet was built, so it does not move with the other columns. The current financial year is still being planned — treat it as partial.

Sheet FleetCoverage
A1: Vehicle | B1: In live fleet | C1: Type (live) | D1: Seat | E1: Compname (live) | F1: Costed | G1: Cost lines | H1: FY total | I1: All-time total
A2: TN02AB5688 | B2: Yes | C2: RENT VEHICLE | D2: 20 | E2: TECHNOTEK - WOVEN - I | F2: =IF(G2>0,"Yes","No") | G2: =COUNTIFS(CostLines!$A$2:$A$1055,$A2) | H2: =SUMIFS(CostLines!$L$2:$L$1055,CostLines!$A$2:$A$1055,$A2,CostLines!$I$2:$I$1055,README!$B$6) | I2: =SUMIFS(CostLines!$L$2:$L$1055,CostLines!$A$2:$A$1055,$A2)
A3: TN030857 | B3: Yes | C3: RENT VEHICLE | D3: 20 | E3: TECHNOTEK - GLOVES - I | F3: =IF(G3>0,"Yes","No") | G3: =COUNTIFS(CostLines!$A$2:$A$1055,$A3) | H3: =SUMIFS(CostLines!$L$2:$L$1055,CostLines!$A$2:$A$1055,$A3,CostLines!$I$2:$I$1055,README!$B$6) | I3: =SUMIFS(CostLines!$L$2:$L$1055,CostLines!$A$2:$A$1055,$A3)
A4: TN05V6697 | B4: Yes | C4: RENT VEHICLE | D4: 20 | E4: TECHNOTEK - GLOVES - I | F4: =IF(G4>0,"Yes","No") | G4: =COUNTIFS(CostLines!$A$2:$A$1055,$A4) | H4: =SUMIFS(CostLines!$L$2:$L$1055,CostLines!$A$2:$A$1055,$A4,CostLines!$I$2:$I$1055,README!$B$6) | I4: =SUMIFS(CostLines!$L$2:$L$1055,CostLines!$A$2:$A$1055,$A4)
A5: TN20AJ3944 | B5: Yes | C5: RENT VEHICLE | D5: 20 | E5: GAINUP - GARMENTS - II | F5: =IF(G5>0,"Yes","No") | G5: =COUNTIFS(CostLines!$A$2:$A$1055,$A5) | H5: =SUMIFS(CostLines!$L$2:$L$1055,CostLines!$A$2:$A$1055,$A5,CostLines!$I$2:$I$1055,README!$B$6) | I5: =SUMIFS(CostLines!$L$2:$L$1055,CostLines!$A$2:$A$1055,$A5)
A6: TN20AK5513 | B6: Yes | C6: RENT VEHICLE | D6: 20 | E6: TECHNOTEK - WOVEN - I | F6: =IF(G6>0,"Yes","No") | G6: =COUNTIFS(CostLines!$A$2:$A$1055,$A6) | H6: =SUMIFS(CostLines!$L$2:$L$1055,CostLines!$A$2:$A$1055,$A6,CostLines!$I$2:$I$1055,README!$B$6) | I6: =SUMIFS(CostLines!$L$2:$L$1055,CostLines!$A$2:$A$1055,$A6)
A7: TN20AL3611 | B7: Yes | C7: RENT VEHICLE | D7: 20 | E7: TECHNOTEK - WOVEN - I | F7: =IF(G7>0,"Yes","No") | G7: =COUNTIFS(CostLines!$A$2:$A$1055,$A7) | H7: =SUMIFS(CostLines!$L$2:$L$1055,CostLines!$A$2:$A$1055,$A7,CostLines!$I$2:$I$1055,README!$B$6) | I7: =SUMIFS(CostLines!$L$2:$L$1055,CostLines!$A$2:$A$1055,$A7)
A8: TN20AU6396 | B8: Yes | C8: RENT VEHICLE | D8: 20 | E8: TECHNOTEK - WOVEN - I | F8: =IF(G8>0,"Yes","No") | G8: =COUNTIFS(CostLines!$A$2:$A$1055,$A8) | H8: =SUMIFS(CostLines!$L$2:$L$1055,CostLines!$A$2:$A$1055,$A8,CostLines!$I$2:$I$1055,README!$B$6) | I8: =SUMIFS(CostLines!$L$2:$L$1055,CostLines!$A$2:$A$1055,$A8)
A9: TN23AC2721 | B9: Yes | C9: RENT VEHICLE | D9: 20 | E9: TECHNOTEK - WOVEN - I | F9: =IF(G9>0,"Yes","No") | G9: =COUNTIFS(CostLines!$A$2:$A$1055,$A9) | H9: =SUMIFS(CostLines!$L$2:$L$1055,CostLines!$A$2:$A$1055,$A9,CostLines!$I$2:$I$1055,README!$B$6) | I9: =SUMIFS(CostLines!$L$2:$L$1055,CostLines!$A$2:$A$1055,$A9)
A10: TN25M4073 | B10: Yes | C10: RENT VEHICLE | D10: 20 | E10: TECHNOTEK - GLOVES - I | F10: =IF(G10>0,"Yes","No") | G10: =COUNTIFS(CostLines!$A$2:$A$1055,$A10) | H10: =SUMIFS(CostLines!$L$2:$L$1055,CostLines!$A$2:$A$1055,$A10,CostLines!$I$2:$I$1055,README!$B$6) | I10: =SUMIFS(CostLines!$L$2:$L$1055,CostLines!$A$2:$A$1055,$A10)
A11: TN25M4928 | B11: Yes | C11: RENT VEHICLE | D11: 20 | E11: GAINUP - GARMENTS - II | F11: =IF(G11>0,"Yes","No") | G11: =COUNTIFS(CostLines!$A$2:$A$1055,$A11) | H11: =SUMIFS(CostLines!$L$2:$L$1055,CostLines!$A$2:$A$1055,$A11,CostLines!$I$2:$I$1055,README!$B$6) | I11: =SUMIFS(CostLines!$L$2:$L$1055,CostLines!$A$2:$A$1055,$A11)
A12: TN31AB3789 | B12: Yes | C12: RENT VEHICLE | D12: 20 | E12: TECHNOTEK - GLOVES - I | F12: =IF(G12>0,"Yes","No") | G12: =COUNTIFS(CostLines!$A$2:$A$1055,$A12) | H12: =SUMIFS(CostLines!$L$2:$L$1055,CostLines!$A$2:$A$1055,$A12,CostLines!$I$2:$I$1055,README!$B$6) | I12: =SUMIFS(CostLines!$L$2:$L$1055,CostLines!$A$2:$A$1055,$A12)
A13: TN31AC0182 | B13: Yes | C13: RENT VEHICLE | D13: 20 | E13: TECHNOTEK - WOVEN - I | F13: =IF(G13>0,"Yes","No") | G13: =COUNTIFS(CostLines!$A$2:$A$1055,$A13) | H13: =SUMIFS(CostLines!$L$2:$L$1055,CostLines!$A$2:$A$1055,$A13,CostLines!$I$2:$I$1055,README!$B$6) | I13: =SUMIFS(CostLines!$L$2:$L$1055,CostLines!$A$2:$A$1055,$A13)
... A29: TN54T2368 | B29: Yes | C29: RENT VEHICLE | D29: 20 | E29: TECHNOTEK - WOVEN - I | F29: =IF(G29>0,"Yes","No") | G29: =COUNTIFS(CostLines!$A$2:$A$1055,$A29) | H29: =SUMIFS(CostLines!$L$2:$L$1055,CostLines!$A$2:$A$1055,$A29,CostLines!$I$2:$I$1055,README!$B$6) | I29: =SUMIFS(CostLines!$L$2:$L$1055,CostLines!$A$2:$A$1055,$A29)
A30: TN57AC3636 | B30: No | F30: =IF(G30>0,"Yes","No") | G30: =COUNTIFS(CostLines!$A$2:$A$1055,$A30) | H30: =SUMIFS(CostLines!$L$2:$L$1055,CostLines!$A$2:$A$1055,$A30,CostLines!$I$2:$I$1055,README!$B$6) | I30: =SUMIFS(CostLines!$L$2:$L$1055,CostLines!$A$2:$A$1055,$A30)
A31: TN57AE3636 | B31: Yes | C31: COMPANY VEHICLE | D31: 41 | E31: GAINUP - SPINNING | F31: =IF(G31>0,"Yes","No") | G31: =COUNTIFS(CostLines!$A$2:$A$1055,$A31) | H31: =SUMIFS(CostLines!$L$2:$L$1055,CostLines!$A$2:$A$1055,$A31,CostLines!$I$2:$I$1055,README!$B$6) | I31: =SUMIFS(CostLines!$L$2:$L$1055,CostLines!$A$2:$A$1055,$A31)
A32: TN57AE9806 | B32: No | F32: =IF(G32>0,"Yes","No") | G32: =COUNTIFS(CostLines!$A$2:$A$1055,$A32) | H32: =SUMIFS(CostLines!$L$2:$L$1055,CostLines!$A$2:$A$1055,$A32,CostLines!$I$2:$I$1055,README!$B$6) | I32: =SUMIFS(CostLines!$L$2:$L$1055,CostLines!$A$2:$A$1055,$A32)
A33: TN57AF3636 | B33: No | F33: =IF(G33>0,"Yes","No") | G33: =COUNTIFS(CostLines!$A$2:$A$1055,$A33) | H33: =SUMIFS(CostLines!$L$2:$L$1055,CostLines!$A$2:$A$1055,$A33,CostLines!$I$2:$I$1055,README!$B$6) | I33: =SUMIFS(CostLines!$L$2:$L$1055,CostLines!$A$2:$A$1055,$A33)
A34: TN57AH3636 | B34: No | F34: =IF(G34>0,"Yes","No") | G34: =COUNTIFS(CostLines!$A$2:$A$1055,$A34) | H34: =SUMIFS(CostLines!$L$2:$L$1055,CostLines!$A$2:$A$1055,$A34,CostLines!$I$2:$I$1055,README!$B$6) | I34: =SUMIFS(CostLines!$L$2:$L$1055,CostLines!$A$2:$A$1055,$A34)
A35: TN57AK3636 | B35: No | F35: =IF(G35>0,"Yes","No") | G35: =COUNTIFS(CostLines!$A$2:$A$1055,$A35) | H35: =SUMIFS(CostLines!$L$2:$L$1055,CostLines!$A$2:$A$1055,$A35,CostLines!$I$2:$I$1055,README!$B$6) | I35: =SUMIFS(CostLines!$L$2:$L$1055,CostLines!$A$2:$A$1055,$A35)
A36: TN57AM3636 | B36: No | F36: =IF(G36>0,"Yes","No") | G36: =COUNTIFS(CostLines!$A$2:$A$1055,$A36) | H36: =SUMIFS(CostLines!$L$2:$L$1055,CostLines!$A$2:$A$1055,$A36,CostLines!$I$2:$I$1055,README!$B$6) | I36: =SUMIFS(CostLines!$L$2:$L$1055,CostLines!$A$2:$A$1055,$A36)
A37: TN57AU3636 | B37: Yes | C37: COMPANY VEHICLE | D37: 41 | E37: TECHNOTEK - WOVEN - I | F37: =IF(G37>0,"Yes","No") | G37: =COUNTIFS(CostLines!$A$2:$A$1055,$A37) | H37: =SUMIFS(CostLines!$L$2:$L$1055,CostLines!$A$2:$A$1055,$A37,CostLines!$I$2:$I$1055,README!$B$6) | I37: =SUMIFS(CostLines!$L$2:$L$1055,CostLines!$A$2:$A$1055,$A37)
A38: TN57BC3636 | B38: Yes | C38: COMPANY VEHICLE | D38: 49 | E38: TECHNOTEK - WOVEN - I | F38: =IF(G38>0,"Yes","No") | G38: =COUNTIFS(CostLines!$A$2:$A$1055,$A38) | H38: =SUMIFS(CostLines!$L$2:$L$1055,CostLines!$A$2:$A$1055,$A38,CostLines!$I$2:$I$1055,README!$B$6) | I38: =SUMIFS(CostLines!$L$2:$L$1055,CostLines!$A$2:$A$1055,$A38)
A39: TN57BE3636 | B39: No | F39: =IF(G39>0,"Yes","No") | G39: =COUNTIFS(CostLines!$A$2:$A$1055,$A39) | H39: =SUMIFS(CostLines!$L$2:$L$1055,CostLines!$A$2:$A$1055,$A39,CostLines!$I$2:$I$1055,README!$B$6) | I39: =SUMIFS(CostLines!$L$2:$L$1055,CostLines!$A$2:$A$1055,$A39)
A40: TN57BH3636 | B40: Yes | C40: COMPANY VEHICLE | D40: 39 | E40: GAINUP - SOCKS - II | F40: =IF(G40>0,"Yes","No") | G40: =COUNTIFS(CostLines!$A$2:$A$1055,$A40) | H40: =SUMIFS(CostLines!$L$2:$L$1055,CostLines!$A$2:$A$1055,$A40,CostLines!$I$2:$I$1055,README!$B$6) | I40: =SUMIFS(CostLines!$L$2:$L$1055,CostLines!$A$2:$A$1055,$A40)
A41: TN57BL3636 | B41: No | F41: =IF(G41>0,"Yes","No") | G41: =COUNTIFS(CostLines!$A$2:$A$1055,$A41) | H41: =SUMIFS(CostLines!$L$2:$L$1055,CostLines!$A$2:$A$1055,$A41,CostLines!$I$2:$I$1055,README!$B$6) | I41: =SUMIFS(CostLines!$L$2:$L$1055,CostLines!$A$2:$A$1055,$A41)
A42: TN57BM3636 | B42: Yes | C42: COMPANY VEHICLE | D42: 36 | E42: GAINUP - SPINNING | F42: =IF(G42>0,"Yes","No") | G42: =COUNTIFS(CostLines!$A$2:$A$1055,$A42) | H42: =SUMIFS(CostLines!$L$2:$L$1055,CostLines!$A$2:$A$1055,$A42,CostLines!$I$2:$I$1055,README!$B$6) | I42: =SUMIFS(CostLines!$L$2:$L$1055,CostLines!$A$2:$A$1055,$A42)
A43: TN57BP3434 | B43: Yes | C43: COMPANY VEHICLE | D43: 54 | E43: TECHNOTEK - WOVEN - I | F43: =IF(G43>0,"Yes","No") | G43: =COUNTIFS(CostLines!$A$2:$A$1055,$A43) | H43: =SUMIFS(CostLines!$L$2:$L$1055,CostLines!$A$2:$A$1055,$A43,CostLines!$I$2:$I$1055,README!$B$6) | I43: =SUMIFS(CostLines!$L$2:$L$1055,CostLines!$A$2:$A$1055,$A43)
A44: TN57BP3636 | B44: No | F44: =IF(G44>0,"Yes","No") | G44: =COUNTIFS(CostLines!$A$2:$A$1055,$A44) | H44: =SUMIFS(CostLines!$L$2:$L$1055,CostLines!$A$2:$A$1055,$A44,CostLines!$I$2:$I$1055,README!$B$6) | I44: =SUMIFS(CostLines!$L$2:$L$1055,CostLines!$A$2:$A$1055,$A44)
A45: TN57BP5356 | B45: No | F45: =IF(G45>0,"Yes","No") | G45: =COUNTIFS(CostLines!$A$2:$A$1055,$A45) | H45: =SUMIFS(CostLines!$L$2:$L$1055,CostLines!$A$2:$A$1055,$A45,CostLines!$I$2:$I$1055,README!$B$6) | I45: =SUMIFS(CostLines!$L$2:$L$1055,CostLines!$A$2:$A$1055,$A45)
A46: TN57BQ3434 | B46: Yes | C46: COMPANY VEHICLE | D46: 54 | E46: TECHNOTEK - GLOVES - I | F46: =IF(G46>0,"Yes","No") | G46: =COUNTIFS(CostLines!$A$2:$A$1055,$A46) | H46: =SUMIFS(CostLines!$L$2:$L$1055,CostLines!$A$2:$A$1055,$A46,CostLines!$I$2:$I$1055,README!$B$6) | I46: =SUMIFS(CostLines!$L$2:$L$1055,CostLines!$A$2:$A$1055,$A46)
A47: TN57BQ3636 | B47: Yes | C47: COMPANY VEHICLE | D47: 36 | E47: GAINUP - SOCKS - I | F47: =IF(G47>0,"Yes","No") | G47: =COUNTIFS(CostLines!$A$2:$A$1055,$A47) | H47: =SUMIFS(CostLines!$L$2:$L$1055,CostLines!$A$2:$A$1055,$A47,CostLines!$I$2:$I$1055,README!$B$6) | I47: =SUMIFS(CostLines!$L$2:$L$1055,CostLines!$A$2:$A$1055,$A47)
A48: TN57BR3434 | B48: Yes | C48: COMPANY VEHICLE | D48: 54 | E48: GAINUP - SPINNING | F48: =IF(G48>0,"Yes","No") | G48: =COUNTIFS(CostLines!$A$2:$A$1055,$A48) | H48: =SUMIFS(CostLines!$L$2:$L$1055,CostLines!$A$2:$A$1055,$A48,CostLines!$I$2:$I$1055,README!$B$6) | I48: =SUMIFS(CostLines!$L$2:$L$1055,CostLines!$A$2:$A$1055,$A48)
A49: TN57BS3142 | B49: No | F49: =IF(G49>0,"Yes","No") | G49: =COUNTIFS(CostLines!$A$2:$A$1055,$A49) | H49: =SUMIFS(CostLines!$L$2:$L$1055,CostLines!$A$2:$A$1055,$A49,CostLines!$I$2:$I$1055,README!$B$6) | I49: =SUMIFS(CostLines!$L$2:$L$1055,CostLines!$A$2:$A$1055,$A49)
A50: TN57BS3434 | B50: Yes | C50: COMPANY VEHICLE | D50: 54 | E50: TECHNOTEK - GLOVES - I | F50: =IF(G50>0,"Yes","No") | G50: =COUNTIFS(CostLines!$A$2:$A$1055,$A50) | H50: =SUMIFS(CostLines!$L$2:$L$1055,CostLines!$A$2:$A$1055,$A50,CostLines!$I$2:$I$1055,README!$B$6) | I50: =SUMIFS(CostLines!$L$2:$L$1055,CostLines!$A$2:$A$1055,$A50)
A51: TN57BS3636 | B51: No | F51: =IF(G51>0,"Yes","No") | G51: =COUNTIFS(CostLines!$A$2:$A$1055,$A51) | H51: =SUMIFS(CostLines!$L$2:$L$1055,CostLines!$A$2:$A$1055,$A51,CostLines!$I$2:$I$1055,README!$B$6) | I51: =SUMIFS(CostLines!$L$2:$L$1055,CostLines!$A$2:$A$1055,$A51)
A52: TN57BS8404 | B52: No | F52: =IF(G52>0,"Yes","No") | G52: =COUNTIFS(CostLines!$A$2:$A$1055,$A52) | H52: =SUMIFS(CostLines!$L$2:$L$1055,CostLines!$A$2:$A$1055,$A52,CostLines!$I$2:$I$1055,README!$B$6) | I52: =SUMIFS(CostLines!$L$2:$L$1055,CostLines!$A$2:$A$1055,$A52)
A53: TN57BX3636 | B53: No | F53: =IF(G53>0,"Yes","No") | G53: =COUNTIFS(CostLines!$A$2:$A$1055,$A53) | H53: =SUMIFS(CostLines!$L$2:$L$1055,CostLines!$A$2:$A$1055,$A53,CostLines!$I$2:$I$1055,README!$B$6) | I53: =SUMIFS(CostLines!$L$2:$L$1055,CostLines!$A$2:$A$1055,$A53)
A54: TN57CA3434 | B54: Yes | C54: COMPANY VEHICLE | D54: 54 | E54: GAINUP - SPINNING | F54: =IF(G54>0,"Yes","No") | G54: =COUNTIFS(CostLines!$A$2:$A$1055,$A54) | H54: =SUMIFS(CostLines!$L$2:$L$1055,CostLines!$A$2:$A$1055,$A54,CostLines!$I$2:$I$1055,README!$B$6) | I54: =SUMIFS(CostLines!$L$2:$L$1055,CostLines!$A$2:$A$1055,$A54)
A55: TN57CA3636 | B55: Yes | C55: COMPANY VEHICLE | D55: 49 | E55: GAINUP - GARMENTS - I | F55: =IF(G55>0,"Yes","No") | G55: =COUNTIFS(CostLines!$A$2:$A$1055,$A55) | H55: =SUMIFS(CostLines!$L$2:$L$1055,CostLines!$A$2:$A$1055,$A55,CostLines!$I$2:$I$1055,README!$B$6) | I55: =SUMIFS(CostLines!$L$2:$L$1055,CostLines!$A$2:$A$1055,$A55)
A56: TN57CB3434 | B56: Yes | C56: COMPANY VEHICLE | D56: 54 | E56: GAINUP - GARMENTS - I | F56: =IF(G56>0,"Yes","No") | G56: =COUNTIFS(CostLines!$A$2:$A$1055,$A56) | H56: =SUMIFS(CostLines!$L$2:$L$1055,CostLines!$A$2:$A$1055,$A56,CostLines!$I$2:$I$1055,README!$B$6) | I56: =SUMIFS(CostLines!$L$2:$L$1055,CostLines!$A$2:$A$1055,$A56)
A57: TN57CB3636 | B57: Yes | C57: COMPANY VEHICLE | D57: 49 | E57: GAINUP - SOCKS - II | F57: =IF(G57>0,"Yes","No") | G57: =COUNTIFS(CostLines!$A$2:$A$1055,$A57) | H57: =SUMIFS(CostLines!$L$2:$L$1055,CostLines!$A$2:$A$1055,$A57,CostLines!$I$2:$I$1055,README!$B$6) | I57: =SUMIFS(CostLines!$L$2:$L$1055,CostLines!$A$2:$A$1055,$A57)
A58: TN57CC3636 | B58: Yes | C58: COMPANY VEHICLE | D58: 49 | E58: TECHNOTEK - WOVEN - I | F58: =IF(G58>0,"Yes","No") | G58: =COUNTIFS(CostLines!$A$2:$A$1055,$A58) | H58: =SUMIFS(CostLines!$L$2:$L$1055,CostLines!$A$2:$A$1055,$A58,CostLines!$I$2:$I$1055,README!$B$6) | I58: =SUMIFS(CostLines!$L$2:$L$1055,CostLines!$A$2:$A$1055,$A58)
A59: TN57CD3434 | B59: Yes | C59: COMPANY VEHICLE | D59: 54 | E59: GAINUP - GARMENTS - I | F59: =IF(G59>0,"Yes","No") | G59: =COUNTIFS(CostLines!$A$2:$A$1055,$A59) | H59: =SUMIFS(CostLines!$L$2:$L$1055,CostLines!$A$2:$A$1055,$A59,CostLines!$I$2:$I$1055,README!$B$6) | I59: =SUMIFS(CostLines!$L$2:$L$1055,CostLines!$A$2:$A$1055,$A59)
A60: TN57CD3636 | B60: No | F60: =IF(G60>0,"Yes","No") | G60: =COUNTIFS(CostLines!$A$2:$A$1055,$A60) | H60: =SUMIFS(CostLines!$L$2:$L$1055,CostLines!$A$2:$A$1055,$A60,CostLines!$I$2:$I$1055,README!$B$6) | I60: =SUMIFS(CostLines!$L$2:$L$1055,CostLines!$A$2:$A$1055,$A60)
A61: TN57CE3434 | B61: Yes | C61: COMPANY VEHICLE | D61: 54 | E61: TECHNOTEK - WOVEN - I | F61: =IF(G61>0,"Yes","No") | G61: =COUNTIFS(CostLines!$A$2:$A$1055,$A61) | H61: =SUMIFS(CostLines!$L$2:$L$1055,CostLines!$A$2:$A$1055,$A61,CostLines!$I$2:$I$1055,README!$B$6) | I61: =SUMIFS(CostLines!$L$2:$L$1055,CostLines!$A$2:$A$1055,$A61)
A62: TN57CE3636 | B62: Yes | C62: COMPANY VEHICLE | D62: 54 | E62: GAINUP - SPINNING | F62: =IF(G62>0,"Yes","No") | G62: =COUNTIFS(CostLines!$A$2:$A$1055,$A62) | H62: =SUMIFS(CostLines!$L$2:$L$1055,CostLines!$A$2:$A$1055,$A62,CostLines!$I$2:$I$1055,README!$B$6) | I62: =SUMIFS(CostLines!$L$2:$L$1055,CostLines!$A$2:$A$1055,$A62)
A63: TN57CF3434 | B63: Yes | C63: COMPANY VEHICLE | D63: 54 | E63: TECHNOTEK - GLOVES - I | F63: =IF(G63>0,"Yes","No") | G63: =COUNTIFS(CostLines!$A$2:$A$1055,$A63) | H63: =SUMIFS(CostLines!$L$2:$L$1055,CostLines!$A$2:$A$1055,$A63,CostLines!$I$2:$I$1055,README!$B$6) | I63: =SUMIFS(CostLines!$L$2:$L$1055,CostLines!$A$2:$A$1055,$A63)
A64: TN57CF3636 | B64: Yes | C64: COMPANY VEHICLE | D64: 54 | E64: TECHNOTEK - GLOVES - I | F64: =IF(G64>0,"Yes","No") | G64: =COUNTIFS(CostLines!$A$2:$A$1055,$A64) | H64: =SUMIFS(CostLines!$L$2:$L$1055,CostLines!$A$2:$A$1055,$A64,CostLines!$I$2:$I$1055,README!$B$6) | I64: =SUMIFS(CostLines!$L$2:$L$1055,CostLines!$A$2:$A$1055,$A64)
A65: TN57CH3636 | B65: Yes | C65: COMPANY VEHICLE | D65: 54 | E65: TECHNOTEK - WOVEN - I | F65: =IF(G65>0,"Yes","No") | G65: =COUNTIFS(CostLines!$A$2:$A$1055,$A65) | H65: =SUMIFS(CostLines!$L$2:$L$1055,CostLines!$A$2:$A$1055,$A65,CostLines!$I$2:$I$1055,README!$B$6) | I65: =SUMIFS(CostLines!$L$2:$L$1055,CostLines!$A$2:$A$1055,$A65)
A66: TN57CJ3434 | B66: Yes | C66: COMPANY VEHICLE | D66: 54 | E66: GAINUP - GARMENTS - II | F66: =IF(G66>0,"Yes","No") | G66: =COUNTIFS(CostLines!$A$2:$A$1055,$A66) | H66: =SUMIFS(CostLines!$L$2:$L$1055,CostLines!$A$2:$A$1055,$A66,CostLines!$I$2:$I$1055,README!$B$6) | I66: =SUMIFS(CostLines!$L$2:$L$1055,CostLines!$A$2:$A$1055,$A66)
A67: TN57CJ3636 | B67: Yes | C67: COMPANY VEHICLE | D67: 54 | E67: GAINUP - GARMENTS - II | F67: =IF(G67>0,"Yes","No") | G67: =COUNTIFS(CostLines!$A$2:$A$1055,$A67) | H67: =SUMIFS(CostLines!$L$2:$L$1055,CostLines!$A$2:$A$1055,$A67,CostLines!$I$2:$I$1055,README!$B$6) | I67: =SUMIFS(CostLines!$L$2:$L$1055,CostLines!$A$2:$A$1055,$A67)
A68: TN57CK3434 | B68: Yes | C68: COMPANY VEHICLE | D68: 54 | E68: GAINUP - GARMENTS | F68: =IF(G68>0,"Yes","No") | G68: =COUNTIFS(CostLines!$A$2:$A$1055,$A68) | H68: =SUMIFS(CostLines!$L$2:$L$1055,CostLines!$A$2:$A$1055,$A68,CostLines!$I$2:$I$1055,README!$B$6) | I68: =SUMIFS(CostLines!$L$2:$L$1055,CostLines!$A$2:$A$1055,$A68)
A69: TN57CK3636 | B69: Yes | C69: COMPANY VEHICLE | D69: 54 | E69: GAINUP - SOCKS - I | F69: =IF(G69>0,"Yes","No") | G69: =COUNTIFS(CostLines!$A$2:$A$1055,$A69) | H69: =SUMIFS(CostLines!$L$2:$L$1055,CostLines!$A$2:$A$1055,$A69,CostLines!$I$2:$I$1055,README!$B$6) | I69: =SUMIFS(CostLines!$L$2:$L$1055,CostLines!$A$2:$A$1055,$A69)
A70: TN57CL3434 | B70: Yes | C70: COMPANY VEHICLE | D70: 54 | E70: TECHNOTEK - WOVEN - I | F70: =IF(G70>0,"Yes","No") | G70: =COUNTIFS(CostLines!$A$2:$A$1055,$A70) | H70: =SUMIFS(CostLines!$L$2:$L$1055,CostLines!$A$2:$A$1055,$A70,CostLines!$I$2:$I$1055,README!$B$6) | I70: =SUMIFS(CostLines!$L$2:$L$1055,CostLines!$A$2:$A$1055,$A70)
A71: TN57CL3636 | B71: No | F71: =IF(G71>0,"Yes","No") | G71: =COUNTIFS(CostLines!$A$2:$A$1055,$A71) | H71: =SUMIFS(CostLines!$L$2:$L$1055,CostLines!$A$2:$A$1055,$A71,CostLines!$I$2:$I$1055,README!$B$6) | I71: =SUMIFS(CostLines!$L$2:$L$1055,CostLines!$A$2:$A$1055,$A71)
A72: TN57CM3636 | B72: No | F72: =IF(G72>0,"Yes","No") | G72: =COUNTIFS(CostLines!$A$2:$A$1055,$A72) | H72: =SUMIFS(CostLines!$L$2:$L$1055,CostLines!$A$2:$A$1055,$A72,CostLines!$I$2:$I$1055,README!$B$6) | I72: =SUMIFS(CostLines!$L$2:$L$1055,CostLines!$A$2:$A$1055,$A72)
A73: TN57L8446 | B73: Yes | C73: RENT VEHICLE | D73: 20 | E73: TECHNOTEK - WOVEN - I | F73: =IF(G73>0,"Yes","No") | G73: =COUNTIFS(CostLines!$A$2:$A$1055,$A73) | H73: =SUMIFS(CostLines!$L$2:$L$1055,CostLines!$A$2:$A$1055,$A73,CostLines!$I$2:$I$1055,README!$B$6) | I73: =SUMIFS(CostLines!$L$2:$L$1055,CostLines!$A$2:$A$1055,$A73)
A74: TN57P6909 | B74: Yes | C74: RENT VEHICLE | D74: 20 | E74: GAINUP - GARMENTS - II | F74: =IF(G74>0,"Yes","No") | G74: =COUNTIFS(CostLines!$A$2:$A$1055,$A74) | H74: =SUMIFS(CostLines!$L$2:$L$1055,CostLines!$A$2:$A$1055,$A74,CostLines!$I$2:$I$1055,README!$B$6) | I74: =SUMIFS(CostLines!$L$2:$L$1055,CostLines!$A$2:$A$1055,$A74)
A75: TN58BC3494 | B75: Yes | C75: RENT VEHICLE | D75: 20 | E75: TECHNOTEK - WOVEN - I | F75: =IF(G75>0,"Yes","No") | G75: =COUNTIFS(CostLines!$A$2:$A$1055,$A75) | H75: =SUMIFS(CostLines!$L$2:$L$1055,CostLines!$A$2:$A$1055,$A75,CostLines!$I$2:$I$1055,README!$B$6) | I75: =SUMIFS(CostLines!$L$2:$L$1055,CostLines!$A$2:$A$1055,$A75)
A76: TN58BJ3434 | B76: No | F76: =IF(G76>0,"Yes","No") | G76: =COUNTIFS(CostLines!$A$2:$A$1055,$A76) | H76: =SUMIFS(CostLines!$L$2:$L$1055,CostLines!$A$2:$A$1055,$A76,CostLines!$I$2:$I$1055,README!$B$6) | I76: =SUMIFS(CostLines!$L$2:$L$1055,CostLines!$A$2:$A$1055,$A76)
A77: TN58BJ3636 | B77: No | F77: =IF(G77>0,"Yes","No") | G77: =COUNTIFS(CostLines!$A$2:$A$1055,$A77) | H77: =SUMIFS(CostLines!$L$2:$L$1055,CostLines!$A$2:$A$1055,$A77,CostLines!$I$2:$I$1055,README!$B$6) | I77: =SUMIFS(CostLines!$L$2:$L$1055,CostLines!$A$2:$A$1055,$A77)
A78: TN58BK3434 | B78: No | F78: =IF(G78>0,"Yes","No") | G78: =COUNTIFS(CostLines!$A$2:$A$1055,$A78) | H78: =SUMIFS(CostLines!$L$2:$L$1055,CostLines!$A$2:$A$1055,$A78,CostLines!$I$2:$I$1055,README!$B$6) | I78: =SUMIFS(CostLines!$L$2:$L$1055,CostLines!$A$2:$A$1055,$A78)
A79: TN58BK3636 | B79: Yes | C79: COMPANY VEHICLE | D79: 54 | E79: GAINUP - GARMENTS | F79: =IF(G79>0,"Yes","No") | G79: =COUNTIFS(CostLines!$A$2:$A$1055,$A79) | H79: =SUMIFS(CostLines!$L$2:$L$1055,CostLines!$A$2:$A$1055,$A79,CostLines!$I$2:$I$1055,README!$B$6) | I79: =SUMIFS(CostLines!$L$2:$L$1055,CostLines!$A$2:$A$1055,$A79)
A80: TN58BL3434 | B80: Yes | C80: COMPANY VEHICLE | D80: 54 | E80: TECHNOTEK - WOVEN - I | F80: =IF(G80>0,"Yes","No") | G80: =COUNTIFS(CostLines!$A$2:$A$1055,$A80) | H80: =SUMIFS(CostLines!$L$2:$L$1055,CostLines!$A$2:$A$1055,$A80,CostLines!$I$2:$I$1055,README!$B$6) | I80: =SUMIFS(CostLines!$L$2:$L$1055,CostLines!$A$2:$A$1055,$A80)
A81: TN58BL3636 | B81: Yes | C81: COMPANY VEHICLE | D81: 54 | E81: GAINUP - GARMENTS - I | F81: =IF(G81>0,"Yes","No") | G81: =COUNTIFS(CostLines!$A$2:$A$1055,$A81) | H81: =SUMIFS(CostLines!$L$2:$L$1055,CostLines!$A$2:$A$1055,$A81,CostLines!$I$2:$I$1055,README!$B$6) | I81: =SUMIFS(CostLines!$L$2:$L$1055,CostLines!$A$2:$A$1055,$A81)
A82: TN58BM3434 | B82: Yes | C82: COMPANY VEHICLE | D82: 54 | E82: TECHNOTEK - WOVEN - I | F82: =IF(G82>0,"Yes","No") | G82: =COUNTIFS(CostLines!$A$2:$A$1055,$A82) | H82: =SUMIFS(CostLines!$L$2:$L$1055,CostLines!$A$2:$A$1055,$A82,CostLines!$I$2:$I$1055,README!$B$6) | I82: =SUMIFS(CostLines!$L$2:$L$1055,CostLines!$A$2:$A$1055,$A82)
A83: TN58BM3636 | B83: Yes | C83: COMPANY VEHICLE | D83: 54 | E83: GAINUP - GARMENTS - I | F83: =IF(G83>0,"Yes","No") | G83: =COUNTIFS(CostLines!$A$2:$A$1055,$A83) | H83: =SUMIFS(CostLines!$L$2:$L$1055,CostLines!$A$2:$A$1055,$A83,CostLines!$I$2:$I$1055,README!$B$6) | I83: =SUMIFS(CostLines!$L$2:$L$1055,CostLines!$A$2:$A$1055,$A83)
A84: TN58BP3434 | B84: Yes | C84: COMPANY VEHICLE | D84: 54 | E84: TECHNOTEK - GLOVES - I | F84: =IF(G84>0,"Yes","No") | G84: =COUNTIFS(CostLines!$A$2:$A$1055,$A84) | H84: =SUMIFS(CostLines!$L$2:$L$1055,CostLines!$A$2:$A$1055,$A84,CostLines!$I$2:$I$1055,README!$B$6) | I84: =SUMIFS(CostLines!$L$2:$L$1055,CostLines!$A$2:$A$1055,$A84)
A85: TN58BP3636 | B85: No | F85: =IF(G85>0,"Yes","No") | G85: =COUNTIFS(CostLines!$A$2:$A$1055,$A85) | H85: =SUMIFS(CostLines!$L$2:$L$1055,CostLines!$A$2:$A$1055,$A85,CostLines!$I$2:$I$1055,README!$B$6) | I85: =SUMIFS(CostLines!$L$2:$L$1055,CostLines!$A$2:$A$1055,$A85)
A86: TN58BQ3434 | B86: No | F86: =IF(G86>0,"Yes","No") | G86: =COUNTIFS(CostLines!$A$2:$A$1055,$A86) | H86: =SUMIFS(CostLines!$L$2:$L$1055,CostLines!$A$2:$A$1055,$A86,CostLines!$I$2:$I$1055,README!$B$6) | I86: =SUMIFS(CostLines!$L$2:$L$1055,CostLines!$A$2:$A$1055,$A86)
A87: TN58BQ3636 | B87: No | F87: =IF(G87>0,"Yes","No") | G87: =COUNTIFS(CostLines!$A$2:$A$1055,$A87) | H87: =SUMIFS(CostLines!$L$2:$L$1055,CostLines!$A$2:$A$1055,$A87,CostLines!$I$2:$I$1055,README!$B$6) | I87: =SUMIFS(CostLines!$L$2:$L$1055,CostLines!$A$2:$A$1055,$A87)
A88: TN58BR3434 | B88: Yes | C88: COMPANY VEHICLE | D88: 54 | E88: GAINUP - SOCKS - I | F88: =IF(G88>0,"Yes","No") | G88: =COUNTIFS(CostLines!$A$2:$A$1055,$A88) | H88: =SUMIFS(CostLines!$L$2:$L$1055,CostLines!$A$2:$A$1055,$A88,CostLines!$I$2:$I$1055,README!$B$6) | I88: =SUMIFS(CostLines!$L$2:$L$1055,CostLines!$A$2:$A$1055,$A88)
A89: TN58BR3636 | B89: No | F89: =IF(G89>0,"Yes","No") | G89: =COUNTIFS(CostLines!$A$2:$A$1055,$A89) | H89: =SUMIFS(CostLines!$L$2:$L$1055,CostLines!$A$2:$A$1055,$A89,CostLines!$I$2:$I$1055,README!$B$6) | I89: =SUMIFS(CostLines!$L$2:$L$1055,CostLines!$A$2:$A$1055,$A89)
A90: TN58BS3434 | B90: Yes | C90: COMPANY VEHICLE | D90: 54 | E90: GAINUP - GARMENTS - I | F90: =IF(G90>0,"Yes","No") | G90: =COUNTIFS(CostLines!$A$2:$A$1055,$A90) | H90: =SUMIFS(CostLines!$L$2:$L$1055,CostLines!$A$2:$A$1055,$A90,CostLines!$I$2:$I$1055,README!$B$6) | I90: =SUMIFS(CostLines!$L$2:$L$1055,CostLines!$A$2:$A$1055,$A90)
A91: TN58BS3636 | B91: No | F91: =IF(G91>0,"Yes","No") | G91: =COUNTIFS(CostLines!$A$2:$A$1055,$A91) | H91: =SUMIFS(CostLines!$L$2:$L$1055,CostLines!$A$2:$A$1055,$A91,CostLines!$I$2:$I$1055,README!$B$6) | I91: =SUMIFS(CostLines!$L$2:$L$1055,CostLines!$A$2:$A$1055,$A91)
A92: TN58CA3636 | B92: No | F92: =IF(G92>0,"Yes","No") | G92: =COUNTIFS(CostLines!$A$2:$A$1055,$A92) | H92: =SUMIFS(CostLines!$L$2:$L$1055,CostLines!$A$2:$A$1055,$A92,CostLines!$I$2:$I$1055,README!$B$6) | I92: =SUMIFS(CostLines!$L$2:$L$1055,CostLines!$A$2:$A$1055,$A92)
A93: TN58S5303 | B93: Yes | C93: RENT VEHICLE | D93: 20 | E93: TECHNOTEK - HEADWEAR - I | F93: =IF(G93>0,"Yes","No") | G93: =COUNTIFS(CostLines!$A$2:$A$1055,$A93) | H93: =SUMIFS(CostLines!$L$2:$L$1055,CostLines!$A$2:$A$1055,$A93,CostLines!$I$2:$I$1055,README!$B$6) | I93: =SUMIFS(CostLines!$L$2:$L$1055,CostLines!$A$2:$A$1055,$A93)
A94: TN59AB3444 | B94: Yes | C94: RENT VEHICLE | D94: 20 | E94: TECHNOTEK - HEADWEAR - I | F94: =IF(G94>0,"Yes","No") | G94: =COUNTIFS(CostLines!$A$2:$A$1055,$A94) | H94: =SUMIFS(CostLines!$L$2:$L$1055,CostLines!$A$2:$A$1055,$A94,CostLines!$I$2:$I$1055,README!$B$6) | I94: =SUMIFS(CostLines!$L$2:$L$1055,CostLines!$A$2:$A$1055,$A94)
A95: TN59AH9703 | B95: Yes | C95: RENT VEHICLE | D95: 20 | E95: TECHNOTEK - WOVEN - I | F95: =IF(G95>0,"Yes","No") | G95: =COUNTIFS(CostLines!$A$2:$A$1055,$A95) | H95: =SUMIFS(CostLines!$L$2:$L$1055,CostLines!$A$2:$A$1055,$A95,CostLines!$I$2:$I$1055,README!$B$6) | I95: =SUMIFS(CostLines!$L$2:$L$1055,CostLines!$A$2:$A$1055,$A95)
A96: TN60AP3434 | B96: Yes | C96: COMPANY VEHICLE | D96: 54 | E96: TECHNOTEK - WOVEN - I | F96: =IF(G96>0,"Yes","No") | G96: =COUNTIFS(CostLines!$A$2:$A$1055,$A96) | H96: =SUMIFS(CostLines!$L$2:$L$1055,CostLines!$A$2:$A$1055,$A96,CostLines!$I$2:$I$1055,README!$B$6) | I96: =SUMIFS(CostLines!$L$2:$L$1055,CostLines!$A$2:$A$1055,$A96)
A97: TN60AQ3434 | B97: Yes | C97: COMPANY VEHICLE | D97: 54 | E97: TECHNOTEK - WOVEN - I | F97: =IF(G97>0,"Yes","No") | G97: =COUNTIFS(CostLines!$A$2:$A$1055,$A97) | H97: =SUMIFS(CostLines!$L$2:$L$1055,CostLines!$A$2:$A$1055,$A97,CostLines!$I$2:$I$1055,README!$B$6) | I97: =SUMIFS(CostLines!$L$2:$L$1055,CostLines!$A$2:$A$1055,$A97)
A98: TN60AS3434 | B98: Yes | C98: COMPANY VEHICLE | D98: 54 | E98: TECHNOTEK - WOVEN - I | F98: =IF(G98>0,"Yes","No") | G98: =COUNTIFS(CostLines!$A$2:$A$1055,$A98) | H98: =SUMIFS(CostLines!$L$2:$L$1055,CostLines!$A$2:$A$1055,$A98,CostLines!$I$2:$I$1055,README!$B$6) | I98: =SUMIFS(CostLines!$L$2:$L$1055,CostLines!$A$2:$A$1055,$A98)
A99: TN60AS3636 | B99: Yes | C99: COMPANY VEHICLE | D99: 54 | E99: GAINUP - PRINTING & EMBROIDERY | F99: =IF(G99>0,"Yes","No") | G99: =COUNTIFS(CostLines!$A$2:$A$1055,$A99) | H99: =SUMIFS(CostLines!$L$2:$L$1055,CostLines!$A$2:$A$1055,$A99,CostLines!$I$2:$I$1055,README!$B$6) | I99: =SUMIFS(CostLines!$L$2:$L$1055,CostLines!$A$2:$A$1055,$A99)
A100: TN63E9861 | B100: Yes | C100: RENT VEHICLE | D100: 20 | E100: TECHNOTEK - WOVEN - I | F100: =IF(G100>0,"Yes","No") | G100: =COUNTIFS(CostLines!$A$2:$A$1055,$A100) | H100: =SUMIFS(CostLines!$L$2:$L$1055,CostLines!$A$2:$A$1055,$A100,CostLines!$I$2:$I$1055,README!$B$6) | I100: =SUMIFS(CostLines!$L$2:$L$1055,CostLines!$A$2:$A$1055,$A100)
A101: TN63U4754 | B101: Yes | C101: RENT VEHICLE | D101: 20 | E101: GAINUP - GARMENTS - I | F101: =IF(G101>0,"Yes","No") | G101: =COUNTIFS(CostLines!$A$2:$A$1055,$A101) | H101: =SUMIFS(CostLines!$L$2:$L$1055,CostLines!$A$2:$A$1055,$A101,CostLines!$I$2:$I$1055,README!$B$6) | I101: =SUMIFS(CostLines!$L$2:$L$1055,CostLines!$A$2:$A$1055,$A101)
A102: TN69M1957 | B102: Yes | C102: RENT VEHICLE | D102: 20 | E102: TECHNOTEK - GLOVES - I | F102: =IF(G102>0,"Yes","No") | G102: =COUNTIFS(CostLines!$A$2:$A$1055,$A102) | H102: =SUMIFS(CostLines!$L$2:$L$1055,CostLines!$A$2:$A$1055,$A102,CostLines!$I$2:$I$1055,README!$B$6) | I102: =SUMIFS(CostLines!$L$2:$L$1055,CostLines!$A$2:$A$1055,$A102)
A103: TN74AW0645 | B103: Yes | C103: RENT VEHICLE | D103: 20 | E103: TECHNOTEK - GLOVES - I | F103: =IF(G103>0,"Yes","No") | G103: =COUNTIFS(CostLines!$A$2:$A$1055,$A103) | H103: =SUMIFS(CostLines!$L$2:$L$1055,CostLines!$A$2:$A$1055,$A103,CostLines!$I$2:$I$1055,README!$B$6) | I103: =SUMIFS(CostLines!$L$2:$L$1055,CostLines!$A$2:$A$1055,$A103)
A104: TN74AY1634 | B104: Yes | C104: RENT VEHICLE | D104: 20 | E104: GAINUP - GARMENTS - I | F104: =IF(G104>0,"Yes","No") | G104: =COUNTIFS(CostLines!$A$2:$A$1055,$A104) | H104: =SUMIFS(CostLines!$L$2:$L$1055,CostLines!$A$2:$A$1055,$A104,CostLines!$I$2:$I$1055,README!$B$6) | I104: =SUMIFS(CostLines!$L$2:$L$1055,CostLines!$A$2:$A$1055,$A104)
E106: Total | G106: =SUM(G2:G104) | H106: =SUM(H2:H104) | I106: =SUM(I2:I104)
A108: Live fleet from data/erp_live.json (the employee feed). A RENT VEHICLE has no costing line here and a COMPANY VEHICLE always has one — the split is exact. Vehicles marked 'No' in column B are costed but no longer carry employees: retired or non-transport.

Sheet RawSample
A1: Verbatim rows from the feed — exactly as the ERP returns them
A2: Field names and date format are the ERP's, unchanged. Dates arrive as dd-mm-yyyy strings with a 00:00:00 tail.
A4: {"Order_No": "GUP-VEH0009", "Order_Date": "02-07-2024 00:00:00", "Project_Type": "VEHICLE", "Proj_Activity_Name": "FC WORK", "Plan_Entry_No": "546", "Description": "FC WORK", "Testing": "T", "Veh_Name": "TN57AC3636", "Rate": "56950.0000", "Grs_Amount": "56950.00", "Pur_Amount": "56950.00", "Period_Name": "YEARLY", "From_Date": "01-04-2024 00:00:00", "To_Date": "31-03-2025 00:00:00", "Division": "SOCKS", "Employee": "VIVEK B", "Approved_Date": "27-12-2024 00:00:00"}
A5: {"Order_No": "GUP-VEH0011", "Order_Date": "04-07-2024 00:00:00", "Project_Type": "VEHICLE", "Proj_Activity_Name": "ROAD TAX", "Plan_Entry_No": "548", "Description": "ROAD TAX", "Testing": "T", "Veh_Name": "TN57AC3636", "Rate": "24846.0000", "Grs_Amount": "24846.00", "Pur_Amount": "24846.00", "Period_Name": "YEARLY", "From_Date": "01-04-2024 00:00:00", "To_Date": "31-03-2025 00:00:00", "Division": "SOCKS", "Employee": "VIVEK B", "Approved_Date": "04-10-2024 00:00:00"}
A6: {"Order_No": "GUP-VEH0011", "Order_Date": "04-07-2024 00:00:00", "Project_Type": "VEHICLE", "Proj_Activity_Name": "ROAD TAX", "Plan_Entry_No": "548", "Description": "ROAD TAX", "Testing": "T", "Veh_Name": "TN57AC3636", "Rate": "24846.0000", "Grs_Amount": "24846.00", "Pur_Amount": "24846.00", "Period_Name": "YEARLY", "From_Date": "01-04-2024 00:00:00", "To_Date": "31-03-2025 00:00:00", "Division": "SOCKS", "Employee": "VIVEK B", "Approved_Date": "23-12-2024 00:00:00"}
A7: {"Order_No": "GUP-VEH0011", "Order_Date": "04-07-2024 00:00:00", "Project_Type": "VEHICLE", "Proj_Activity_Name": "ROAD TAX", "Plan_Entry_No": "548", "Description": "GREEN TAX", "Testing": "T", "Veh_Name": "TN57AC3636", "Rate": "190.0000", "Grs_Amount": "190.00", "Pur_Amount": "190.00", "Period_Name": "YEARLY", "From_Date": "01-04-2024 00:00:00", "To_Date": "31-03-2025 00:00:00", "Division": "SOCKS", "Employee": "VIVEK B", "Approved_Date": "23-12-2024 00:00:00"}
A8: {"Order_No": "GUP-VEH0011", "Order_Date": "04-07-2024 00:00:00", "Project_Type": "VEHICLE", "Proj_Activity_Name": "ROAD TAX", "Plan_Entry_No": "548", "Description": "GREEN TAX", "Testing": "T", "Veh_Name": "TN57AC3636", "Rate": "190.0000", "Grs_Amount": "190.00", "Pur_Amount": "190.00", "Period_Name": "YEARLY", "From_Date": "01-04-2024 00:00:00", "To_Date": "31-03-2025 00:00:00", "Division": "SOCKS", "Employee": "VIVEK B", "Approved_Date": "04-10-2024 00:00:00"}
A9: {"Order_No": "GUP-VEH0011", "Order_Date": "04-07-2024 00:00:00", "Project_Type": "VEHICLE", "Proj_Activity_Name": "ROAD TAX", "Plan_Entry_No": "548", "Description": "GREEN TAX", "Testing": "T", "Veh_Name": "TN57AC3636", "Rate": "190.0000", "Grs_Amount": "190.00", "Pur_Amount": "190.00", "Period_Name": "YEARLY", "From_Date": "01-04-2024 00:00:00", "To_Date": "31-03-2025 00:00:00", "Division": "SOCKS", "Employee": "VIVEK B", "Approved_Date": "08-07-2024 00:00:00"}
A10: {"Order_No": "GUP-VEH0011", "Order_Date": "04-07-2024 00:00:00", "Project_Type": "VEHICLE", "Proj_Activity_Name": "ROAD TAX", "Plan_Entry_No": "548", "Description": "ROAD TAX", "Testing": "T", "Veh_Name": "TN57AC3636", "Rate": "24846.0000", "Grs_Amount": "24846.00", "Pur_Amount": "24846.00", "Period_Name": "YEARLY", "From_Date": "01-04-2024 00:00:00", "To_Date": "31-03-2025 00:00:00", "Division": "SOCKS", "Employee": "VIVEK B", "Approved_Date": "08-07-2024 00:00:00"}
A11: {"Order_No": "GUP-VEH0010", "Order_Date": "02-07-2024 00:00:00", "Project_Type": "VEHICLE", "Proj_Activity_Name": "RTO EXPENSE", "Plan_Entry_No": "547", "Description": "RTO EXPENSE", "Testing": "T", "Veh_Name": "TN57AC3636", "Rate": "7500.0000", "Grs_Amount": "7500.00", "Pur_Amount": "7500.00", "Period_Name": "YEARLY", "From_Date": "01-04-2024 00:00:00", "To_Date": "31-03-2025 00:00:00", "Division": "SOCKS", "Employee": "VIVEK B", "Approved_Date": "12-12-2024 00:00:00"}
A12: {"Order_No": "GUP-VEH0006", "Order_Date": "30-05-2024 00:00:00", "Project_Type": "VEHICLE", "Proj_Activity_Name": "TYRE", "Plan_Entry_No": "522", "Description": "TYRE", "Testing": "T", "Veh_Name": "TN57AC3636", "Rate": "19200.0000", "Grs_Amount": "19200.00", "Pur_Amount": "19200.00", "Period_Name": "YEARLY", "From_Date": "01-04-2024 00:00:00", "To_Date": "31-03-2025 00:00:00", "Division": "SOCKS", "Employee": "VIVEK B", "Approved_Date": "31-05-2024 00:00:00"}
A13: {"Order_No": "GUP-VEH0013", "Order_Date": "05-07-2024 00:00:00", "Project_Type": "VEHICLE", "Proj_Activity_Name": "VEHICLE INSURANCE", "Plan_Entry_No": "550", "Description": "VEHICLE INSURANCE", "Testing": "T", "Veh_Name": "TN57AC3636", "Rate": "59316.0000", "Grs_Amount": "59316.00", "Pur_Amount": "59316.00", "Period_Name": "YEARLY", "From_Date": "01-04-2024 00:00:00", "To_Date": "31-03-2025 00:00:00", "Division": "SOCKS", "Employee": "VIVEK B", "Approved_Date": "06-12-2024 00:00:00"}
... A15: {"Order_No": "GUP-VEH0014", "Order_Date": "01-04-2025 00:00:00", "Project_Type": "VEHICLE", "Proj_Activity_Name": "ROAD TAX", "Plan_Entry_No": "609", "Description": "GREEN TAX", "Testing": "T", "Veh_Name": "TN57AC3636", "Rate": "190.0000", "Grs_Amount": "190.00", "Pur_Amount": "190.00", "Period_Name": "QUARTER - I", "From_Date": "01-04-2025 00:00:00", "To_Date": "30-06-2025 00:00:00", "Division": "SOCKS", "Employee": "VIVEK B", "Approved_Date": "08-01-2026 00:00:00"}
